Workbook

Sheet Dossier_Projet
A1: Projet MOTK Habitat - colonne vertébrale de l'écosystème LTS
A2: Document lisible par tous : logique métier, rôle des onglets, et articulation Excel -> generate_contacts.js -> server.js -> App React
A4: 1. Objet du système
A5: Le classeur devient la base de référence du parc LTS. Une ligne de logement = un code_acces stable. Les feuilles métier structurent la gestion locative, les ventes, les travaux, les entreprises et les contacts Telegram.
A7: 2. Rôle des onglets
A8: LTS_Parc = référentiel du patrimoine ; Contacts_Activation = personnes et activation Telegram ; Gestion_Locative = dossier courant du locataire ; Ventes = parcours d'accession ; Travaux = demandes et interventions ; Marches / Entreprises_Activation = pilotage prestataires ; Notifications / Historique_Actions = traçabilité ; Pilotage = indicateurs.
A10: 3. Generate_contacts.js
A11: Le script prépare les activations : normalise les téléphones, génère les codes secrets, construit les liens Telegram et prépare les messages d'activation à envoyer aux habitants.
A13: 4. Server.js
A14: Le serveur lit les feuilles Excel, contrôle la cohérence, calcule les alertes et les priorités, gère l'activation Telegram, oriente les demandes, puis journalise les notifications envoyées aux locataires et aux entreprises.
A16: 5. Application React
A17: L'application affiche les LTS, les statuts, les alertes, les ventes, les travaux, les entreprises et les indicateurs de pilotage dans une interface simple pour les agents et la direction.
... A23: Le classeur utilise des référentiels, des listes déroulantes, des colonnes de workflow et des colonnes de calcul. Les agents choisissent, valident, datent et commentent ; les calculs, les blocages et les messages sont automatisés.

Sheet Architecture_Technique
A1: Architecture technique et fonctionnelle
A2: Vue simple du système MOTK Habitat
A3: Composant | B3: Entrées | C3: Traitements | D3: Sorties | E3: Usage
A4: Excel / LTS_Parc | B4: Codes résidence et logement, adresse, vendabilité, diagnostics | C4: Structure de base du patrimoine | D4: Référentiel propre | E4: Base unique de vérité
A5: Contacts_Activation | B5: Noms, téléphones, liens Telegram, code secret | C5: Activation sécurisée, gestion du contact actif | D5: Chat ID, statut d'activation, message d'activation | E5: Relation habitant
A6: Gestion_Locative | B6: Assurance, avis d'impôt, pièce manquante, bail | C6: Contrôle administratif et relances | D6: Alerte gestion, statut dossier | E6: Suivi locatif
A7: Travaux | B7: Demandes, validation agent, attribution entreprise | C7: Workflow demande -> validation -> intervention | D7: Notifications locataire et entreprise | E7: Exécution terrain
A8: Ventes | B8: Demande achat, prix, TAE, SPANC, chèques, notaire | C8: Workflow accession et blocages | D8: Suivi vente, notifications, reste à charge | E8: Pilotage accession
A9: Marches / Entreprises | B9: Marchés, lots, entreprise, mode d'attribution | C9: Orientation vers prestataire marché / hors marché | D9: Activation entreprise et traçabilité | E9: Pilotage prestataires
A10: generate_contacts.js | B10: Contacts_Activation | C10: Normalisation téléphone, code secret, lien Telegram, message | D10: Feuille prête pour campagne d'activation | E10: Préparation opérationnelle
A11: server.js | B11: Toutes les feuilles métiers | C11: Lecture, synchronisation, contrôle, alertes, envoi Telegram | D11: Notifications, historique, dashboard API | E11: Moteur central
A12: App React | B12: API serveur / feuilles consolidées | C12: Visualisation cartographique et métier | D12: Vues agents / direction | E12: Pilotage et supervision

Sheet Parametres
A1: Paramètres du système
A2: Valeurs de base à ajuster avant déploiement
A3: Paramètre | B3: Valeur | C3: Commentaire | D3: Catégorie | E3: Résidences non vendables
A4: TELEGRAM_BOT_USERNAME | B4: motk_notification_bot | C4: Nom du bot Telegram utilisé pour les liens d'activation | D4: Technique | E4: ALAMANDAS
A5: CHEQUE_PRIMO_MIN | B5: 500 | C5: Montant minimal chèque primo-accédant | D5: Vente | E5: SAPOTIS
A6: CHEQUE_PRIMO_MAX | B6: 5000 | C6: Montant maximal chèque primo-accédant | D6: Vente | E6: GRENADINES
A7: CHEQUE_CINOR | B7: 3000 | C7: Montant fixe aide CINOR | D7: Vente | E7: CLOTILDA
A8: TAE_PAR_DEFAUT_VENTE | B8: oui | C8: Tout logement en vente doit avoir un diag TAE | D8: Vente
A9: SPANC_PAR_DEFAUT | B9: non | C9: Par défaut : ajuster logement par logement | D9: Vente
A10: DELAI_RELANCE_JOURS | B10: 7 | C10: Délai conseillé pour relance automatique | D10: Pilotage
A11: TELEGRAM_POLL_INTERVAL_MS | B11: 5000 | C11: Poll Telegram côté serveur | D11: Technique
A12: CHECK_INTERVAL_MS | B12: 90000 | C12: Scan périodique du moteur d'alertes | D12: Technique

Sheet Contacts_Activation
A1: secteur | B1: quartier | C1: code_lts | D1: code_acces | E1: nom_lts | F1: nom | G1: prenom | H1: telephone_principal | I1: telephone_secondaire | J1: telephone_normalise | K1: remarques_contact | L1: email | M1: type_contact | N1: contact_actif | O1: date_entree | P1: date_sortie | Q1: motif_sortie | R1: telegram_chat_id | S1: statut_activation | T1: date_activation | U1: code_secret | V1: secret_utilise | W1: tentatives_activation | X1: activation_bloquee | Y1: motif_blocage | Z1: date_derniere_tentative | AA1: activation_etape | AB1: activation_code_temp | AC1: lien_telegram_start | AD1: message_activation
A2: 1 | B2: Sainte Cloitlde | C2: LTS-001 | D2: LTS-001-001 | E2: ALAMANDAS | F2: RIVIERE | G2: Fabienne | H2: 0692670367 | J2: 0692670367 | M2: locataire | N2: oui | S2: A activer | U2: 1001 | V2: non | W2: 0 | X2: non | AC2: https://t.me/motk_notification_bot?start=LTS-001-001 | AD2: 🏛️ Ville de Saint-Denis Service Habitat – Projet MOTK Bonjour Fabienne RIVIERE Activez vos notifications logement : Lien : https://t.me/motk_notification_bot?start=LTS-001-001 Code secret : 1001 Étapes : 1) Cliquez sur le lien 2) Appuyez sur Start 3) Envoyez votre numéro de téléphone 4) Envoyez votre code secret.
A3: 1 | B3: Sainte Cloitlde | C3: LTS-001 | D3: LTS-001-002 | E3: ALAMANDAS | F3: ARAYE | G3: Evelyne | H3: 0262294396 | I3: 0692085376 | J3: 0262294396 | M3: locataire | N3: oui | S3: A activer | U3: 1002 | V3: non | W3: 0 | X3: non | AC3: https://t.me/motk_notification_bot?start=LTS-001-002 | AD3: 🏛️ Ville de Saint-Denis Service Habitat – Projet MOTK Bonjour Evelyne ARAYE Activez vos notifications logement : Lien : https://t.me/motk_notification_bot?start=LTS-001-002 Code secret : 1002 Étapes : 1) Cliquez sur le lien 2) Appuyez sur Start 3) Envoyez votre numéro de téléphone 4) Envoyez votre code secret.
A4: 1 | B4: Sainte Cloitlde | C4: LTS-001 | D4: LTS-001-003 | E4: ALAMANDAS | F4: ARLANDON | G4: Jean Luc | H4: 0692253329 | I4: 0692373955 | J4: 0692253329 | K4: FREDERICK ARLANDON | M4: locataire | N4: oui | S4: A activer | U4: 1003 | V4: non | W4: 0 | X4: non | AC4: https://t.me/motk_notification_bot?start=LTS-001-003 | AD4: 🏛️ Ville de Saint-Denis Service Habitat – Projet MOTK Bonjour Jean Luc ARLANDON Activez vos notifications logement : Lien : https://t.me/motk_notification_bot?start=LTS-001-003 Code secret : 1003 Étapes : 1) Cliquez sur le lien 2) Appuyez sur Start 3) Envoyez votre numéro de téléphone 4) Envoyez votre code secret.
A5: 1 | B5: Sainte Cloitlde | C5: LTS-001 | D5: LTS-001-004 | E5: ALAMANDAS | F5: CAZAMBO | G5: Jean François | H5: 0693137209 | J5: 0693137209 | M5: locataire | N5: oui | S5: A activer | U5: 1004 | V5: non | W5: 0 | X5: non | AC5: https://t.me/motk_notification_bot?start=LTS-001-004 | AD5: 🏛️ Ville de Saint-Denis Service Habitat – Projet MOTK Bonjour Jean François CAZAMBO Activez vos notifications logement : Lien : https://t.me/motk_notification_bot?start=LTS-001-004 Code secret : 1004 Étapes : 1) Cliquez sur le lien 2) Appuyez sur Start 3) Envoyez votre numéro de téléphone 4) Envoyez votre code secret.
A6: 1 | B6: Sainte Cloitlde | C6: LTS-001 | D6: LTS-001-005 | E6: ALAMANDAS | F6: CHANE LAW | G6: Jimmy | H6: 0692957824 | J6: 0692957824 | M6: locataire | N6: oui | S6: A activer | U6: 1005 | V6: non | W6: 0 | X6: non | AC6: https://t.me/motk_notification_bot?start=LTS-001-005 | AD6: 🏛️ Ville de Saint-Denis Service Habitat – Projet MOTK Bonjour Jimmy CHANE LAW Activez vos notifications logement : Lien : https://t.me/motk_notification_bot?start=LTS-001-005 Code secret : 1005 Étapes : 1) Cliquez sur le lien 2) Appuyez sur Start 3) Envoyez votre numéro de téléphone 4) Envoyez votre code secret.
A7: 1 | B7: Sainte Cloitlde | C7: LTS-001 | D7: LTS-001-006 | E7: ALAMANDAS | F7: METELLUS | G7: Stéphane | H7: 0693044649 | J7: 0693044649 | M7: locataire | N7: oui | S7: A activer | U7: 1006 | V7: non | W7: 0 | X7: non | AC7: https://t.me/motk_notification_bot?start=LTS-001-006 | AD7: 🏛️ Ville de Saint-Denis Service Habitat – Projet MOTK Bonjour Stéphane METELLUS Activez vos notifications logement : Lien : https://t.me/motk_notification_bot?start=LTS-001-006 Code secret : 1006 Étapes : 1) Cliquez sur le lien 2) Appuyez sur Start 3) Envoyez votre numéro de téléphone 4) Envoyez votre code secret.
A8: 1 | B8: Sainte Cloitlde | C8: LTS-001 | D8: LTS-001-007 | E8: ALAMANDAS | F8: FICHORA | G8: Armand | H8: 0262284589 | J8: 0262284589 | M8: locataire | N8: oui | S8: A activer | U8: 1007 | V8: non | W8: 0 | X8: non | AC8: https://t.me/motk_notification_bot?start=LTS-001-007 | AD8: 🏛️ Ville de Saint-Denis Service Habitat – Projet MOTK Bonjour Armand FICHORA Activez vos notifications logement : Lien : https://t.me/motk_notification_bot?start=LTS-001-007 Code secret : 1007 Étapes : 1) Cliquez sur le lien 2) Appuyez sur Start 3) Envoyez votre numéro de téléphone 4) Envoyez votre code secret.
A9: 1 | B9: Sainte Cloitlde | C9: LTS-001 | D9: LTS-001-008 | E9: ALAMANDAS | F9: LOUISE | G9: Marie | H9: 0693051870 | J9: 0693051870 | K9: emmanuelle Boyer | M9: locataire | N9: oui | S9: A activer | U9: 1008 | V9: non | W9: 0 | X9: non | AC9: https://t.me/motk_notification_bot?start=LTS-001-008 | AD9: 🏛️ Ville de Saint-Denis Service Habitat – Projet MOTK Bonjour Marie LOUISE Activez vos notifications logement : Lien : https://t.me/motk_notification_bot?start=LTS-001-008 Code secret : 1008 Étapes : 1) Cliquez sur le lien 2) Appuyez sur Start 3) Envoyez votre numéro de téléphone 4) Envoyez votre code secret.
A10: 1 | B10: Sainte Cloitlde | C10: LTS-001 | D10: LTS-001-009 | E10: ALAMANDAS | F10: GALTIER | G10: Rita Marie | H10: 0262293081 | I10: 0692898654 | J10: 0262293081 | K10: fils | M10: locataire | N10: oui | S10: A activer | U10: 1009 | V10: non | W10: 0 | X10: non | AC10: https://t.me/motk_notification_bot?start=LTS-001-009 | AD10: 🏛️ Ville de Saint-Denis Service Habitat – Projet MOTK Bonjour Rita Marie GALTIER Activez vos notifications logement : Lien : https://t.me/motk_notification_bot?start=LTS-001-009 Code secret : 1009 Étapes : 1) Cliquez sur le lien 2) Appuyez sur Start 3) Envoyez votre numéro de téléphone 4) Envoyez votre code secret.
A11: 1 | B11: Sainte Cloitlde | C11: LTS-001 | D11: LTS-001-010 | E11: ALAMANDAS | F11: GERVILLE | G11: Rose May | H11: 0692464983 | J11: 0692464983 | M11: locataire | N11: oui | S11: A activer | U11: 1010 | V11: non | W11: 0 | X11: non | AC11: https://t.me/motk_notification_bot?start=LTS-001-010 | AD11: 🏛️ Ville de Saint-Denis Service Habitat – Projet MOTK Bonjour Rose May GERVILLE Activez vos notifications logement : Lien : https://t.me/motk_notification_bot?start=LTS-001-010 Code secret : 1010 Étapes : 1) Cliquez sur le lien 2) Appuyez sur Start 3) Envoyez votre numéro de téléphone 4) Envoyez votre code secret.
A12: 1 | B12: Sainte Cloitlde | C12: LTS-001 | D12: LTS-001-011 | E12: ALAMANDAS | F12: GRENIER | G12: Ruffine Marie | H12: 0262503633 | I12: 0692190983 | J12: 0262503633 | K12: OU | M12: locataire | N12: oui | S12: A activer | U12: 1011 | V12: non | W12: 0 | X12: non | AC12: https://t.me/motk_notification_bot?start=LTS-001-011 | AD12: 🏛️ Ville de Saint-Denis Service Habitat – Projet MOTK Bonjour Ruffine Marie GRENIER Activez vos notifications logement : Lien : https://t.me/motk_notification_bot?start=LTS-001-011 Code secret : 1011 Étapes : 1) Cliquez sur le lien 2) Appuyez sur Start 3) Envoyez votre numéro de téléphone 4) Envoyez votre code secret.
A13: 1 | B13: Sainte Cloitlde | C13: LTS-001 | D13: LTS-001-012 | E13: ALAMANDAS | F13: SAUTRON | G13: Willy David | H13: 0693634302 | I13: 0692084218 / 0692494271 | J13: 0693634302 | K13: Mme SAUTRON | M13: locataire | N13: oui | S13: A activer | U13: 1012 | V13: non | W13: 0 | X13: non | AC13: https://t.me/motk_notification_bot?start=LTS-001-012 | AD13: 🏛️ Ville de Saint-Denis Service Habitat – Projet MOTK Bonjour Willy David SAUTRON Activez vos notifications logement : Lien : https://t.me/motk_notification_bot?start=LTS-001-012 Code secret : 1012 Étapes : 1) Cliquez sur le lien 2) Appuyez sur Start 3) Envoyez votre numéro de téléphone 4) Envoyez votre code secret.
A14: 1 | B14: Sainte Cloitlde | C14: LTS-001 | D14: LTS-001-013 | E14: ALAMANDAS | F14: LAFABLE | G14: Philippe | H14: 0692467006 | J14: 0692467006 | M14: locataire | N14: oui | S14: A activer | U14: 1013 | V14: non | W14: 0 | X14: non | AC14: https://t.me/motk_notification_bot?start=LTS-001-013 | AD14: 🏛️ Ville de Saint-Denis Service Habitat – Projet MOTK Bonjour Philippe LAFABLE Activez vos notifications logement : Lien : https://t.me/motk_notification_bot?start=LTS-001-013 Code secret : 1013 Étapes : 1) Cliquez sur le lien 2) Appuyez sur Start 3) Envoyez votre numéro de téléphone 4) Envoyez votre code secret.
A15: 1 | B15: Sainte Cloitlde | C15: LTS-001 | D15: LTS-001-014 | E15: ALAMANDAS | F15: LAURENT | G15: Jean René | H15: 0262289120 | J15: 0262289120 | M15: locataire | N15: oui | S15: A activer | U15: 1014 | V15: non | W15: 0 | X15: non | AC15: https://t.me/motk_notification_bot?start=LTS-001-014 | AD15: 🏛️ Ville de Saint-Denis Service Habitat – Projet MOTK Bonjour Jean René LAURENT Activez vos notifications logement : Lien : https://t.me/motk_notification_bot?start=LTS-001-014 Code secret : 1014 Étapes : 1) Cliquez sur le lien 2) Appuyez sur Start 3) Envoyez votre numéro de téléphone 4) Envoyez votre code secret.
A16: 1 | B16: Sainte Cloitlde | C16: LTS-001 | D16: LTS-001-015 | E16: ALAMANDAS | F16: LAURENT | G16: Jean Bernard | H16: 0692916258 | J16: 0692916258 | M16: locataire | N16: oui | S16: A activer | U16: 1015 | V16: non | W16: 0 | X16: non | AC16: https://t.me/motk_notification_bot?start=LTS-001-015 | AD16: 🏛️ Ville de Saint-Denis Service Habitat – Projet MOTK Bonjour Jean Bernard LAURENT Activez vos notifications logement : Lien : https://t.me/motk_notification_bot?start=LTS-001-015 Code secret : 1015 Étapes : 1) Cliquez sur le lien 2) Appuyez sur Start 3) Envoyez votre numéro de téléphone 4) Envoyez votre code secret.
A17: 1 | B17: Sainte Cloitlde | C17: LTS-001 | D17: LTS-001-016 | E17: ALAMANDAS | F17: MARKA | G17: Claude | H17: 0692906779 | J17: 0692906779 | M17: locataire | N17: oui | S17: A activer | U17: 1016 | V17: non | W17: 0 | X17: non | AC17: https://t.me/motk_notification_bot?start=LTS-001-016 | AD17: 🏛️ Ville de Saint-Denis Service Habitat – Projet MOTK Bonjour Claude MARKA Activez vos notifications logement : Lien : https://t.me/motk_notification_bot?start=LTS-001-016 Code secret : 1016 Étapes : 1) Cliquez sur le lien 2) Appuyez sur Start 3) Envoyez votre numéro de téléphone 4) Envoyez votre code secret.
A18: 1 | B18: Sainte Cloitlde | C18: LTS-001 | D18: LTS-001-017 | E18: ALAMANDAS | F18: MOUTOUSSAMY | G18: Jacques Antoine | H18: 0692807626 | I18: 0262190122 | J18: 0692807626 | M18: locataire | N18: oui | S18: A activer | U18: 1017 | V18: non | W18: 0 | X18: non | AC18: https://t.me/motk_notification_bot?start=LTS-001-017 | AD18: 🏛️ Ville de Saint-Denis Service Habitat – Projet MOTK Bonjour Jacques Antoine MOUTOUSSAMY Activez vos notifications logement : Lien : https://t.me/motk_notification_bot?start=LTS-001-017 Code secret : 1017 Étapes : 1) Cliquez sur le lien 2) Appuyez sur Start 3) Envoyez votre numéro de téléphone 4) Envoyez votre code secret.
A19: 1 | B19: Sainte Cloitlde | C19: LTS-001 | D19: LTS-001-018 | E19: ALAMANDAS | F19: PAYET | G19: Josiane Aline | H19: 0262504956 | I19: 0692677087 | J19: 0262504956 | M19: locataire | N19: oui | S19: A activer | U19: 1018 | V19: non | W19: 0 | X19: non | AC19: https://t.me/motk_notification_bot?start=LTS-001-018 | AD19: 🏛️ Ville de Saint-Denis Service Habitat – Projet MOTK Bonjour Josiane Aline PAYET Activez vos notifications logement : Lien : https://t.me/motk_notification_bot?start=LTS-001-018 Code secret : 1018 Étapes : 1) Cliquez sur le lien 2) Appuyez sur Start 3) Envoyez votre numéro de téléphone 4) Envoyez votre code secret.
A20: 1 | B20: Sainte Cloitlde | C20: LTS-001 | D20: LTS-001-019 | E20: ALAMANDAS | F20: ROBERT | G20: Jean Patrick | H20: 0692668371 | I20: 0692916112 | J20: 0692668371 | M20: locataire | N20: oui | S20: A activer | U20: 1019 | V20: non | W20: 0 | X20: non | AC20: https://t.me/motk_notification_bot?start=LTS-001-019 | AD20: 🏛️ Ville de Saint-Denis Service Habitat – Projet MOTK Bonjour Jean Patrick ROBERT Activez vos notifications logement : Lien : https://t.me/motk_notification_bot?start=LTS-001-019 Code secret : 1019 Étapes : 1) Cliquez sur le lien 2) Appuyez sur Start 3) Envoyez votre numéro de téléphone 4) Envoyez votre code secret.
A21: 1 | B21: Sainte Cloitlde | C21: LTS-001 | D21: LTS-001-020 | E21: ALAMANDAS | F21: REFANE | G21: Marie Virginie | H21: 0692860902 | J21: 0692860902 | M21: locataire | N21: oui | S21: A activer | U21: 1020 | V21: non | W21: 0 | X21: non | AC21: https://t.me/motk_notification_bot?start=LTS-001-020 | AD21: 🏛️ Ville de Saint-Denis Service Habitat – Projet MOTK Bonjour Marie Virginie REFANE Activez vos notifications logement : Lien : https://t.me/motk_notification_bot?start=LTS-001-020 Code secret : 1020 Étapes : 1) Cliquez sur le lien 2) Appuyez sur Start 3) Envoyez votre numéro de téléphone 4) Envoyez votre code secret.
A22: 1 | B22: Sainte Cloitlde | C22: LTS-001 | D22: LTS-001-021 | E22: ALAMANDAS | F22: SINAPAYEN SINAMALE | G22: Henriette | H22: 0693860123 | I22: 0692143045 | J22: 0693860123 | K22: petit fils | M22: locataire | N22: oui | S22: A activer | U22: 1021 | V22: non | W22: 0 | X22: non | AC22: https://t.me/motk_notification_bot?start=LTS-001-021 | AD22: 🏛️ Ville de Saint-Denis Service Habitat – Projet MOTK Bonjour Henriette SINAPAYEN SINAMALE Activez vos notifications logement : Lien : https://t.me/motk_notification_bot?start=LTS-001-021 Code secret : 1021 Étapes : 1) Cliquez sur le lien 2) Appuyez sur Start 3) Envoyez votre numéro de téléphone 4) Envoyez votre code secret.
A23: 1 | B23: Sainte Cloitlde | C23: LTS-001 | D23: LTS-001-022 | E23: ALAMANDAS | F23: MARKA | G23: GREGORY | H23: 0692843883 | J23: 0692843883 | M23: locataire | N23: oui | S23: A activer | U23: 1022 | V23: non | W23: 0 | X23: non | AC23: https://t.me/motk_notification_bot?start=LTS-001-022 | AD23: 🏛️ Ville de Saint-Denis Service Habitat – Projet MOTK Bonjour GREGORY MARKA Activez vos notifications logement : Lien : https://t.me/motk_notification_bot?start=LTS-001-022 Code secret : 1022 Étapes : 1) Cliquez sur le lien 2) Appuyez sur Start 3) Envoyez votre numéro de téléphone 4) Envoyez votre code secret.
A24: 1 | B24: Sainte Cloitlde | C24: LTS-001 | D24: LTS-001-023 | E24: ALAMANDAS | F24: TECHER | G24: Jean Fabrice | H24: 0693546553 | J24: 0693546553 | K24: GALAOR SQUATEUR | M24: locataire | N24: oui | S24: A activer | U24: 1023 | V24: non | W24: 0 | X24: non | AC24: https://t.me/motk_notification_bot?start=LTS-001-023 | AD24: 🏛️ Ville de Saint-Denis Service Habitat – Projet MOTK Bonjour Jean Fabrice TECHER Activez vos notifications logement : Lien : https://t.me/motk_notification_bot?start=LTS-001-023 Code secret : 1023 Étapes : 1) Cliquez sur le lien 2) Appuyez sur Start 3) Envoyez votre numéro de téléphone 4) Envoyez votre code secret.
A25: 1 | B25: Sainte Cloitlde | C25: LTS-001 | D25: LTS-001-024 | E25: ALAMANDAS | F25: TECHER | G25: Joseph Francis | H25: 0692487884 | J25: 0692487884 | M25: locataire | N25: oui | S25: A activer | U25: 1024 | V25: non | W25: 0 | X25: non | AC25: https://t.me/motk_notification_bot?start=LTS-001-024 | AD25: 🏛️ Ville de Saint-Denis Service Habitat – Projet MOTK Bonjour Joseph Francis TECHER Activez vos notifications logement : Lien : https://t.me/motk_notification_bot?start=LTS-001-024 Code secret : 1024 Étapes : 1) Cliquez sur le lien 2) Appuyez sur Start 3) Envoyez votre numéro de téléphone 4) Envoyez votre code secret.
A26: 1 | B26: Sainte Cloitlde | C26: LTS-001 | D26: LTS-001-025 | E26: ALAMANDAS | F26: VIRAPIN CAROUMBIN | G26: Marie-Josée | H26: 0692689202 | J26: 0692689202 | M26: locataire | N26: oui | S26: A activer | U26: 1025 | V26: non | W26: 0 | X26: non | AC26: https://t.me/motk_notification_bot?start=LTS-001-025 | AD26: 🏛️ Ville de Saint-Denis Service Habitat – Projet MOTK Bonjour Marie-Josée VIRAPIN CAROUMBIN Activez vos notifications logement : Lien : https://t.me/motk_notification_bot?start=LTS-001-025 Code secret : 1025 Étapes : 1) Cliquez sur le lien 2) Appuyez sur Start 3) Envoyez votre numéro de téléphone 4) Envoyez votre code secret.
A27: 1 | B27: Sainte Cloitlde | C27: LTS-001 | D27: LTS-001-026 | E27: ALAMANDAS | F27: CORRE | G27: Laurianne Emmanuelle | H27: 0692842718 | I27: 0692341364 | J27: 0692842718 | K27: PÈRE | MERE | M27: locataire | N27: oui | S27: A activer | U27: 1026 | V27: non | W27: 0 | X27: non | AC27: https://t.me/motk_notification_bot?start=LTS-001-026 | AD27: 🏛️ Ville de Saint-Denis Service Habitat – Projet MOTK Bonjour Laurianne Emmanuelle CORRE Activez vos notifications logement : Lien : https://t.me/motk_notification_bot?start=LTS-001-026 Code secret : 1026 Étapes : 1) Cliquez sur le lien 2) Appuyez sur Start 3) Envoyez votre numéro de téléphone 4) Envoyez votre code secret.
A28: 1 | B28: Sainte Cloitlde | C28: LTS-001 | D28: LTS-001-027 | E28: ALAMANDAS | F28: SEVERIN | G28: André Claude | H28: 0692922924 | I28: 0693283029 / 0692661125 | J28: 0692922924 | K28: sa fille | severin | M28: locataire | N28: oui | S28: A activer | U28: 1027 | V28: non | W28: 0 | X28: non | AC28: https://t.me/motk_notification_bot?start=LTS-001-027 | AD28: 🏛️ Ville de Saint-Denis Service Habitat – Projet MOTK Bonjour André Claude SEVERIN Activez vos notifications logement : Lien : https://t.me/motk_notification_bot?start=LTS-001-027 Code secret : 1027 Étapes : 1) Cliquez sur le lien 2) Appuyez sur Start 3) Envoyez votre numéro de téléphone 4) Envoyez votre code secret.
A29: 1 | B29: Sainte Cloitlde | C29: LTS-001 | D29: LTS-001-028 | E29: ALAMANDAS | F29: LAURENT | G29: Thomas | H29: 0692139045 | J29: 0692139045 | M29: locataire | N29: oui | S29: A activer | U29: 1028 | V29: non | W29: 0 | X29: non | AC29: https://t.me/motk_notification_bot?start=LTS-001-028 | AD29: 🏛️ Ville de Saint-Denis Service Habitat – Projet MOTK Bonjour Thomas LAURENT Activez vos notifications logement : Lien : https://t.me/motk_notification_bot?start=LTS-001-028 Code secret : 1028 Étapes : 1) Cliquez sur le lien 2) Appuyez sur Start 3) Envoyez votre numéro de téléphone 4) Envoyez votre code secret.
A30: 1 | B30: Sainte Cloitlde | C30: LTS-001 | D30: LTS-001-029 | E30: ALAMANDAS | F30: LAURENT | G30: Jean Alain | H30: 0692590826 | I30: 0692946258 / 0693823305 | J30: 0692590826 | M30: locataire | N30: oui | S30: A activer | U30: 1029 | V30: non | W30: 0 | X30: non | AC30: https://t.me/motk_notification_bot?start=LTS-001-029 | AD30: 🏛️ Ville de Saint-Denis Service Habitat – Projet MOTK Bonjour Jean Alain LAURENT Activez vos notifications logement : Lien : https://t.me/motk_notification_bot?start=LTS-001-029 Code secret : 1029 Étapes : 1) Cliquez sur le lien 2) Appuyez sur Start 3) Envoyez votre numéro de téléphone 4) Envoyez votre code secret.
A31: 1 | B31: Sainte Cloitlde | C31: LTS-001 | D31: LTS-001-030 | E31: ALAMANDAS | F31: FIBAC | G31: Marie Hélène | H31: 0692660767 | J31: 0692660767 | M31: locataire | N31: oui | S31: A activer | U31: 1030 | V31: non | W31: 0 | X31: non | AC31: https://t.me/motk_notification_bot?start=LTS-001-030 | AD31: 🏛️ Ville de Saint-Denis Service Habitat – Projet MOTK Bonjour Marie Hélène FIBAC Activez vos notifications logement : Lien : https://t.me/motk_notification_bot?start=LTS-001-030 Code secret : 1030 Étapes : 1) Cliquez sur le lien 2) Appuyez sur Start 3) Envoyez votre numéro de téléphone 4) Envoyez votre code secret.
A32: 1 | B32: Prima | C32: LTS-002 | D32: LTS-002-001 | E32: ATTES | F32: ANDRIANA | G32: Marie Françoise | H32: 0693525546 | I32: 0692547291 | J32: 0693525546 | K32: PIERRE ALFLECHE | M32: locataire | N32: oui | S32: A activer | U32: 1031 | V32: non | W32: 0 | X32: non | AC32: https://t.me/motk_notification_bot?start=LTS-002-001 | AD32: 🏛️ Ville de Saint-Denis Service Habitat – Projet MOTK Bonjour Marie Françoise ANDRIANA Activez vos notifications logement : Lien : https://t.me/motk_notification_bot?start=LTS-002-001 Code secret : 1031 Étapes : 1) Cliquez sur le lien 2) Appuyez sur Start 3) Envoyez votre numéro de téléphone 4) Envoyez votre code secret.
A33: 1 | B33: Prima | C33: LTS-002 | D33: LTS-002-002 | E33: ATTES | F33: HIVANHOE | G33: Jean Patrick | H33: 0262902947 | J33: 0262902947 | K33: UDAF | M33: locataire | N33: oui | S33: A activer | U33: 1032 | V33: non | W33: 0 | X33: non | AC33: https://t.me/motk_notification_bot?start=LTS-002-002 | AD33: 🏛️ Ville de Saint-Denis Service Habitat – Projet MOTK Bonjour Jean Patrick HIVANHOE Activez vos notifications logement : Lien : https://t.me/motk_notification_bot?start=LTS-002-002 Code secret : 1032 Étapes : 1) Cliquez sur le lien 2) Appuyez sur Start 3) Envoyez votre numéro de téléphone 4) Envoyez votre code secret.
A34: 1 | B34: Prima | C34: LTS-002 | D34: LTS-002-003 | E34: ATTES | F34: MASSEAUX | G34: Clarisse Alida | H34: 0692260455 | J34: 0692260455 | M34: locataire | N34: oui | S34: A activer | U34: 1033 | V34: non | W34: 0 | X34: non | AC34: https://t.me/motk_notification_bot?start=LTS-002-003 | AD34: 🏛️ Ville de Saint-Denis Service Habitat – Projet MOTK Bonjour Clarisse Alida MASSEAUX Activez vos notifications logement : Lien : https://t.me/motk_notification_bot?start=LTS-002-003 Code secret : 1033 Étapes : 1) Cliquez sur le lien 2) Appuyez sur Start 3) Envoyez votre numéro de téléphone 4) Envoyez votre code secret.
A35: 3 | B35: Le Brulé | C35: LTS-003 | D35: LTS-003-001 | E35: AZALEES | F35: IMAHO | G35: Emmanuelle Anne Gaëlle | H35: 0692631658 | I35: 0693111634 | J35: 0692631658 | K35: NUM W | M35: locataire | N35: oui | S35: A activer | U35: 1034 | V35: non | W35: 0 | X35: non | AC35: https://t.me/motk_notification_bot?start=LTS-003-001 | AD35: 🏛️ Ville de Saint-Denis Service Habitat – Projet MOTK Bonjour Emmanuelle Anne Gaëlle IMAHO Activez vos notifications logement : Lien : https://t.me/motk_notification_bot?start=LTS-003-001 Code secret : 1034 Étapes : 1) Cliquez sur le lien 2) Appuyez sur Start 3) Envoyez votre numéro de téléphone 4) Envoyez votre code secret.
A36: 3 | B36: Le Brulé | C36: LTS-003 | D36: LTS-003-002 | E36: AZALEES | F36: IFIANTEPIA | G36: occupé en attente decision | H36: 0692229197 | J36: 0692229197 | M36: locataire | N36: oui | S36: A activer | U36: 1035 | V36: non | W36: 0 | X36: non | AC36: https://t.me/motk_notification_bot?start=LTS-003-002 | AD36: 🏛️ Ville de Saint-Denis Service Habitat – Projet MOTK Bonjour occupé en attente decision IFIANTEPIA Activez vos notifications logement : Lien : https://t.me/motk_notification_bot?start=LTS-003-002 Code secret : 1035 Étapes : 1) Cliquez sur le lien 2) Appuyez sur Start 3) Envoyez votre numéro de téléphone 4) Envoyez votre code secret.
A37: 3 | B37: Le Brulé | C37: LTS-003 | D37: LTS-003-003 | E37: AZALEES | F37: THOMAS NÉE TURPIN | G37: Marie Micheline | H37: 0692587339 | J37: 0692587339 | M37: locataire | N37: oui | S37: A activer | U37: 1036 | V37: non | W37: 0 | X37: non | AC37: https://t.me/motk_notification_bot?start=LTS-003-003 | AD37: 🏛️ Ville de Saint-Denis Service Habitat – Projet MOTK Bonjour Marie Micheline THOMAS NÉE TURPIN Activez vos notifications logement : Lien : https://t.me/motk_notification_bot?start=LTS-003-003 Code secret : 1036 Étapes : 1) Cliquez sur le lien 2) Appuyez sur Start 3) Envoyez votre numéro de téléphone 4) Envoyez votre code secret.
A38: 3 | B38: Le Brulé | C38: LTS-003 | D38: LTS-003-004 | E38: AZALEES | F38: POLEYA | G38: Joachim | H38: 0692743656 | J38: 0692743656 | M38: locataire | N38: oui | S38: A activer | U38: 1037 | V38: non | W38: 0 | X38: non | AC38: https://t.me/motk_notification_bot?start=LTS-003-004 | AD38: 🏛️ Ville de Saint-Denis Service Habitat – Projet MOTK Bonjour Joachim POLEYA Activez vos notifications logement : Lien : https://t.me/motk_notification_bot?start=LTS-003-004 Code secret : 1037 Étapes : 1) Cliquez sur le lien 2) Appuyez sur Start 3) Envoyez votre numéro de téléphone 4) Envoyez votre code secret.
A39: 2 | B39: Marcadet | C39: LTS-004 | D39: LTS-004-001 | E39: BARBADINES | F39: ABDALAH BEDANI | G39: Marie Thérèse | H39: 0692128814 | J39: 0692128814 | M39: locataire | N39: oui | S39: A activer | U39: 1038 | V39: non | W39: 0 | X39: non | AC39: https://t.me/motk_notification_bot?start=LTS-004-001 | AD39: 🏛️ Ville de Saint-Denis Service Habitat – Projet MOTK Bonjour Marie Thérèse ABDALAH BEDANI Activez vos notifications logement : Lien : https://t.me/motk_notification_bot?start=LTS-004-001 Code secret : 1038 Étapes : 1) Cliquez sur le lien 2) Appuyez sur Start 3) Envoyez votre numéro de téléphone 4) Envoyez votre code secret.
A40: 2 | B40: Marcadet | C40: LTS-004 | D40: LTS-004-002 | E40: BARBADINES | F40: MAILLOT | H40: 0692209721 | J40: 0692209721 | M40: locataire | N40: oui | S40: A activer | U40: 1039 | V40: non | W40: 0 | X40: non | AC40: https://t.me/motk_notification_bot?start=LTS-004-002 | AD40: 🏛️ Ville de Saint-Denis Service Habitat – Projet MOTK Bonjour MAILLOT Activez vos notifications logement : Lien : https://t.me/motk_notification_bot?start=LTS-004-002 Code secret : 1039 Étapes : 1) Cliquez sur le lien 2) Appuyez sur Start 3) Envoyez votre numéro de téléphone 4) Envoyez votre code secret.
A41: 2 | B41: Marcadet | C41: LTS-004 | D41: LTS-004-003 | E41: BARBADINES | F41: CARPIN VELLEYEN | G41: Maximin | H41: 0692353423 | I41: 0692326054 / 0692362257 | J41: 0692353423 | K41: VINCENT 61 44 | M41: locataire | N41: oui | S41: A activer | U41: 1040 | V41: non | W41: 0 | X41: non | AC41: https://t.me/motk_notification_bot?start=LTS-004-003 | AD41: 🏛️ Ville de Saint-Denis Service Habitat – Projet MOTK Bonjour Maximin CARPIN VELLEYEN Activez vos notifications logement : Lien : https://t.me/motk_notification_bot?start=LTS-004-003 Code secret : 1040 Étapes : 1) Cliquez sur le lien 2) Appuyez sur Start 3) Envoyez votre numéro de téléphone 4) Envoyez votre code secret.
A42: 2 | B42: Marcadet | C42: LTS-004 | D42: LTS-004-004 | E42: BARBADINES | F42: CLAIN | G42: Christian Daniel | H42: 0692102185 | J42: 0692102185 | M42: locataire | N42: oui | S42: A activer | U42: 1041 | V42: non | W42: 0 | X42: non | AC42: https://t.me/motk_notification_bot?start=LTS-004-004 | AD42: 🏛️ Ville de Saint-Denis Service Habitat – Projet MOTK Bonjour Christian Daniel CLAIN Activez vos notifications logement : Lien : https://t.me/motk_notification_bot?start=LTS-004-004 Code secret : 1041 Étapes : 1) Cliquez sur le lien 2) Appuyez sur Start 3) Envoyez votre numéro de téléphone 4) Envoyez votre code secret.
A43: 2 | B43: Marcadet | C43: LTS-004 | D43: LTS-004-005 | E43: BARBADINES | F43: ELEONORE | G43: Yves Joseph | H43: 0692517903 | J43: 0692517903 | M43: locataire | N43: oui | S43: A activer | U43: 1042 | V43: non | W43: 0 | X43: non | AC43: https://t.me/motk_notification_bot?start=LTS-004-005 | AD43: 🏛️ Ville de Saint-Denis Service Habitat – Projet MOTK Bonjour Yves Joseph ELEONORE Activez vos notifications logement : Lien : https://t.me/motk_notification_bot?start=LTS-004-005 Code secret : 1042 Étapes : 1) Cliquez sur le lien 2) Appuyez sur Start 3) Envoyez votre numéro de téléphone 4) Envoyez votre code secret.
A44: 2 | B44: Marcadet | C44: LTS-004 | D44: LTS-004-006 | E44: BARBADINES | F44: ERINACINT | G44: Marie Régine | M44: locataire | N44: oui | S44: A activer | U44: 1043 | V44: non | W44: 0 | X44: non | AC44: https://t.me/motk_notification_bot?start=LTS-004-006 | AD44: 🏛️ Ville de Saint-Denis Service Habitat – Projet MOTK Bonjour Marie Régine ERINACINT Activez vos notifications logement : Lien : https://t.me/motk_notification_bot?start=LTS-004-006 Code secret : 1043 Étapes : 1) Cliquez sur le lien 2) Appuyez sur Start 3) Envoyez votre numéro de téléphone 4) Envoyez votre code secret.
A45: 2 | B45: Marcadet | C45: LTS-004 | D45: LTS-004-007 | E45: BARBADINES | F45: ESPARON | G45: Marie Rose Andrée | H45: 0262418046 | J45: 0262418046 | M45: locataire | N45: oui | S45: A activer | U45: 1044 | V45: non | W45: 0 | X45: non | AC45: https://t.me/motk_notification_bot?start=LTS-004-007 | AD45: 🏛️ Ville de Saint-Denis Service Habitat – Projet MOTK Bonjour Marie Rose Andrée ESPARON Activez vos notifications logement : Lien : https://t.me/motk_notification_bot?start=LTS-004-007 Code secret : 1044 Étapes : 1) Cliquez sur le lien 2) Appuyez sur Start 3) Envoyez votre numéro de téléphone 4) Envoyez votre code secret.
A46: 2 | B46: Marcadet | C46: LTS-004 | D46: LTS-004-008 | E46: BARBADINES | F46: GRONDIN | G46: Joseph Jean Yves | H46: 0693945329 | I46: 0692769137 | J46: 0693945329 | K46: LA FILLE | M46: locataire | N46: oui | S46: A activer | U46: 1045 | V46: non | W46: 0 | X46: non | AC46: https://t.me/motk_notification_bot?start=LTS-004-008 | AD46: 🏛️ Ville de Saint-Denis Service Habitat – Projet MOTK Bonjour Joseph Jean Yves GRONDIN Activez vos notifications logement : Lien : https://t.me/motk_notification_bot?start=LTS-004-008 Code secret : 1045 Étapes : 1) Cliquez sur le lien 2) Appuyez sur Start 3) Envoyez votre numéro de téléphone 4) Envoyez votre code secret.
A47: 2 | B47: Marcadet | C47: LTS-004 | D47: LTS-004-009 | E47: BARBADINES | F47: IBRAHIM | G47: Yousouf | H47: 0693850799 | I47: 0262415521 | J47: 0693850799 | K47: LA FILLE FIXE | M47: locataire | N47: oui | S47: A activer | U47: 1046 | V47: non | W47: 0 | X47: non | AC47: https://t.me/motk_notification_bot?start=LTS-004-009 | AD47: 🏛️ Ville de Saint-Denis Service Habitat – Projet MOTK Bonjour Yousouf IBRAHIM Activez vos notifications logement : Lien : https://t.me/motk_notification_bot?start=LTS-004-009 Code secret : 1046 Étapes : 1) Cliquez sur le lien 2) Appuyez sur Start 3) Envoyez votre numéro de téléphone 4) Envoyez votre code secret.
A48: 2 | B48: Marcadet | C48: LTS-004 | D48: LTS-004-010 | E48: BARBADINES | F48: JOVIEN | G48: Marie Denise | H48: 0692218923 | J48: 0692218923 | M48: locataire | N48: oui | S48: A activer | U48: 1047 | V48: non | W48: 0 | X48: non | AC48: https://t.me/motk_notification_bot?start=LTS-004-010 | AD48: 🏛️ Ville de Saint-Denis Service Habitat – Projet MOTK Bonjour Marie Denise JOVIEN Activez vos notifications logement : Lien : https://t.me/motk_notification_bot?start=LTS-004-010 Code secret : 1047 Étapes : 1) Cliquez sur le lien 2) Appuyez sur Start 3) Envoyez votre numéro de téléphone 4) Envoyez votre code secret.
A49: 2 | B49: Marcadet | C49: LTS-004 | D49: LTS-004-011 | E49: BARBADINES | F49: KAVO | G49: Marie Françoise | H49: 0692754305 | J49: 0692754305 | M49: locataire | N49: oui | S49: A activer | U49: 1048 | V49: non | W49: 0 | X49: non | AC49: https://t.me/motk_notification_bot?start=LTS-004-011 | AD49: 🏛️ Ville de Saint-Denis Service Habitat – Projet MOTK Bonjour Marie Françoise KAVO Activez vos notifications logement : Lien : https://t.me/motk_notification_bot?start=LTS-004-011 Code secret : 1048 Étapes : 1) Cliquez sur le lien 2) Appuyez sur Start 3) Envoyez votre numéro de téléphone 4) Envoyez votre code secret.
A50: 2 | B50: Marcadet | C50: LTS-004 | D50: LTS-004-012 | E50: BARBADINES | F50: LAVAL | G50: Yvette Marie Céline | H50: 0693017032 | I50: 0692934231 | J50: 0693017032 | K50: Jenifer | M50: locataire | N50: oui | S50: A activer | U50: 1049 | V50: non | W50: 0 | X50: non | AC50: https://t.me/motk_notification_bot?start=LTS-004-012 | AD50: 🏛️ Ville de Saint-Denis Service Habitat – Projet MOTK Bonjour Yvette Marie Céline LAVAL Activez vos notifications logement : Lien : https://t.me/motk_notification_bot?start=LTS-004-012 Code secret : 1049 Étapes : 1) Cliquez sur le lien 2) Appuyez sur Start 3) Envoyez votre numéro de téléphone 4) Envoyez votre code secret.
A51: 2 | B51: Marcadet | C51: LTS-004 | D51: LTS-004-013 | E51: BARBADINES | F51: MADJINDA | G51: Halima | H51: 0693206157 | J51: 0693206157 | M51: locataire | N51: oui | S51: A activer | U51: 1050 | V51: non | W51: 0 | X51: non | AC51: https://t.me/motk_notification_bot?start=LTS-004-013 | AD51: 🏛️ Ville de Saint-Denis Service Habitat – Projet MOTK Bonjour Halima MADJINDA Activez vos notifications logement : Lien : https://t.me/motk_notification_bot?start=LTS-004-013 Code secret : 1050 Étapes : 1) Cliquez sur le lien 2) Appuyez sur Start 3) Envoyez votre numéro de téléphone 4) Envoyez votre code secret.
A52: 2 | B52: Marcadet | C52: LTS-004 | D52: LTS-004-014 | E52: BARBADINES | F52: MARKA | G52: Marie Mélanie | M52: locataire | N52: oui | S52: A activer | U52: 1051 | V52: non | W52: 0 | X52: non | AC52: https://t.me/motk_notification_bot?start=LTS-004-014 | AD52: 🏛️ Ville de Saint-Denis Service Habitat – Projet MOTK Bonjour Marie Mélanie MARKA Activez vos notifications logement : Lien : https://t.me/motk_notification_bot?start=LTS-004-014 Code secret : 1051 Étapes : 1) Cliquez sur le lien 2) Appuyez sur Start 3) Envoyez votre numéro de téléphone 4) Envoyez votre code secret.
A53: 2 | B53: Marcadet | C53: LTS-004 | D53: LTS-004-015 | E53: BARBADINES | F53: M'HOUMADI | G53: Oussoufi | H53: 0692631773 | J53: 0692631773 | M53: locataire | N53: oui | S53: A activer | U53: 1052 | V53: non | W53: 0 | X53: non | AC53: https://t.me/motk_notification_bot?start=LTS-004-015 | AD53: 🏛️ Ville de Saint-Denis Service Habitat – Projet MOTK Bonjour Oussoufi M'HOUMADI Activez vos notifications logement : Lien : https://t.me/motk_notification_bot?start=LTS-004-015 Code secret : 1052 Étapes : 1) Cliquez sur le lien 2) Appuyez sur Start 3) Envoyez votre numéro de téléphone 4) Envoyez votre code secret.
A54: 2 | B54: Marcadet | C54: LTS-004 | D54: LTS-004-016 | E54: BARBADINES | F54: MAHABO | K54: 692543500 | M54: locataire | N54: oui | S54: A activer | U54: 1053 | V54: non | W54: 0 | X54: non | AC54: https://t.me/motk_notification_bot?start=LTS-004-016 | AD54: 🏛️ Ville de Saint-Denis Service Habitat – Projet MOTK Bonjour MAHABO Activez vos notifications logement : Lien : https://t.me/motk_notification_bot?start=LTS-004-016 Code secret : 1053 Étapes : 1) Cliquez sur le lien 2) Appuyez sur Start 3) Envoyez votre numéro de téléphone 4) Envoyez votre code secret.
A55: 2 | B55: Marcadet | C55: LTS-004 | D55: LTS-004-017 | E55: BARBADINES | F55: PAROS | G55: Simone | H55: 0692347454 | J55: 0692347454 | M55: locataire | N55: oui | S55: A activer | U55: 1054 | V55: non | W55: 0 | X55: non | AC55: https://t.me/motk_notification_bot?start=LTS-004-017 | AD55: 🏛️ Ville de Saint-Denis Service Habitat – Projet MOTK Bonjour Simone PAROS Activez vos notifications logement : Lien : https://t.me/motk_notification_bot?start=LTS-004-017 Code secret : 1054 Étapes : 1) Cliquez sur le lien 2) Appuyez sur Start 3) Envoyez votre numéro de téléphone 4) Envoyez votre code secret.
A56: 2 | B56: Marcadet | C56: LTS-004 | D56: LTS-004-018 | E56: BARBADINES | F56: PAYET | G56: David | H56: 0692328124 | J56: 0692328124 | M56: locataire | N56: oui | S56: A activer | U56: 1055 | V56: non | W56: 0 | X56: non | AC56: https://t.me/motk_notification_bot?start=LTS-004-018 | AD56: 🏛️ Ville de Saint-Denis Service Habitat – Projet MOTK Bonjour David PAYET Activez vos notifications logement : Lien : https://t.me/motk_notification_bot?start=LTS-004-018 Code secret : 1055 Étapes : 1) Cliquez sur le lien 2) Appuyez sur Start 3) Envoyez votre numéro de téléphone 4) Envoyez votre code secret.
A57: 2 | B57: Marcadet | C57: LTS-004 | D57: LTS-004-019 | E57: BARBADINES | F57: PAYET | G57: Marie Danielle | H57: 0692758155 | J57: 0692758155 | M57: locataire | N57: oui | S57: A activer | U57: 1056 | V57: non | W57: 0 | X57: non | AC57: https://t.me/motk_notification_bot?start=LTS-004-019 | AD57: 🏛️ Ville de Saint-Denis Service Habitat – Projet MOTK Bonjour Marie Danielle PAYET Activez vos notifications logement : Lien : https://t.me/motk_notification_bot?start=LTS-004-019 Code secret : 1056 Étapes : 1) Cliquez sur le lien 2) Appuyez sur Start 3) Envoyez votre numéro de téléphone 4) Envoyez votre code secret.
A58: 2 | B58: Marcadet | C58: LTS-004 | D58: LTS-004-020 | E58: BARBADINES | F58: RAVAT | G58: Fatema | H58: 0692677852 | J58: 0692677852 | M58: locataire | N58: oui | S58: A activer | U58: 1057 | V58: non | W58: 0 | X58: non | AC58: https://t.me/motk_notification_bot?start=LTS-004-020 | AD58: 🏛️ Ville de Saint-Denis Service Habitat – Projet MOTK Bonjour Fatema RAVAT Activez vos notifications logement : Lien : https://t.me/motk_notification_bot?start=LTS-004-020 Code secret : 1057 Étapes : 1) Cliquez sur le lien 2) Appuyez sur Start 3) Envoyez votre numéro de téléphone 4) Envoyez votre code secret.
A59: 2 | B59: Marcadet | C59: LTS-004 | D59: LTS-004-021 | E59: BARBADINES | F59: ROSENTAL | G59: Patricia | M59: locataire | N59: oui | S59: A activer | U59: 1058 | V59: non | W59: 0 | X59: non | AC59: https://t.me/motk_notification_bot?start=LTS-004-021 | AD59: 🏛️ Ville de Saint-Denis Service Habitat – Projet MOTK Bonjour Patricia ROSENTAL Activez vos notifications logement : Lien : https://t.me/motk_notification_bot?start=LTS-004-021 Code secret : 1058 Étapes : 1) Cliquez sur le lien 2) Appuyez sur Start 3) Envoyez votre numéro de téléphone 4) Envoyez votre code secret.
A60: 2 | B60: Marcadet | C60: LTS-004 | D60: LTS-004-022 | E60: BARBADINES | F60: SABABADICHETTY | G60: Jean Eric et Joseph Raoul | H60: 0692158289 | I60: 0693527699 | J60: 0692158289 | M60: locataire | N60: oui | S60: A activer | U60: 1059 | V60: non | W60: 0 | X60: non | AC60: https://t.me/motk_notification_bot?start=LTS-004-022 | AD60: 🏛️ Ville de Saint-Denis Service Habitat – Projet MOTK Bonjour Jean Eric et Joseph Raoul SABABADICHETTY Activez vos notifications logement : Lien : https://t.me/motk_notification_bot?start=LTS-004-022 Code secret : 1059 Étapes : 1) Cliquez sur le lien 2) Appuyez sur Start 3) Envoyez votre numéro de téléphone 4) Envoyez votre code secret.
A61: 2 | B61: Marcadet | C61: LTS-004 | D61: LTS-004-023 | E61: BARBADINES | F61: SALEM | G61: Brice | H61: 0693311767 | I61: 0692186561 | J61: 0693311767 | K61: SA FEMME | M61: locataire | N61: oui | S61: A activer | U61: 1060 | V61: non | W61: 0 | X61: non | AC61: https://t.me/motk_notification_bot?start=LTS-004-023 | AD61: 🏛️ Ville de Saint-Denis Service Habitat – Projet MOTK Bonjour Brice SALEM Activez vos notifications logement : Lien : https://t.me/motk_notification_bot?start=LTS-004-023 Code secret : 1060 Étapes : 1) Cliquez sur le lien 2) Appuyez sur Start 3) Envoyez votre numéro de téléphone 4) Envoyez votre code secret.
A62: 2 | B62: Marcadet | C62: LTS-004 | D62: LTS-004-024 | E62: BARBADINES | F62: SANOLAH | G62: Eva Bibi | H62: 0692169701 | J62: 0692169701 | M62: locataire | N62: oui | S62: A activer | U62: 1061 | V62: non | W62: 0 | X62: non | AC62: https://t.me/motk_notification_bot?start=LTS-004-024 | AD62: 🏛️ Ville de Saint-Denis Service Habitat – Projet MOTK Bonjour Eva Bibi SANOLAH Activez vos notifications logement : Lien : https://t.me/motk_notification_bot?start=LTS-004-024 Code secret : 1061 Étapes : 1) Cliquez sur le lien 2) Appuyez sur Start 3) Envoyez votre numéro de téléphone 4) Envoyez votre code secret.
A63: 2 | B63: Marcadet | C63: LTS-004 | D63: LTS-004-025 | E63: BARBADINES | F63: ELIZEON | G63: Fabrice | H63: 0692856383 | J63: 0692856383 | M63: locataire | N63: oui | S63: A activer | U63: 1062 | V63: non | W63: 0 | X63: non | AC63: https://t.me/motk_notification_bot?start=LTS-004-025 | AD63: 🏛️ Ville de Saint-Denis Service Habitat – Projet MOTK Bonjour Fabrice ELIZEON Activez vos notifications logement : Lien : https://t.me/motk_notification_bot?start=LTS-004-025 Code secret : 1062 Étapes : 1) Cliquez sur le lien 2) Appuyez sur Start 3) Envoyez votre numéro de téléphone 4) Envoyez votre code secret.
A64: 4 | B64: Moufia | C64: LTS-005 | D64: LTS-005-001 | E64: BILIMBIS | F64: ARABOUT | G64: Darina | H64: 0693338433 | J64: 0693338433 | M64: locataire | N64: oui | S64: A activer | U64: 1063 | V64: non | W64: 0 | X64: non | AC64: https://t.me/motk_notification_bot?start=LTS-005-001 | AD64: 🏛️ Ville de Saint-Denis Service Habitat – Projet MOTK Bonjour Darina ARABOUT Activez vos notifications logement : Lien : https://t.me/motk_notification_bot?start=LTS-005-001 Code secret : 1063 Étapes : 1) Cliquez sur le lien 2) Appuyez sur Start 3) Envoyez votre numéro de téléphone 4) Envoyez votre code secret.
A65: 4 | B65: Moufia | C65: LTS-005 | D65: LTS-005-002 | E65: BILIMBIS | F65: BELVISEE | G65: Frédéric | H65: 0693046702 | J65: 0693046702 | M65: locataire | N65: oui | S65: A activer | U65: 1064 | V65: non | W65: 0 | X65: non | AC65: https://t.me/motk_notification_bot?start=LTS-005-002 | AD65: 🏛️ Ville de Saint-Denis Service Habitat – Projet MOTK Bonjour Frédéric BELVISEE Activez vos notifications logement : Lien : https://t.me/motk_notification_bot?start=LTS-005-002 Code secret : 1064 Étapes : 1) Cliquez sur le lien 2) Appuyez sur Start 3) Envoyez votre numéro de téléphone 4) Envoyez votre code secret.
A66: 4 | B66: Moufia | C66: LTS-005 | D66: LTS-005-003 | E66: BILIMBIS | F66: ROBERT | G66: Marie Sylvie | H66: 0692692306 | J66: 0692692306 | K66: MME ROBERT | M66: locataire | N66: oui | S66: A activer | U66: 1065 | V66: non | W66: 0 | X66: non | AC66: https://t.me/motk_notification_bot?start=LTS-005-003 | AD66: 🏛️ Ville de Saint-Denis Service Habitat – Projet MOTK Bonjour Marie Sylvie ROBERT Activez vos notifications logement : Lien : https://t.me/motk_notification_bot?start=LTS-005-003 Code secret : 1065 Étapes : 1) Cliquez sur le lien 2) Appuyez sur Start 3) Envoyez votre numéro de téléphone 4) Envoyez votre code secret.
A67: 4 | B67: Moufia | C67: LTS-005 | D67: LTS-005-004 | E67: BILIMBIS | F67: BOYER | G67: Mimose | H67: 0692779160 | J67: 0692779160 | M67: locataire | N67: oui | S67: A activer | U67: 1066 | V67: non | W67: 0 | X67: non | AC67: https://t.me/motk_notification_bot?start=LTS-005-004 | AD67: 🏛️ Ville de Saint-Denis Service Habitat – Projet MOTK Bonjour Mimose BOYER Activez vos notifications logement : Lien : https://t.me/motk_notification_bot?start=LTS-005-004 Code secret : 1066 Étapes : 1) Cliquez sur le lien 2) Appuyez sur Start 3) Envoyez votre numéro de téléphone 4) Envoyez votre code secret.
A68: 4 | B68: Moufia | C68: LTS-005 | D68: LTS-005-005 | E68: BILIMBIS | F68: BOYER | G68: Cyril Joseph | H68: 0692253800 | J68: 0692253800 | M68: locataire | N68: oui | S68: A activer | U68: 1067 | V68: non | W68: 0 | X68: non | AC68: https://t.me/motk_notification_bot?start=LTS-005-005 | AD68: 🏛️ Ville de Saint-Denis Service Habitat – Projet MOTK Bonjour Cyril Joseph BOYER Activez vos notifications logement : Lien : https://t.me/motk_notification_bot?start=LTS-005-005 Code secret : 1067 Étapes : 1) Cliquez sur le lien 2) Appuyez sur Start 3) Envoyez votre numéro de téléphone 4) Envoyez votre code secret.
A69: 4 | B69: Moufia | C69: LTS-005 | D69: LTS-005-006 | E69: BILIMBIS | F69: ROCROU | G69: Camille Joël | H69: 0692828750 | J69: 0692828750 | M69: locataire | N69: oui | S69: A activer | U69: 1068 | V69: non | W69: 0 | X69: non | AC69: https://t.me/motk_notification_bot?start=LTS-005-006 | AD69: 🏛️ Ville de Saint-Denis Service Habitat – Projet MOTK Bonjour Camille Joël ROCROU Activez vos notifications logement : Lien : https://t.me/motk_notification_bot?start=LTS-005-006 Code secret : 1068 Étapes : 1) Cliquez sur le lien 2) Appuyez sur Start 3) Envoyez votre numéro de téléphone 4) Envoyez votre code secret.
A70: 4 | B70: Moufia | C70: LTS-005 | D70: LTS-005-007 | E70: BILIMBIS | F70: CHNAYTI | G70: Dounia | H70: 0692336953 | I70: 0262577819 | J70: 0692336953 | M70: locataire | N70: oui | S70: A activer | U70: 1069 | V70: non | W70: 0 | X70: non | AC70: https://t.me/motk_notification_bot?start=LTS-005-007 | AD70: 🏛️ Ville de Saint-Denis Service Habitat – Projet MOTK Bonjour Dounia CHNAYTI Activez vos notifications logement : Lien : https://t.me/motk_notification_bot?start=LTS-005-007 Code secret : 1069 Étapes : 1) Cliquez sur le lien 2) Appuyez sur Start 3) Envoyez votre numéro de téléphone 4) Envoyez votre code secret.
A71: 4 | B71: Moufia | C71: LTS-005 | D71: LTS-005-008 | E71: BILIMBIS | F71: HOAREAU | G71: Jenifer | H71: 0693431072 | J71: 0693431072 | M71: locataire | N71: oui | S71: A activer | U71: 1070 | V71: non | W71: 0 | X71: non | AC71: https://t.me/motk_notification_bot?start=LTS-005-008 | AD71: 🏛️ Ville de Saint-Denis Service Habitat – Projet MOTK Bonjour Jenifer HOAREAU Activez vos notifications logement : Lien : https://t.me/motk_notification_bot?start=LTS-005-008 Code secret : 1070 Étapes : 1) Cliquez sur le lien 2) Appuyez sur Start 3) Envoyez votre numéro de téléphone 4) Envoyez votre code secret.
A72: 4 | B72: Moufia | C72: LTS-005 | D72: LTS-005-009 | E72: BILIMBIS | F72: GRONDIN | G72: Marie Michèle | H72: 0262221550 | I72: 0692022133 | J72: 0262221550 | K72: 5 | M72: locataire | N72: oui | S72: A activer | U72: 1071 | V72: non | W72: 0 | X72: non | AC72: https://t.me/motk_notification_bot?start=LTS-005-009 | AD72: 🏛️ Ville de Saint-Denis Service Habitat – Projet MOTK Bonjour Marie Michèle GRONDIN Activez vos notifications logement : Lien : https://t.me/motk_notification_bot?start=LTS-005-009 Code secret : 1071 Étapes : 1) Cliquez sur le lien 2) Appuyez sur Start 3) Envoyez votre numéro de téléphone 4) Envoyez votre code secret.
A73: 4 | B73: Moufia | C73: LTS-005 | D73: LTS-005-010 | E73: BILIMBIS | F73: HOAREAU | G73: Suzette Lourdes | H73: 0262298512 | J73: 0262298512 | M73: locataire | N73: oui | S73: A activer | U73: 1072 | V73: non | W73: 0 | X73: non | AC73: https://t.me/motk_notification_bot?start=LTS-005-010 | AD73: 🏛️ Ville de Saint-Denis Service Habitat – Projet MOTK Bonjour Suzette Lourdes HOAREAU Activez vos notifications logement : Lien : https://t.me/motk_notification_bot?start=LTS-005-010 Code secret : 1072 Étapes : 1) Cliquez sur le lien 2) Appuyez sur Start 3) Envoyez votre numéro de téléphone 4) Envoyez votre code secret.
A74: 4 | B74: Moufia | C74: LTS-005 | D74: LTS-005-011 | E74: BILIMBIS | F74: HUET | G74: Marie Ingrid | H74: 0692809596 | J74: 0692809596 | M74: locataire | N74: oui | S74: A activer | U74: 1073 | V74: non | W74: 0 | X74: non | AC74: https://t.me/motk_notification_bot?start=LTS-005-011 | AD74: 🏛️ Ville de Saint-Denis Service Habitat – Projet MOTK Bonjour Marie Ingrid HUET Activez vos notifications logement : Lien : https://t.me/motk_notification_bot?start=LTS-005-011 Code secret : 1073 Étapes : 1) Cliquez sur le lien 2) Appuyez sur Start 3) Envoyez votre numéro de téléphone 4) Envoyez votre code secret.
A75: 4 | B75: Moufia | C75: LTS-005 | D75: LTS-005-012 | E75: BILIMBIS | F75: ICHOUZA | G75: Béatrice | H75: 0262234375 | I75: 0692619143 | J75: 0262234375 | M75: locataire | N75: oui | S75: A activer | U75: 1074 | V75: non | W75: 0 | X75: non | AC75: https://t.me/motk_notification_bot?start=LTS-005-012 | AD75: 🏛️ Ville de Saint-Denis Service Habitat – Projet MOTK Bonjour Béatrice ICHOUZA Activez vos notifications logement : Lien : https://t.me/motk_notification_bot?start=LTS-005-012 Code secret : 1074 Étapes : 1) Cliquez sur le lien 2) Appuyez sur Start 3) Envoyez votre numéro de téléphone 4) Envoyez votre code secret.
A76: 4 | B76: Moufia | C76: LTS-005 | D76: LTS-005-013 | E76: BILIMBIS | F76: ICHOUZA | G76: Marie Gladys | H76: 0692799962 | J76: 0692799962 | M76: locataire | N76: oui | S76: A activer | U76: 1075 | V76: non | W76: 0 | X76: non | AC76: https://t.me/motk_notification_bot?start=LTS-005-013 | AD76: 🏛️ Ville de Saint-Denis Service Habitat – Projet MOTK Bonjour Marie Gladys ICHOUZA Activez vos notifications logement : Lien : https://t.me/motk_notification_bot?start=LTS-005-013 Code secret : 1075 Étapes : 1) Cliquez sur le lien 2) Appuyez sur Start 3) Envoyez votre numéro de téléphone 4) Envoyez votre code secret.
A77: 4 | B77: Moufia | C77: LTS-005 | D77: LTS-005-014 | E77: BILIMBIS | F77: IMIRA | G77: Marie Rita | H77: 0692782803 | J77: 0692782803 | M77: locataire | N77: oui | S77: A activer | U77: 1076 | V77: non | W77: 0 | X77: non | AC77: https://t.me/motk_notification_bot?start=LTS-005-014 | AD77: 🏛️ Ville de Saint-Denis Service Habitat – Projet MOTK Bonjour Marie Rita IMIRA Activez vos notifications logement : Lien : https://t.me/motk_notification_bot?start=LTS-005-014 Code secret : 1076 Étapes : 1) Cliquez sur le lien 2) Appuyez sur Start 3) Envoyez votre numéro de téléphone 4) Envoyez votre code secret.
A78: 4 | B78: Moufia | C78: LTS-005 | D78: LTS-005-015 | E78: BILIMBIS | F78: JEAN BAPTISTE | G78: Alexandra | H78: 0692374881 | J78: 0692374881 | M78: locataire | N78: oui | S78: A activer | U78: 1077 | V78: non | W78: 0 | X78: non | AC78: https://t.me/motk_notification_bot?start=LTS-005-015 | AD78: 🏛️ Ville de Saint-Denis Service Habitat – Projet MOTK Bonjour Alexandra JEAN BAPTISTE Activez vos notifications logement : Lien : https://t.me/motk_notification_bot?start=LTS-005-015 Code secret : 1077 Étapes : 1) Cliquez sur le lien 2) Appuyez sur Start 3) Envoyez votre numéro de téléphone 4) Envoyez votre code secret.
A79: 4 | B79: Moufia | C79: LTS-005 | D79: LTS-005-016 | E79: BILIMBIS | F79: LEBON | G79: Rock | H79: 0692903963 | J79: 0692903963 | M79: locataire | N79: oui | S79: A activer | U79: 1078 | V79: non | W79: 0 | X79: non | AC79: https://t.me/motk_notification_bot?start=LTS-005-016 | AD79: 🏛️ Ville de Saint-Denis Service Habitat – Projet MOTK Bonjour Rock LEBON Activez vos notifications logement : Lien : https://t.me/motk_notification_bot?start=LTS-005-016 Code secret : 1078 Étapes : 1) Cliquez sur le lien 2) Appuyez sur Start 3) Envoyez votre numéro de téléphone 4) Envoyez votre code secret.
A80: 4 | B80: Moufia | C80: LTS-005 | D80: LTS-005-017 | E80: BILIMBIS | F80: LEBRETON | G80: Yanito | H80: 0692922592 | J80: 0692922592 | M80: locataire | N80: oui | S80: A activer | U80: 1079 | V80: non | W80: 0 | X80: non | AC80: https://t.me/motk_notification_bot?start=LTS-005-017 | AD80: 🏛️ Ville de Saint-Denis Service Habitat – Projet MOTK Bonjour Yanito LEBRETON Activez vos notifications logement : Lien : https://t.me/motk_notification_bot?start=LTS-005-017 Code secret : 1079 Étapes : 1) Cliquez sur le lien 2) Appuyez sur Start 3) Envoyez votre numéro de téléphone 4) Envoyez votre code secret.
A81: 4 | B81: Moufia | C81: LTS-005 | D81: LTS-005-018 | E81: BILIMBIS | F81: KIBIO | G81: Kayliane | H81: 0692496477 | I81: 0693450257 | J81: 0692496477 | K81: MME KIBIO | M81: locataire | N81: oui | S81: A activer | U81: 1080 | V81: non | W81: 0 | X81: non | AC81: https://t.me/motk_notification_bot?start=LTS-005-018 | AD81: 🏛️ Ville de Saint-Denis Service Habitat – Projet MOTK Bonjour Kayliane KIBIO Activez vos notifications logement : Lien : https://t.me/motk_notification_bot?start=LTS-005-018 Code secret : 1080 Étapes : 1) Cliquez sur le lien 2) Appuyez sur Start 3) Envoyez votre numéro de téléphone 4) Envoyez votre code secret.
A82: 4 | B82: Moufia | C82: LTS-005 | D82: LTS-005-019 | E82: BILIMBIS | F82: ROBERT | G82: Eugénie | H82: 0692826196 | J82: 0692826196 | M82: locataire | N82: oui | S82: A activer | U82: 1081 | V82: non | W82: 0 | X82: non | AC82: https://t.me/motk_notification_bot?start=LTS-005-019 | AD82: 🏛️ Ville de Saint-Denis Service Habitat – Projet MOTK Bonjour Eugénie ROBERT Activez vos notifications logement : Lien : https://t.me/motk_notification_bot?start=LTS-005-019 Code secret : 1081 Étapes : 1) Cliquez sur le lien 2) Appuyez sur Start 3) Envoyez votre numéro de téléphone 4) Envoyez votre code secret.
A83: 4 | B83: Moufia | C83: LTS-005 | D83: LTS-005-020 | E83: BILIMBIS | F83: SADON | G83: Marie Jeanine | H83: 0693049639 | I83: 0262134356 | J83: 0693049639 | K83: fixe | M83: locataire | N83: oui | S83: A activer | U83: 1082 | V83: non | W83: 0 | X83: non | AC83: https://t.me/motk_notification_bot?start=LTS-005-020 | AD83: 🏛️ Ville de Saint-Denis Service Habitat – Projet MOTK Bonjour Marie Jeanine SADON Activez vos notifications logement : Lien : https://t.me/motk_notification_bot?start=LTS-005-020 Code secret : 1082 Étapes : 1) Cliquez sur le lien 2) Appuyez sur Start 3) Envoyez votre numéro de téléphone 4) Envoyez votre code secret.
A84: 4 | B84: Moufia | C84: LTS-005 | D84: LTS-005-021 | E84: BILIMBIS | F84: SINAN | G84: Marie Anièle | H84: 0693037800 | J84: 0693037800 | M84: locataire | N84: oui | S84: A activer | U84: 1083 | V84: non | W84: 0 | X84: non | AC84: https://t.me/motk_notification_bot?start=LTS-005-021 | AD84: 🏛️ Ville de Saint-Denis Service Habitat – Projet MOTK Bonjour Marie Anièle SINAN Activez vos notifications logement : Lien : https://t.me/motk_notification_bot?start=LTS-005-021 Code secret : 1083 Étapes : 1) Cliquez sur le lien 2) Appuyez sur Start 3) Envoyez votre numéro de téléphone 4) Envoyez votre code secret.
A85: 4 | B85: Moufia | C85: LTS-005 | D85: LTS-005-022 | E85: BILIMBIS | F85: TURPIN | G85: Josian | H85: 0692916291 | J85: 0692916291 | M85: locataire | N85: oui | S85: A activer | U85: 1084 | V85: non | W85: 0 | X85: non | AC85: https://t.me/motk_notification_bot?start=LTS-005-022 | AD85: 🏛️ Ville de Saint-Denis Service Habitat – Projet MOTK Bonjour Josian TURPIN Activez vos notifications logement : Lien : https://t.me/motk_notification_bot?start=LTS-005-022 Code secret : 1084 Étapes : 1) Cliquez sur le lien 2) Appuyez sur Start 3) Envoyez votre numéro de téléphone 4) Envoyez votre code secret.
A86: 4 | B86: Moufia | C86: LTS-005 | D86: LTS-005-023 | E86: BILIMBIS | F86: TURPIN | G86: Marie Julienne | H86: 0262299212 | I86: 0692697117 | J86: 0262299212 | M86: locataire | N86: oui | S86: A activer | U86: 1085 | V86: non | W86: 0 | X86: non | AC86: https://t.me/motk_notification_bot?start=LTS-005-023 | AD86: 🏛️ Ville de Saint-Denis Service Habitat – Projet MOTK Bonjour Marie Julienne TURPIN Activez vos notifications logement : Lien : https://t.me/motk_notification_bot?start=LTS-005-023 Code secret : 1085 Étapes : 1) Cliquez sur le lien 2) Appuyez sur Start 3) Envoyez votre numéro de téléphone 4) Envoyez votre code secret.
A87: 4 | B87: Moufia | C87: LTS-005 | D87: LTS-005-024 | E87: BILIMBIS | F87: VIDOT | G87: Marie Claude | H87: 0262977334 | I87: 0693802564 | J87: 0262977334 | K87: SA FILLE | M87: locataire | N87: oui | S87: A activer | U87: 1086 | V87: non | W87: 0 | X87: non | AC87: https://t.me/motk_notification_bot?start=LTS-005-024 | AD87: 🏛️ Ville de Saint-Denis Service Habitat – Projet MOTK Bonjour Marie Claude VIDOT Activez vos notifications logement : Lien : https://t.me/motk_notification_bot?start=LTS-005-024 Code secret : 1086 Étapes : 1) Cliquez sur le lien 2) Appuyez sur Start 3) Envoyez votre numéro de téléphone 4) Envoyez votre code secret.
A88: 4 | B88: La Bretagne | C88: LTS-006 | D88: LTS-006-001 | E88: LANGAVANT | F88: SAITI | H88: 0262989287 | J88: 0262989287 | M88: locataire | N88: oui | S88: A activer | U88: 1087 | V88: non | W88: 0 | X88: non | AC88: https://t.me/motk_notification_bot?start=LTS-006-001 | AD88: 🏛️ Ville de Saint-Denis Service Habitat – Projet MOTK Bonjour SAITI Activez vos notifications logement : Lien : https://t.me/motk_notification_bot?start=LTS-006-001 Code secret : 1087 Étapes : 1) Cliquez sur le lien 2) Appuyez sur Start 3) Envoyez votre numéro de téléphone 4) Envoyez votre code secret.
A89: 4 | B89: La Bretagne | C89: LTS-006 | D89: LTS-006-002 | E89: LANGAVANT | F89: PANECHOU | H89: 0262526270 | J89: 0262526270 | M89: locataire | N89: oui | S89: A activer | U89: 1088 | V89: non | W89: 0 | X89: non | AC89: https://t.me/motk_notification_bot?start=LTS-006-002 | AD89: 🏛️ Ville de Saint-Denis Service Habitat – Projet MOTK Bonjour PANECHOU Activez vos notifications logement : Lien : https://t.me/motk_notification_bot?start=LTS-006-002 Code secret : 1088 Étapes : 1) Cliquez sur le lien 2) Appuyez sur Start 3) Envoyez votre numéro de téléphone 4) Envoyez votre code secret.
A90: 3 | B90: Saint François | C90: LTS-007 | D90: LTS-007-001 | E90: CASKAVELS | F90: DIJOUX | G90: Sébastien | H90: 0692808959 | J90: 0692808959 | M90: locataire | N90: oui | S90: A activer | U90: 1089 | V90: non | W90: 0 | X90: non | AC90: https://t.me/motk_notification_bot?start=LTS-007-001 | AD90: 🏛️ Ville de Saint-Denis Service Habitat – Projet MOTK Bonjour Sébastien DIJOUX Activez vos notifications logement : Lien : https://t.me/motk_notification_bot?start=LTS-007-001 Code secret : 1089 Étapes : 1) Cliquez sur le lien 2) Appuyez sur Start 3) Envoyez votre numéro de téléphone 4) Envoyez votre code secret.
A91: 3 | B91: Saint François | C91: LTS-007 | D91: LTS-007-002 | E91: CASKAVELS | F91: PICARD | G91: Ignace Clémént | H91: 0692461865 | J91: 0692461865 | M91: locataire | N91: oui | S91: A activer | U91: 1090 | V91: non | W91: 0 | X91: non | AC91: https://t.me/motk_notification_bot?start=LTS-007-002 | AD91: 🏛️ Ville de Saint-Denis Service Habitat – Projet MOTK Bonjour Ignace Clémént PICARD Activez vos notifications logement : Lien : https://t.me/motk_notification_bot?start=LTS-007-002 Code secret : 1090 Étapes : 1) Cliquez sur le lien 2) Appuyez sur Start 3) Envoyez votre numéro de téléphone 4) Envoyez votre code secret.
A92: 3 | B92: Saint François | C92: LTS-007 | D92: LTS-007-003 | E92: CASKAVELS | F92: HOARAU | G92: Sheila | H92: 0262302418 | I92: 0693022610 | J92: 0262302418 | M92: locataire | N92: oui | S92: A activer | U92: 1091 | V92: non | W92: 0 | X92: non | AC92: https://t.me/motk_notification_bot?start=LTS-007-003 | AD92: 🏛️ Ville de Saint-Denis Service Habitat – Projet MOTK Bonjour Sheila HOARAU Activez vos notifications logement : Lien : https://t.me/motk_notification_bot?start=LTS-007-003 Code secret : 1091 Étapes : 1) Cliquez sur le lien 2) Appuyez sur Start 3) Envoyez votre numéro de téléphone 4) Envoyez votre code secret.
A93: 3 | B93: Saint François | C93: LTS-007 | D93: LTS-007-004 | E93: CASKAVELS | F93: JOSON | G93: Marie Thérèse | M93: locataire | N93: oui | S93: A activer | U93: 1092 | V93: non | W93: 0 | X93: non | AC93: https://t.me/motk_notification_bot?start=LTS-007-004 | AD93: 🏛️ Ville de Saint-Denis Service Habitat – Projet MOTK Bonjour Marie Thérèse JOSON Activez vos notifications logement : Lien : https://t.me/motk_notification_bot?start=LTS-007-004 Code secret : 1092 Étapes : 1) Cliquez sur le lien 2) Appuyez sur Start 3) Envoyez votre numéro de téléphone 4) Envoyez votre code secret.
A94: 3 | B94: Saint François | C94: LTS-007 | D94: LTS-007-005 | E94: CASKAVELS | F94: MAILLOT | G94: René-Claude | H94: 0262647470 | I94: 0692104376 | J94: 0262647470 | K94: RENE Claude | M94: locataire | N94: oui | S94: A activer | U94: 1093 | V94: non | W94: 0 | X94: non | AC94: https://t.me/motk_notification_bot?start=LTS-007-005 | AD94: 🏛️ Ville de Saint-Denis Service Habitat – Projet MOTK Bonjour René-Claude MAILLOT Activez vos notifications logement : Lien : https://t.me/motk_notification_bot?start=LTS-007-005 Code secret : 1093 Étapes : 1) Cliquez sur le lien 2) Appuyez sur Start 3) Envoyez votre numéro de téléphone 4) Envoyez votre code secret.
A95: 3 | B95: Saint François | C95: LTS-007 | D95: LTS-007-006 | E95: CASKAVELS | F95: MALAYA | G95: Jean Raymond | H95: 0262305300 | J95: 0262305300 | M95: locataire | N95: oui | S95: A activer | U95: 1094 | V95: non | W95: 0 | X95: non | AC95: https://t.me/motk_notification_bot?start=LTS-007-006 | AD95: 🏛️ Ville de Saint-Denis Service Habitat – Projet MOTK Bonjour Jean Raymond MALAYA Activez vos notifications logement : Lien : https://t.me/motk_notification_bot?start=LTS-007-006 Code secret : 1094 Étapes : 1) Cliquez sur le lien 2) Appuyez sur Start 3) Envoyez votre numéro de téléphone 4) Envoyez votre code secret.
A96: 3 | B96: Saint François | C96: LTS-007 | D96: LTS-007-007 | E96: CASKAVELS | F96: MALAYA | G96: Simone | H96: 0262302939 | J96: 0262302939 | M96: locataire | N96: oui | S96: A activer | U96: 1095 | V96: non | W96: 0 | X96: non | AC96: https://t.me/motk_notification_bot?start=LTS-007-007 | AD96: 🏛️ Ville de Saint-Denis Service Habitat – Projet MOTK Bonjour Simone MALAYA Activez vos notifications logement : Lien : https://t.me/motk_notification_bot?start=LTS-007-007 Code secret : 1095 Étapes : 1) Cliquez sur le lien 2) Appuyez sur Start 3) Envoyez votre numéro de téléphone 4) Envoyez votre code secret.
A97: 3 | B97: Saint François | C97: LTS-007 | D97: LTS-007-008 | E97: CASKAVELS | F97: NAZE | G97: Anne Marie Catherine | H97: 0262303814 | I97: 0693909611 | J97: 0262303814 | M97: locataire | N97: oui | S97: A activer | U97: 1096 | V97: non | W97: 0 | X97: non | AC97: https://t.me/motk_notification_bot?start=LTS-007-008 | AD97: 🏛️ Ville de Saint-Denis Service Habitat – Projet MOTK Bonjour Anne Marie Catherine NAZE Activez vos notifications logement : Lien : https://t.me/motk_notification_bot?start=LTS-007-008 Code secret : 1096 Étapes : 1) Cliquez sur le lien 2) Appuyez sur Start 3) Envoyez votre numéro de téléphone 4) Envoyez votre code secret.
A98: 3 | B98: Saint François | C98: LTS-007 | D98: LTS-007-009 | E98: CASKAVELS | F98: TURPIN | G98: Marie Laetitia | H98: 0692181507 | I98: 0262811637 | J98: 0692181507 | M98: locataire | N98: oui | S98: A activer | U98: 1097 | V98: non | W98: 0 | X98: non | AC98: https://t.me/motk_notification_bot?start=LTS-007-009 | AD98: 🏛️ Ville de Saint-Denis Service Habitat – Projet MOTK Bonjour Marie Laetitia TURPIN Activez vos notifications logement : Lien : https://t.me/motk_notification_bot?start=LTS-007-009 Code secret : 1097 Étapes : 1) Cliquez sur le lien 2) Appuyez sur Start 3) Envoyez votre numéro de téléphone 4) Envoyez votre code secret.
A99: 4 | B99: Bois de Nefles | C99: LTS-008 | D99: LTS-008-001 | E99: CLOTILDA | F99: BATONNET | G99: Jeannine Yvette | H99: 0693300830 | J99: 0693300830 | M99: locataire | N99: oui | S99: A activer | U99: 1098 | V99: non | W99: 0 | X99: non | AC99: https://t.me/motk_notification_bot?start=LTS-008-001 | AD99: 🏛️ Ville de Saint-Denis Service Habitat – Projet MOTK Bonjour Jeannine Yvette BATONNET Activez vos notifications logement : Lien : https://t.me/motk_notification_bot?start=LTS-008-001 Code secret : 1098 Étapes : 1) Cliquez sur le lien 2) Appuyez sur Start 3) Envoyez votre numéro de téléphone 4) Envoyez votre code secret.
A100: 4 | B100: Bois de Nefles | C100: LTS-008 | D100: LTS-008-002 | E100: CLOTILDA | F100: SALEZ | G100: Catherine | H100: 0693323223 | J100: 0693323223 | M100: locataire | N100: oui | S100: A activer | U100: 1099 | V100: non | W100: 0 | X100: non | AC100: https://t.me/motk_notification_bot?start=LTS-008-002 | AD100: 🏛️ Ville de Saint-Denis Service Habitat – Projet MOTK Bonjour Catherine SALEZ Activez vos notifications logement : Lien : https://t.me/motk_notification_bot?start=LTS-008-002 Code secret : 1099 Étapes : 1) Cliquez sur le lien 2) Appuyez sur Start 3) Envoyez votre numéro de téléphone 4) Envoyez votre code secret.
...

Sheet Referentiels
A1: Référentiels et listes déroulantes
A2: Ne pas saisir librement les statuts : utilisez ces listes pour éviter les erreurs
A3: OUI_NON | C3: STATUT_ACTIVATION | E3: CONTACT_ACTIF | G3: TYPE_CONTACT | I3: ORIGINE_DEMANDE | K3: STATUT_DEMANDE | M3: STATUT_DETAIL | O3: TYPE_TRAVAUX | Q3: URGENCE | S3: MODE_ATTRIBUTION | U3: NOTIFICATION | W3: STATUT_VENTE | Y3: STATUT_DIAG | AA3: STATUT_CHEQUE | AC3: STATUT_PAIEMENT | AE3: STATUT_DOSSIER | AG3: STATUT_MARCHE | AI3: MODE_PRESTATION | AK3: CANAL | AM3: VENTE_AUTORISEE
A4: oui | C4: A activer | E4: oui | G4: locataire | I4: locataire | K4: nouvelle | M4: en_attente | O4: plomberie | Q4: faible | S4: marche | U4: a_notifier | W4: demande_recue | Y4: a_faire | AA4: a_instruire | AC4: en_attente | AE4: ok | AG4: actif | AI4: titulaire_marche | AK4: Telegram | AM4: oui
A5: non | C5: oui | E5: non | G5: cooccupant | I5: agent | K5: analyse | M5: en_cours | O5: electricite | Q5: moyenne | S5: hors_marche | U5: envoyee | W5: en_instruction | Y5: fait | AA5: valide | AC5: depot_recu | AE5: a_regulariser | AG5: termine | AI5: hors_marche | AK5: SMS | AM5: non
C6: non | G6: référent | I6: entreprise | K6: validee | M6: termine | O6: toiture | Q6: urgente | S6: urgence | U6: non_concerne | W6: pret_signature | Y6: non_concerne | AA6: refuse | AC6: virement_effectue | AE6: incomplet | AG6: suspendu | AI6: urgence | AK6: Mail
C7: bloquee | G7: gestionnaire | I7: direction | K7: refusee | M7: bloque | O7: serrurerie | S7: consultation | W7: signature | AA7: non_concerne | AC7: non_concerne | AG7: a_lancer | AI7: consultation | AK7: Manuel
O8: assainissement | W8: realisee
O9: peinture | W9: refusee
O10: menuiserie
O11: vrd
O12: autre

Sheet LTS_Parc
A1: secteur | B1: quartier | C1: code_lts | D1: code_acces | E1: nom_lts | F1: adresse | G1: nombre_logements | H1: x | I1: y | J1: nom | K1: prenom | L1: telephone_principal | M1: telephone_secondaire | N1: remarques_contact | O1: a_vendre | P1: location_pure | Q1: a_vendre | R1: vente_statut | S1: x | T1: y | U1: contact_actif | V1: statut_global | W1: priorite | X1: niveau_sante
A2: 1 | B2: Sainte Cloitlde | C2: LTS-001 | D2: LTS-001-001 | E2: ALAMANDAS | F2: 15 Bloc 20 Rue des Alamandas | G2: 30 | H2: 68 | I2: 24 | J2: RIVIERE | K2: Fabienne | L2: 0692670367 | O2: non | P2: Résidence exclue du dispositif de vente | Q2: non | U2: =IF(COUNTIFS(Contacts_Activation!D:D,D2,Contacts_Activation!N:N,"oui")>0,"oui","non") -> oui | V2: =IF(COUNTIFS(Travaux!C:C,D2,Travaux!X:X,"en_cours")>0,"travaux_en_cours",IF(COUNTIFS(Ventes!C:C,D2,Ventes!L:L,"signature")>0,"vente_signature",IF(COUNTIFS(Ventes!C:C,D2,Ventes!AD:AD,"oui")>0,"vente_bloquee",IF(COUNTIFS(Gestion_Locative!C:C,D2,Gestion_Locative!O:O,"incomplet")>0,"gestion_fragile","stable")))) -> vente_bloquee
A3: 1 | B3: Sainte Cloitlde | C3: LTS-001 | D3: LTS-001-002 | E3: ALAMANDAS | F3: 26 Bloc 24 Rue des Alamandas | G3: 30 | H3: 68 | I3: 24 | J3: ARAYE | K3: Evelyne | L3: 0262294396 | M3: 0692085376 | O3: non | P3: Résidence exclue du dispositif de vente | Q3: non | U3: =IF(COUNTIFS(Contacts_Activation!D:D,D3,Contacts_Activation!N:N,"oui")>0,"oui","non") -> oui | V3: =IF(COUNTIFS(Travaux!C:C,D3,Travaux!X:X,"en_cours")>0,"travaux_en_cours",IF(COUNTIFS(Ventes!C:C,D3,Ventes!L:L,"signature")>0,"vente_signature",IF(COUNTIFS(Ventes!C:C,D3,Ventes!AD:AD,"oui")>0,"vente_bloquee",IF(COUNTIFS(Gestion_Locative!C:C,D3,Gestion_Locative!O:O,"incomplet")>0,"gestion_fragile","stable")))) -> vente_bloquee
A4: 1 | B4: Sainte Cloitlde | C4: LTS-001 | D4: LTS-001-003 | E4: ALAMANDAS | F4: 19 Bloc 22 Rue des Alamandas | G4: 30 | H4: 68 | I4: 24 | J4: ARLANDON | K4: Jean Luc | L4: 0692253329 | M4: 0692373955 | N4: FREDERICK ARLANDON | O4: non | P4: Résidence exclue du dispositif de vente | Q4: non | U4: =IF(COUNTIFS(Contacts_Activation!D:D,D4,Contacts_Activation!N:N,"oui")>0,"oui","non") -> oui | V4: =IF(COUNTIFS(Travaux!C:C,D4,Travaux!X:X,"en_cours")>0,"travaux_en_cours",IF(COUNTIFS(Ventes!C:C,D4,Ventes!L:L,"signature")>0,"vente_signature",IF(COUNTIFS(Ventes!C:C,D4,Ventes!AD:AD,"oui")>0,"vente_bloquee",IF(COUNTIFS(Gestion_Locative!C:C,D4,Gestion_Locative!O:O,"incomplet")>0,"gestion_fragile","stable")))) -> vente_bloquee
A5: 1 | B5: Sainte Cloitlde | C5: LTS-001 | D5: LTS-001-004 | E5: ALAMANDAS | F5: 27 Bloc 24 Rue des Alamandas | G5: 30 | H5: 68 | I5: 24 | J5: CAZAMBO | K5: Jean François | L5: 0693137209 | O5: non | P5: Résidence exclue du dispositif de vente | Q5: non | U5: =IF(COUNTIFS(Contacts_Activation!D:D,D5,Contacts_Activation!N:N,"oui")>0,"oui","non") -> oui | V5: =IF(COUNTIFS(Travaux!C:C,D5,Travaux!X:X,"en_cours")>0,"travaux_en_cours",IF(COUNTIFS(Ventes!C:C,D5,Ventes!L:L,"signature")>0,"vente_signature",IF(COUNTIFS(Ventes!C:C,D5,Ventes!AD:AD,"oui")>0,"vente_bloquee",IF(COUNTIFS(Gestion_Locative!C:C,D5,Gestion_Locative!O:O,"incomplet")>0,"gestion_fragile","stable")))) -> vente_bloquee
A6: 1 | B6: Sainte Cloitlde | C6: LTS-001 | D6: LTS-001-005 | E6: ALAMANDAS | F6: 11 Bloc 18 Rue des Alamandas | G6: 30 | H6: 68 | I6: 24 | J6: CHANE LAW | K6: Jimmy | L6: 0692957824 | O6: non | P6: Résidence exclue du dispositif de vente | Q6: non | U6: =IF(COUNTIFS(Contacts_Activation!D:D,D6,Contacts_Activation!N:N,"oui")>0,"oui","non") -> oui | V6: =IF(COUNTIFS(Travaux!C:C,D6,Travaux!X:X,"en_cours")>0,"travaux_en_cours",IF(COUNTIFS(Ventes!C:C,D6,Ventes!L:L,"signature")>0,"vente_signature",IF(COUNTIFS(Ventes!C:C,D6,Ventes!AD:AD,"oui")>0,"vente_bloquee",IF(COUNTIFS(Gestion_Locative!C:C,D6,Gestion_Locative!O:O,"incomplet")>0,"gestion_fragile","stable")))) -> vente_bloquee
A7: 1 | B7: Sainte Cloitlde | C7: LTS-001 | D7: LTS-001-006 | E7: ALAMANDAS | F7: 24 Bloc 22 Rue des Alamandas | G7: 30 | H7: 68 | I7: 24 | J7: METELLUS | K7: Stéphane | L7: 0693044649 | O7: non | P7: Résidence exclue du dispositif de vente | Q7: non | U7: =IF(COUNTIFS(Contacts_Activation!D:D,D7,Contacts_Activation!N:N,"oui")>0,"oui","non") -> oui | V7: =IF(COUNTIFS(Travaux!C:C,D7,Travaux!X:X,"en_cours")>0,"travaux_en_cours",IF(COUNTIFS(Ventes!C:C,D7,Ventes!L:L,"signature")>0,"vente_signature",IF(COUNTIFS(Ventes!C:C,D7,Ventes!AD:AD,"oui")>0,"vente_bloquee",IF(COUNTIFS(Gestion_Locative!C:C,D7,Gestion_Locative!O:O,"incomplet")>0,"gestion_fragile","stable")))) -> vente_bloquee
A8: 1 | B8: Sainte Cloitlde | C8: LTS-001 | D8: LTS-001-007 | E8: ALAMANDAS | F8: 12 Bloc 18 Rue des Alamandas | G8: 30 | H8: 68 | I8: 24 | J8: FICHORA | K8: Armand | L8: 0262284589 | O8: non | P8: Résidence exclue du dispositif de vente | Q8: non | U8: =IF(COUNTIFS(Contacts_Activation!D:D,D8,Contacts_Activation!N:N,"oui")>0,"oui","non") -> oui | V8: =IF(COUNTIFS(Travaux!C:C,D8,Travaux!X:X,"en_cours")>0,"travaux_en_cours",IF(COUNTIFS(Ventes!C:C,D8,Ventes!L:L,"signature")>0,"vente_signature",IF(COUNTIFS(Ventes!C:C,D8,Ventes!AD:AD,"oui")>0,"vente_bloquee",IF(COUNTIFS(Gestion_Locative!C:C,D8,Gestion_Locative!O:O,"incomplet")>0,"gestion_fragile","stable")))) -> vente_bloquee
A9: 1 | B9: Sainte Cloitlde | C9: LTS-001 | D9: LTS-001-008 | E9: ALAMANDAS | F9: 29 Bloc 24 Rue des Alamandas | G9: 30 | H9: 68 | I9: 24 | J9: LOUISE | K9: Marie | L9: 0693051870 | N9: emmanuelle Boyer | O9: non | P9: Résidence exclue du dispositif de vente | Q9: non | U9: =IF(COUNTIFS(Contacts_Activation!D:D,D9,Contacts_Activation!N:N,"oui")>0,"oui","non") -> oui | V9: =IF(COUNTIFS(Travaux!C:C,D9,Travaux!X:X,"en_cours")>0,"travaux_en_cours",IF(COUNTIFS(Ventes!C:C,D9,Ventes!L:L,"signature")>0,"vente_signature",IF(COUNTIFS(Ventes!C:C,D9,Ventes!AD:AD,"oui")>0,"vente_bloquee",IF(COUNTIFS(Gestion_Locative!C:C,D9,Gestion_Locative!O:O,"incomplet")>0,"gestion_fragile","stable")))) -> vente_bloquee
A10: 1 | B10: Sainte Cloitlde | C10: LTS-001 | D10: LTS-001-009 | E10: ALAMANDAS | F10: 13 Bloc 20 Rue des Alamandas | G10: 30 | H10: 68 | I10: 24 | J10: GALTIER | K10: Rita Marie | L10: 0262293081 | M10: 0692898654 | N10: fils | O10: non | P10: Résidence exclue du dispositif de vente | Q10: non | U10: =IF(COUNTIFS(Contacts_Activation!D:D,D10,Contacts_Activation!N:N,"oui")>0,"oui","non") -> oui | V10: =IF(COUNTIFS(Travaux!C:C,D10,Travaux!X:X,"en_cours")>0,"travaux_en_cours",IF(COUNTIFS(Ventes!C:C,D10,Ventes!L:L,"signature")>0,"vente_signature",IF(COUNTIFS(Ventes!C:C,D10,Ventes!AD:AD,"oui")>0,"vente_bloquee",IF(COUNTIFS(Gestion_Locative!C:C,D10,Gestion_Locative!O:O,"incomplet")>0,"gestion_fragile","stable")))) -> vente_bloquee
A11: 1 | B11: Sainte Cloitlde | C11: LTS-001 | D11: LTS-001-010 | E11: ALAMANDAS | F11: 25 Bloc 24 Rue des Alamandas | G11: 30 | H11: 68 | I11: 24 | J11: GERVILLE | K11: Rose May | L11: 0692464983 | O11: non | P11: Résidence exclue du dispositif de vente | Q11: non | U11: =IF(COUNTIFS(Contacts_Activation!D:D,D11,Contacts_Activation!N:N,"oui")>0,"oui","non") -> oui | V11: =IF(COUNTIFS(Travaux!C:C,D11,Travaux!X:X,"en_cours")>0,"travaux_en_cours",IF(COUNTIFS(Ventes!C:C,D11,Ventes!L:L,"signature")>0,"vente_signature",IF(COUNTIFS(Ventes!C:C,D11,Ventes!AD:AD,"oui")>0,"vente_bloquee",IF(COUNTIFS(Gestion_Locative!C:C,D11,Gestion_Locative!O:O,"incomplet")>0,"gestion_fragile","stable")))) -> vente_bloquee
A12: 1 | B12: Sainte Cloitlde | C12: LTS-001 | D12: LTS-001-011 | E12: ALAMANDAS | F12: 2 Bloc 16 Rue des Alamandas | G12: 30 | H12: 68 | I12: 24 | J12: GRENIER | K12: Ruffine Marie | L12: 0262503633 | M12: 0692190983 | N12: OU | O12: non | P12: Résidence exclue du dispositif de vente | Q12: non | U12: =IF(COUNTIFS(Contacts_Activation!D:D,D12,Contacts_Activation!N:N,"oui")>0,"oui","non") -> oui | V12: =IF(COUNTIFS(Travaux!C:C,D12,Travaux!X:X,"en_cours")>0,"travaux_en_cours",IF(COUNTIFS(Ventes!C:C,D12,Ventes!L:L,"signature")>0,"vente_signature",IF(COUNTIFS(Ventes!C:C,D12,Ventes!AD:AD,"oui")>0,"vente_bloquee",IF(COUNTIFS(Gestion_Locative!C:C,D12,Gestion_Locative!O:O,"incomplet")>0,"gestion_fragile","stable")))) -> vente_bloquee
A13: 1 | B13: Sainte Cloitlde | C13: LTS-001 | D13: LTS-001-012 | E13: ALAMANDAS | F13: 4 Bloc 16 Rue des Alamandas | G13: 30 | H13: 68 | I13: 24 | J13: SAUTRON | K13: Willy David | L13: 0693634302 | M13: 0692084218 / 0692494271 | N13: Mme SAUTRON | O13: non | P13: Résidence exclue du dispositif de vente | Q13: non | U13: =IF(COUNTIFS(Contacts_Activation!D:D,D13,Contacts_Activation!N:N,"oui")>0,"oui","non") -> oui | V13: =IF(COUNTIFS(Travaux!C:C,D13,Travaux!X:X,"en_cours")>0,"travaux_en_cours",IF(COUNTIFS(Ventes!C:C,D13,Ventes!L:L,"signature")>0,"vente_signature",IF(COUNTIFS(Ventes!C:C,D13,Ventes!AD:AD,"oui")>0,"vente_bloquee",IF(COUNTIFS(Gestion_Locative!C:C,D13,Gestion_Locative!O:O,"incomplet")>0,"gestion_fragile","stable")))) -> vente_bloquee
A14: 1 | B14: Sainte Cloitlde | C14: LTS-001 | D14: LTS-001-013 | E14: ALAMANDAS | F14: 9 Bloc 18 Rue des Alamandas | G14: 30 | H14: 68 | I14: 24 | J14: LAFABLE | K14: Philippe | L14: 0692467006 | O14: non | P14: Résidence exclue du dispositif de vente | Q14: non | U14: =IF(COUNTIFS(Contacts_Activation!D:D,D14,Contacts_Activation!N:N,"oui")>0,"oui","non") -> oui | V14: =IF(COUNTIFS(Travaux!C:C,D14,Travaux!X:X,"en_cours")>0,"travaux_en_cours",IF(COUNTIFS(Ventes!C:C,D14,Ventes!L:L,"signature")>0,"vente_signature",IF(COUNTIFS(Ventes!C:C,D14,Ventes!AD:AD,"oui")>0,"vente_bloquee",IF(COUNTIFS(Gestion_Locative!C:C,D14,Gestion_Locative!O:O,"incomplet")>0,"gestion_fragile","stable")))) -> vente_bloquee
A15: 1 | B15: Sainte Cloitlde | C15: LTS-001 | D15: LTS-001-014 | E15: ALAMANDAS | F15: 14 Bloc 20 Rue des Alamandas | G15: 30 | H15: 68 | I15: 24 | J15: LAURENT | K15: Jean René | L15: 0262289120 | O15: non | P15: Résidence exclue du dispositif de vente | Q15: non | U15: =IF(COUNTIFS(Contacts_Activation!D:D,D15,Contacts_Activation!N:N,"oui")>0,"oui","non") -> oui | V15: =IF(COUNTIFS(Travaux!C:C,D15,Travaux!X:X,"en_cours")>0,"travaux_en_cours",IF(COUNTIFS(Ventes!C:C,D15,Ventes!L:L,"signature")>0,"vente_signature",IF(COUNTIFS(Ventes!C:C,D15,Ventes!AD:AD,"oui")>0,"vente_bloquee",IF(COUNTIFS(Gestion_Locative!C:C,D15,Gestion_Locative!O:O,"incomplet")>0,"gestion_fragile","stable")))) -> vente_bloquee
A16: 1 | B16: Sainte Cloitlde | C16: LTS-001 | D16: LTS-001-015 | E16: ALAMANDAS | F16: 16 Bloc 20 Rue des Alamandas | G16: 30 | H16: 68 | I16: 24 | J16: LAURENT | K16: Jean Bernard | L16: 0692916258 | O16: non | P16: Résidence exclue du dispositif de vente | Q16: non | U16: =IF(COUNTIFS(Contacts_Activation!D:D,D16,Contacts_Activation!N:N,"oui")>0,"oui","non") -> oui | V16: =IF(COUNTIFS(Travaux!C:C,D16,Travaux!X:X,"en_cours")>0,"travaux_en_cours",IF(COUNTIFS(Ventes!C:C,D16,Ventes!L:L,"signature")>0,"vente_signature",IF(COUNTIFS(Ventes!C:C,D16,Ventes!AD:AD,"oui")>0,"vente_bloquee",IF(COUNTIFS(Gestion_Locative!C:C,D16,Gestion_Locative!O:O,"incomplet")>0,"gestion_fragile","stable")))) -> vente_bloquee
A17: 1 | B17: Sainte Cloitlde | C17: LTS-001 | D17: LTS-001-016 | E17: ALAMANDAS | F17: 3 Bloc 16 Rue des Alamandas | G17: 30 | H17: 68 | I17: 24 | J17: MARKA | K17: Claude | L17: 0692906779 | O17: non | P17: Résidence exclue du dispositif de vente | Q17: non | U17: =IF(COUNTIFS(Contacts_Activation!D:D,D17,Contacts_Activation!N:N,"oui")>0,"oui","non") -> oui | V17: =IF(COUNTIFS(Travaux!C:C,D17,Travaux!X:X,"en_cours")>0,"travaux_en_cours",IF(COUNTIFS(Ventes!C:C,D17,Ventes!L:L,"signature")>0,"vente_signature",IF(COUNTIFS(Ventes!C:C,D17,Ventes!AD:AD,"oui")>0,"vente_bloquee",IF(COUNTIFS(Gestion_Locative!C:C,D17,Gestion_Locative!O:O,"incomplet")>0,"gestion_fragile","stable")))) -> vente_bloquee
A18: 1 | B18: Sainte Cloitlde | C18: LTS-001 | D18: LTS-001-017 | E18: ALAMANDAS | F18: 30 Bloc 24 Rue des Alamandas | G18: 30 | H18: 68 | I18: 24 | J18: MOUTOUSSAMY | K18: Jacques Antoine | L18: 0692807626 | M18: 0262190122 | O18: non | P18: Résidence exclue du dispositif de vente | Q18: non | U18: =IF(COUNTIFS(Contacts_Activation!D:D,D18,Contacts_Activation!N:N,"oui")>0,"oui","non") -> oui | V18: =IF(COUNTIFS(Travaux!C:C,D18,Travaux!X:X,"en_cours")>0,"travaux_en_cours",IF(COUNTIFS(Ventes!C:C,D18,Ventes!L:L,"signature")>0,"vente_signature",IF(COUNTIFS(Ventes!C:C,D18,Ventes!AD:AD,"oui")>0,"vente_bloquee",IF(COUNTIFS(Gestion_Locative!C:C,D18,Gestion_Locative!O:O,"incomplet")>0,"gestion_fragile","stable")))) -> vente_bloquee
A19: 1 | B19: Sainte Cloitlde | C19: LTS-001 | D19: LTS-001-018 | E19: ALAMANDAS | F19: 20 Bloc 22 Rue des Alamandas | G19: 30 | H19: 68 | I19: 24 | J19: PAYET | K19: Josiane Aline | L19: 0262504956 | M19: 0692677087 | O19: non | P19: Résidence exclue du dispositif de vente | Q19: non | U19: =IF(COUNTIFS(Contacts_Activation!D:D,D19,Contacts_Activation!N:N,"oui")>0,"oui","non") -> oui | V19: =IF(COUNTIFS(Travaux!C:C,D19,Travaux!X:X,"en_cours")>0,"travaux_en_cours",IF(COUNTIFS(Ventes!C:C,D19,Ventes!L:L,"signature")>0,"vente_signature",IF(COUNTIFS(Ventes!C:C,D19,Ventes!AD:AD,"oui")>0,"vente_bloquee",IF(COUNTIFS(Gestion_Locative!C:C,D19,Gestion_Locative!O:O,"incomplet")>0,"gestion_fragile","stable")))) -> vente_bloquee
A20: 1 | B20: Sainte Cloitlde | C20: LTS-001 | D20: LTS-001-019 | E20: ALAMANDAS | F20: 8 Bloc 18 Rue des Alamandas | G20: 30 | H20: 68 | I20: 24 | J20: ROBERT | K20: Jean Patrick | L20: 0692668371 | M20: 0692916112 | O20: non | P20: Résidence exclue du dispositif de vente | Q20: non | U20: =IF(COUNTIFS(Contacts_Activation!D:D,D20,Contacts_Activation!N:N,"oui")>0,"oui","non") -> oui | V20: =IF(COUNTIFS(Travaux!C:C,D20,Travaux!X:X,"en_cours")>0,"travaux_en_cours",IF(COUNTIFS(Ventes!C:C,D20,Ventes!L:L,"signature")>0,"vente_signature",IF(COUNTIFS(Ventes!C:C,D20,Ventes!AD:AD,"oui")>0,"vente_bloquee",IF(COUNTIFS(Gestion_Locative!C:C,D20,Gestion_Locative!O:O,"incomplet")>0,"gestion_fragile","stable")))) -> vente_bloquee
A21: 1 | B21: Sainte Cloitlde | C21: LTS-001 | D21: LTS-001-020 | E21: ALAMANDAS | F21: 5 Bloc 16 Rue des Alamandas | G21: 30 | H21: 68 | I21: 24 | J21: REFANE | K21: Marie Virginie | L21: 0692860902 | O21: non | P21: Résidence exclue du dispositif de vente | Q21: non | U21: =IF(COUNTIFS(Contacts_Activation!D:D,D21,Contacts_Activation!N:N,"oui")>0,"oui","non") -> oui | V21: =IF(COUNTIFS(Travaux!C:C,D21,Travaux!X:X,"en_cours")>0,"travaux_en_cours",IF(COUNTIFS(Ventes!C:C,D21,Ventes!L:L,"signature")>0,"vente_signature",IF(COUNTIFS(Ventes!C:C,D21,Ventes!AD:AD,"oui")>0,"vente_bloquee",IF(COUNTIFS(Gestion_Locative!C:C,D21,Gestion_Locative!O:O,"incomplet")>0,"gestion_fragile","stable")))) -> vente_bloquee
A22: 1 | B22: Sainte Cloitlde | C22: LTS-001 | D22: LTS-001-021 | E22: ALAMANDAS | F22: 6 Bloc 16 Rue des Alamandas | G22: 30 | H22: 68 | I22: 24 | J22: SINAPAYEN SINAMALE | K22: Henriette | L22: 0693860123 | M22: 0692143045 | N22: petit fils | O22: non | P22: Résidence exclue du dispositif de vente | Q22: non | U22: =IF(COUNTIFS(Contacts_Activation!D:D,D22,Contacts_Activation!N:N,"oui")>0,"oui","non") -> oui | V22: =IF(COUNTIFS(Travaux!C:C,D22,Travaux!X:X,"en_cours")>0,"travaux_en_cours",IF(COUNTIFS(Ventes!C:C,D22,Ventes!L:L,"signature")>0,"vente_signature",IF(COUNTIFS(Ventes!C:C,D22,Ventes!AD:AD,"oui")>0,"vente_bloquee",IF(COUNTIFS(Gestion_Locative!C:C,D22,Gestion_Locative!O:O,"incomplet")>0,"gestion_fragile","stable")))) -> vente_bloquee
A23: 1 | B23: Sainte Cloitlde | C23: LTS-001 | D23: LTS-001-022 | E23: ALAMANDAS | F23: 7 Bloc 18 Rue des Alamandas | G23: 30 | H23: 68 | I23: 24 | J23: MARKA | K23: GREGORY | L23: 0692843883 | O23: non | P23: Résidence exclue du dispositif de vente | Q23: non | U23: =IF(COUNTIFS(Contacts_Activation!D:D,D23,Contacts_Activation!N:N,"oui")>0,"oui","non") -> oui | V23: =IF(COUNTIFS(Travaux!C:C,D23,Travaux!X:X,"en_cours")>0,"travaux_en_cours",IF(COUNTIFS(Ventes!C:C,D23,Ventes!L:L,"signature")>0,"vente_signature",IF(COUNTIFS(Ventes!C:C,D23,Ventes!AD:AD,"oui")>0,"vente_bloquee",IF(COUNTIFS(Gestion_Locative!C:C,D23,Gestion_Locative!O:O,"incomplet")>0,"gestion_fragile","stable")))) -> vente_bloquee
A24: 1 | B24: Sainte Cloitlde | C24: LTS-001 | D24: LTS-001-023 | E24: ALAMANDAS | F24: 10 Bloc 18 Rue des Alamandas | G24: 30 | H24: 68 | I24: 24 | J24: TECHER | K24: Jean Fabrice | L24: 0693546553 | N24: GALAOR SQUATEUR | O24: non | P24: Résidence exclue du dispositif de vente | Q24: non | U24: =IF(COUNTIFS(Contacts_Activation!D:D,D24,Contacts_Activation!N:N,"oui")>0,"oui","non") -> oui | V24: =IF(COUNTIFS(Travaux!C:C,D24,Travaux!X:X,"en_cours")>0,"travaux_en_cours",IF(COUNTIFS(Ventes!C:C,D24,Ventes!L:L,"signature")>0,"vente_signature",IF(COUNTIFS(Ventes!C:C,D24,Ventes!AD:AD,"oui")>0,"vente_bloquee",IF(COUNTIFS(Gestion_Locative!C:C,D24,Gestion_Locative!O:O,"incomplet")>0,"gestion_fragile","stable")))) -> vente_bloquee
A25: 1 | B25: Sainte Cloitlde | C25: LTS-001 | D25: LTS-001-024 | E25: ALAMANDAS | F25: 1 Bloc 16 Rue des Alamandas | G25: 30 | H25: 68 | I25: 24 | J25: TECHER | K25: Joseph Francis | L25: 0692487884 | O25: non | P25: Résidence exclue du dispositif de vente | Q25: non | U25: =IF(COUNTIFS(Contacts_Activation!D:D,D25,Contacts_Activation!N:N,"oui")>0,"oui","non") -> oui | V25: =IF(COUNTIFS(Travaux!C:C,D25,Travaux!X:X,"en_cours")>0,"travaux_en_cours",IF(COUNTIFS(Ventes!C:C,D25,Ventes!L:L,"signature")>0,"vente_signature",IF(COUNTIFS(Ventes!C:C,D25,Ventes!AD:AD,"oui")>0,"vente_bloquee",IF(COUNTIFS(Gestion_Locative!C:C,D25,Gestion_Locative!O:O,"incomplet")>0,"gestion_fragile","stable")))) -> vente_bloquee
A26: 1 | B26: Sainte Cloitlde | C26: LTS-001 | D26: LTS-001-025 | E26: ALAMANDAS | F26: 23 Bloc 22 Rue des Alamandas | G26: 30 | H26: 68 | I26: 24 | J26: VIRAPIN CAROUMBIN | K26: Marie-Josée | L26: 0692689202 | O26: non | P26: Résidence exclue du dispositif de vente | Q26: non | U26: =IF(COUNTIFS(Contacts_Activation!D:D,D26,Contacts_Activation!N:N,"oui")>0,"oui","non") -> oui | V26: =IF(COUNTIFS(Travaux!C:C,D26,Travaux!X:X,"en_cours")>0,"travaux_en_cours",IF(COUNTIFS(Ventes!C:C,D26,Ventes!L:L,"signature")>0,"vente_signature",IF(COUNTIFS(Ventes!C:C,D26,Ventes!AD:AD,"oui")>0,"vente_bloquee",IF(COUNTIFS(Gestion_Locative!C:C,D26,Gestion_Locative!O:O,"incomplet")>0,"gestion_fragile","stable")))) -> vente_bloquee
A27: 1 | B27: Sainte Cloitlde | C27: LTS-001 | D27: LTS-001-026 | E27: ALAMANDAS | F27: 17 Bloc 20 Rue des Alamandas | G27: 30 | H27: 68 | I27: 24 | J27: CORRE | K27: Laurianne Emmanuelle | L27: 0692842718 | M27: 0692341364 | N27: PÈRE | MERE | O27: non | P27: Résidence exclue du dispositif de vente | Q27: non | U27: =IF(COUNTIFS(Contacts_Activation!D:D,D27,Contacts_Activation!N:N,"oui")>0,"oui","non") -> oui | V27: =IF(COUNTIFS(Travaux!C:C,D27,Travaux!X:X,"en_cours")>0,"travaux_en_cours",IF(COUNTIFS(Ventes!C:C,D27,Ventes!L:L,"signature")>0,"vente_signature",IF(COUNTIFS(Ventes!C:C,D27,Ventes!AD:AD,"oui")>0,"vente_bloquee",IF(COUNTIFS(Gestion_Locative!C:C,D27,Gestion_Locative!O:O,"incomplet")>0,"gestion_fragile","stable")))) -> vente_bloquee
A28: 1 | B28: Sainte Cloitlde | C28: LTS-001 | D28: LTS-001-027 | E28: ALAMANDAS | F28: 21 Bloc 22 Rue des Alamandas | G28: 30 | H28: 68 | I28: 24 | J28: SEVERIN | K28: André Claude | L28: 0692922924 | M28: 0693283029 / 0692661125 | N28: sa fille | severin | O28: non | P28: Résidence exclue du dispositif de vente | Q28: non | U28: =IF(COUNTIFS(Contacts_Activation!D:D,D28,Contacts_Activation!N:N,"oui")>0,"oui","non") -> oui | V28: =IF(COUNTIFS(Travaux!C:C,D28,Travaux!X:X,"en_cours")>0,"travaux_en_cours",IF(COUNTIFS(Ventes!C:C,D28,Ventes!L:L,"signature")>0,"vente_signature",IF(COUNTIFS(Ventes!C:C,D28,Ventes!AD:AD,"oui")>0,"vente_bloquee",IF(COUNTIFS(Gestion_Locative!C:C,D28,Gestion_Locative!O:O,"incomplet")>0,"gestion_fragile","stable")))) -> vente_bloquee
A29: 1 | B29: Sainte Cloitlde | C29: LTS-001 | D29: LTS-001-028 | E29: ALAMANDAS | F29: 22 Bloc 22 Rue des Alamandas | G29: 30 | H29: 68 | I29: 24 | J29: LAURENT | K29: Thomas | L29: 0692139045 | O29: non | P29: Résidence exclue du dispositif de vente | Q29: non | U29: =IF(COUNTIFS(Contacts_Activation!D:D,D29,Contacts_Activation!N:N,"oui")>0,"oui","non") -> oui | V29: =IF(COUNTIFS(Travaux!C:C,D29,Travaux!X:X,"en_cours")>0,"travaux_en_cours",IF(COUNTIFS(Ventes!C:C,D29,Ventes!L:L,"signature")>0,"vente_signature",IF(COUNTIFS(Ventes!C:C,D29,Ventes!AD:AD,"oui")>0,"vente_bloquee",IF(COUNTIFS(Gestion_Locative!C:C,D29,Gestion_Locative!O:O,"incomplet")>0,"gestion_fragile","stable")))) -> vente_bloquee
A30: 1 | B30: Sainte Cloitlde | C30: LTS-001 | D30: LTS-001-029 | E30: ALAMANDAS | F30: 28 Bloc 24 Rue des Alamandas | G30: 30 | H30: 68 | I30: 24 | J30: LAURENT | K30: Jean Alain | L30: 0692590826 | M30: 0692946258 / 0693823305 | O30: non | P30: Résidence exclue du dispositif de vente | Q30: non | U30: =IF(COUNTIFS(Contacts_Activation!D:D,D30,Contacts_Activation!N:N,"oui")>0,"oui","non") -> oui | V30: =IF(COUNTIFS(Travaux!C:C,D30,Travaux!X:X,"en_cours")>0,"travaux_en_cours",IF(COUNTIFS(Ventes!C:C,D30,Ventes!L:L,"signature")>0,"vente_signature",IF(COUNTIFS(Ventes!C:C,D30,Ventes!AD:AD,"oui")>0,"vente_bloquee",IF(COUNTIFS(Gestion_Locative!C:C,D30,Gestion_Locative!O:O,"incomplet")>0,"gestion_fragile","stable")))) -> vente_bloquee
A31: 1 | B31: Sainte Cloitlde | C31: LTS-001 | D31: LTS-001-030 | E31: ALAMANDAS | F31: 18 Bloc 20 Rue des Alamandas | G31: 30 | H31: 68 | I31: 24 | J31: FIBAC | K31: Marie Hélène | L31: 0692660767 | O31: non | P31: Résidence exclue du dispositif de vente | Q31: non | U31: =IF(COUNTIFS(Contacts_Activation!D:D,D31,Contacts_Activation!N:N,"oui")>0,"oui","non") -> oui | V31: =IF(COUNTIFS(Travaux!C:C,D31,Travaux!X:X,"en_cours")>0,"travaux_en_cours",IF(COUNTIFS(Ventes!C:C,D31,Ventes!L:L,"signature")>0,"vente_signature",IF(COUNTIFS(Ventes!C:C,D31,Ventes!AD:AD,"oui")>0,"vente_bloquee",IF(COUNTIFS(Gestion_Locative!C:C,D31,Gestion_Locative!O:O,"incomplet")>0,"gestion_fragile","stable")))) -> vente_bloquee
A32: 1 | B32: Prima | C32: LTS-002 | D32: LTS-002-001 | E32: ATTES | F32: 37 Rue du Stade de L'Est | G32: 3 | H32: 75 | I32: 35 | J32: ANDRIANA | K32: Marie Françoise | L32: 0693525546 | M32: 0692547291 | N32: PIERRE ALFLECHE | O32: oui | Q32: non | U32: =IF(COUNTIFS(Contacts_Activation!D:D,D32,Contacts_Activation!N:N,"oui")>0,"oui","non") -> oui | V32: =IF(COUNTIFS(Travaux!C:C,D32,Travaux!X:X,"en_cours")>0,"travaux_en_cours",IF(COUNTIFS(Ventes!C:C,D32,Ventes!L:L,"signature")>0,"vente_signature",IF(COUNTIFS(Ventes!C:C,D32,Ventes!AD:AD,"oui")>0,"vente_bloquee",IF(COUNTIFS(Gestion_Locative!C:C,D32,Gestion_Locative!O:O,"incomplet")>0,"gestion_fragile","stable")))) -> vente_bloquee
A33: 1 | B33: Prima | C33: LTS-002 | D33: LTS-002-002 | E33: ATTES | F33: 23 Rue des Lavandières | G33: 3 | H33: 75 | I33: 35 | J33: HIVANHOE | K33: Jean Patrick | L33: 0262902947 | N33: UDAF | O33: oui | Q33: non | U33: =IF(COUNTIFS(Contacts_Activation!D:D,D33,Contacts_Activation!N:N,"oui")>0,"oui","non") -> oui | V33: =IF(COUNTIFS(Travaux!C:C,D33,Travaux!X:X,"en_cours")>0,"travaux_en_cours",IF(COUNTIFS(Ventes!C:C,D33,Ventes!L:L,"signature")>0,"vente_signature",IF(COUNTIFS(Ventes!C:C,D33,Ventes!AD:AD,"oui")>0,"vente_bloquee",IF(COUNTIFS(Gestion_Locative!C:C,D33,Gestion_Locative!O:O,"incomplet")>0,"gestion_fragile","stable")))) -> vente_bloquee
A34: 1 | B34: Prima | C34: LTS-002 | D34: LTS-002-003 | E34: ATTES | F34: 11 Rue des Lavandières | G34: 3 | H34: 75 | I34: 35 | J34: MASSEAUX | K34: Clarisse Alida | L34: 0692260455 | O34: oui | Q34: non | U34: =IF(COUNTIFS(Contacts_Activation!D:D,D34,Contacts_Activation!N:N,"oui")>0,"oui","non") -> oui | V34: =IF(COUNTIFS(Travaux!C:C,D34,Travaux!X:X,"en_cours")>0,"travaux_en_cours",IF(COUNTIFS(Ventes!C:C,D34,Ventes!L:L,"signature")>0,"vente_signature",IF(COUNTIFS(Ventes!C:C,D34,Ventes!AD:AD,"oui")>0,"vente_bloquee",IF(COUNTIFS(Gestion_Locative!C:C,D34,Gestion_Locative!O:O,"incomplet")>0,"gestion_fragile","stable")))) -> vente_bloquee
A35: 3 | B35: Le Brulé | C35: LTS-003 | D35: LTS-003-001 | E35: AZALEES | F35: 107 Route des Azalées | G35: 4 | H35: 48 | I35: 58 | J35: IMAHO | K35: Emmanuelle Anne Gaëlle | L35: 0692631658 | M35: 0693111634 | N35: NUM W | O35: oui | Q35: non | U35: =IF(COUNTIFS(Contacts_Activation!D:D,D35,Contacts_Activation!N:N,"oui")>0,"oui","non") -> oui | V35: =IF(COUNTIFS(Travaux!C:C,D35,Travaux!X:X,"en_cours")>0,"travaux_en_cours",IF(COUNTIFS(Ventes!C:C,D35,Ventes!L:L,"signature")>0,"vente_signature",IF(COUNTIFS(Ventes!C:C,D35,Ventes!AD:AD,"oui")>0,"vente_bloquee",IF(COUNTIFS(Gestion_Locative!C:C,D35,Gestion_Locative!O:O,"incomplet")>0,"gestion_fragile","stable")))) -> vente_bloquee
A36: 3 | B36: Le Brulé | C36: LTS-003 | D36: LTS-003-002 | E36: AZALEES | F36: 111 Route des Azalées | G36: 4 | H36: 48 | I36: 58 | J36: IFIANTEPIA | K36: occupé en attente decision | L36: 0692229197 | O36: oui | Q36: non | U36: =IF(COUNTIFS(Contacts_Activation!D:D,D36,Contacts_Activation!N:N,"oui")>0,"oui","non") -> oui | V36: =IF(COUNTIFS(Travaux!C:C,D36,Travaux!X:X,"en_cours")>0,"travaux_en_cours",IF(COUNTIFS(Ventes!C:C,D36,Ventes!L:L,"signature")>0,"vente_signature",IF(COUNTIFS(Ventes!C:C,D36,Ventes!AD:AD,"oui")>0,"vente_bloquee",IF(COUNTIFS(Gestion_Locative!C:C,D36,Gestion_Locative!O:O,"incomplet")>0,"gestion_fragile","stable")))) -> vente_bloquee
A37: 3 | B37: Le Brulé | C37: LTS-003 | D37: LTS-003-003 | E37: AZALEES | F37: 107 ter Route des Azalées | G37: 4 | H37: 48 | I37: 58 | J37: THOMAS NÉE TURPIN | K37: Marie Micheline | L37: 0692587339 | O37: oui | Q37: non | U37: =IF(COUNTIFS(Contacts_Activation!D:D,D37,Contacts_Activation!N:N,"oui")>0,"oui","non") -> oui | V37: =IF(COUNTIFS(Travaux!C:C,D37,Travaux!X:X,"en_cours")>0,"travaux_en_cours",IF(COUNTIFS(Ventes!C:C,D37,Ventes!L:L,"signature")>0,"vente_signature",IF(COUNTIFS(Ventes!C:C,D37,Ventes!AD:AD,"oui")>0,"vente_bloquee",IF(COUNTIFS(Gestion_Locative!C:C,D37,Gestion_Locative!O:O,"incomplet")>0,"gestion_fragile","stable")))) -> vente_bloquee
A38: 3 | B38: Le Brulé | C38: LTS-003 | D38: LTS-003-004 | E38: AZALEES | F38: 107 bis Route des Azalées | G38: 4 | H38: 48 | I38: 58 | J38: POLEYA | K38: Joachim | L38: 0692743656 | O38: oui | Q38: non | U38: =IF(COUNTIFS(Contacts_Activation!D:D,D38,Contacts_Activation!N:N,"oui")>0,"oui","non") -> oui | V38: =IF(COUNTIFS(Travaux!C:C,D38,Travaux!X:X,"en_cours")>0,"travaux_en_cours",IF(COUNTIFS(Ventes!C:C,D38,Ventes!L:L,"signature")>0,"vente_signature",IF(COUNTIFS(Ventes!C:C,D38,Ventes!AD:AD,"oui")>0,"vente_bloquee",IF(COUNTIFS(Gestion_Locative!C:C,D38,Gestion_Locative!O:O,"incomplet")>0,"gestion_fragile","stable")))) -> vente_bloquee
A39: 2 | B39: Marcadet | C39: LTS-004 | D39: LTS-004-001 | E39: BARBADINES | F39: 65 Ruelle Marcadet | G39: 25 | H39: 57 | I39: 20 | J39: ABDALAH BEDANI | K39: Marie Thérèse | L39: 0692128814 | O39: oui | Q39: non | U39: =IF(COUNTIFS(Contacts_Activation!D:D,D39,Contacts_Activation!N:N,"oui")>0,"oui","non") -> oui | V39: =IF(COUNTIFS(Travaux!C:C,D39,Travaux!X:X,"en_cours")>0,"travaux_en_cours",IF(COUNTIFS(Ventes!C:C,D39,Ventes!L:L,"signature")>0,"vente_signature",IF(COUNTIFS(Ventes!C:C,D39,Ventes!AD:AD,"oui")>0,"vente_bloquee",IF(COUNTIFS(Gestion_Locative!C:C,D39,Gestion_Locative!O:O,"incomplet")>0,"gestion_fragile","stable")))) -> vente_bloquee
A40: 2 | B40: Marcadet | C40: LTS-004 | D40: LTS-004-002 | E40: BARBADINES | F40: 45 Ruelle Marcadet | G40: 25 | H40: 57 | I40: 20 | J40: MAILLOT | L40: 0692209721 | O40: oui | Q40: non | U40: =IF(COUNTIFS(Contacts_Activation!D:D,D40,Contacts_Activation!N:N,"oui")>0,"oui","non") -> oui | V40: =IF(COUNTIFS(Travaux!C:C,D40,Travaux!X:X,"en_cours")>0,"travaux_en_cours",IF(COUNTIFS(Ventes!C:C,D40,Ventes!L:L,"signature")>0,"vente_signature",IF(COUNTIFS(Ventes!C:C,D40,Ventes!AD:AD,"oui")>0,"vente_bloquee",IF(COUNTIFS(Gestion_Locative!C:C,D40,Gestion_Locative!O:O,"incomplet")>0,"gestion_fragile","stable")))) -> vente_bloquee
A41: 2 | B41: Marcadet | C41: LTS-004 | D41: LTS-004-003 | E41: BARBADINES | F41: 25 Ruelle Marcadet | G41: 25 | H41: 57 | I41: 20 | J41: CARPIN VELLEYEN | K41: Maximin | L41: 0692353423 | M41: 0692326054 / 0692362257 | N41: VINCENT 61 44 | O41: oui | Q41: non | U41: =IF(COUNTIFS(Contacts_Activation!D:D,D41,Contacts_Activation!N:N,"oui")>0,"oui","non") -> oui | V41: =IF(COUNTIFS(Travaux!C:C,D41,Travaux!X:X,"en_cours")>0,"travaux_en_cours",IF(COUNTIFS(Ventes!C:C,D41,Ventes!L:L,"signature")>0,"vente_signature",IF(COUNTIFS(Ventes!C:C,D41,Ventes!AD:AD,"oui")>0,"vente_bloquee",IF(COUNTIFS(Gestion_Locative!C:C,D41,Gestion_Locative!O:O,"incomplet")>0,"gestion_fragile","stable")))) -> vente_bloquee
A42: 2 | B42: Marcadet | C42: LTS-004 | D42: LTS-004-004 | E42: BARBADINES | F42: 47 Ruelle Marcadet | G42: 25 | H42: 57 | I42: 20 | J42: CLAIN | K42: Christian Daniel | L42: 0692102185 | O42: oui | Q42: non | U42: =IF(COUNTIFS(Contacts_Activation!D:D,D42,Contacts_Activation!N:N,"oui")>0,"oui","non") -> oui | V42: =IF(COUNTIFS(Travaux!C:C,D42,Travaux!X:X,"en_cours")>0,"travaux_en_cours",IF(COUNTIFS(Ventes!C:C,D42,Ventes!L:L,"signature")>0,"vente_signature",IF(COUNTIFS(Ventes!C:C,D42,Ventes!AD:AD,"oui")>0,"vente_bloquee",IF(COUNTIFS(Gestion_Locative!C:C,D42,Gestion_Locative!O:O,"incomplet")>0,"gestion_fragile","stable")))) -> vente_bloquee
A43: 2 | B43: Marcadet | C43: LTS-004 | D43: LTS-004-005 | E43: BARBADINES | F43: 21 Ruelle Marcadet | G43: 25 | H43: 57 | I43: 20 | J43: ELEONORE | K43: Yves Joseph | L43: 0692517903 | O43: oui | Q43: non | U43: =IF(COUNTIFS(Contacts_Activation!D:D,D43,Contacts_Activation!N:N,"oui")>0,"oui","non") -> oui | V43: =IF(COUNTIFS(Travaux!C:C,D43,Travaux!X:X,"en_cours")>0,"travaux_en_cours",IF(COUNTIFS(Ventes!C:C,D43,Ventes!L:L,"signature")>0,"vente_signature",IF(COUNTIFS(Ventes!C:C,D43,Ventes!AD:AD,"oui")>0,"vente_bloquee",IF(COUNTIFS(Gestion_Locative!C:C,D43,Gestion_Locative!O:O,"incomplet")>0,"gestion_fragile","stable")))) -> vente_bloquee
A44: 2 | B44: Marcadet | C44: LTS-004 | D44: LTS-004-006 | E44: BARBADINES | F44: 63 Ruelle Marcadet | G44: 25 | H44: 57 | I44: 20 | J44: ERINACINT | K44: Marie Régine | O44: oui | Q44: non | U44: =IF(COUNTIFS(Contacts_Activation!D:D,D44,Contacts_Activation!N:N,"oui")>0,"oui","non") -> oui | V44: =IF(COUNTIFS(Travaux!C:C,D44,Travaux!X:X,"en_cours")>0,"travaux_en_cours",IF(COUNTIFS(Ventes!C:C,D44,Ventes!L:L,"signature")>0,"vente_signature",IF(COUNTIFS(Ventes!C:C,D44,Ventes!AD:AD,"oui")>0,"vente_bloquee",IF(COUNTIFS(Gestion_Locative!C:C,D44,Gestion_Locative!O:O,"incomplet")>0,"gestion_fragile","stable")))) -> vente_bloquee
A45: 2 | B45: Marcadet | C45: LTS-004 | D45: LTS-004-007 | E45: BARBADINES | F45: 9 Ruelle Marcadet | G45: 25 | H45: 57 | I45: 20 | J45: ESPARON | K45: Marie Rose Andrée | L45: 0262418046 | O45: oui | Q45: non | U45: =IF(COUNTIFS(Contacts_Activation!D:D,D45,Contacts_Activation!N:N,"oui")>0,"oui","non") -> oui | V45: =IF(COUNTIFS(Travaux!C:C,D45,Travaux!X:X,"en_cours")>0,"travaux_en_cours",IF(COUNTIFS(Ventes!C:C,D45,Ventes!L:L,"signature")>0,"vente_signature",IF(COUNTIFS(Ventes!C:C,D45,Ventes!AD:AD,"oui")>0,"vente_bloquee",IF(COUNTIFS(Gestion_Locative!C:C,D45,Gestion_Locative!O:O,"incomplet")>0,"gestion_fragile","stable")))) -> vente_bloquee
A46: 2 | B46: Marcadet | C46: LTS-004 | D46: LTS-004-008 | E46: BARBADINES | F46: 61 Ruelle Marcadet | G46: 25 | H46: 57 | I46: 20 | J46: GRONDIN | K46: Joseph Jean Yves | L46: 0693945329 | M46: 0692769137 | N46: LA FILLE | O46: oui | Q46: non | U46: =IF(COUNTIFS(Contacts_Activation!D:D,D46,Contacts_Activation!N:N,"oui")>0,"oui","non") -> oui | V46: =IF(COUNTIFS(Travaux!C:C,D46,Travaux!X:X,"en_cours")>0,"travaux_en_cours",IF(COUNTIFS(Ventes!C:C,D46,Ventes!L:L,"signature")>0,"vente_signature",IF(COUNTIFS(Ventes!C:C,D46,Ventes!AD:AD,"oui")>0,"vente_bloquee",IF(COUNTIFS(Gestion_Locative!C:C,D46,Gestion_Locative!O:O,"incomplet")>0,"gestion_fragile","stable")))) -> vente_bloquee
A47: 2 | B47: Marcadet | C47: LTS-004 | D47: LTS-004-009 | E47: BARBADINES | F47: 55 Ruelle Marcadet | G47: 25 | H47: 57 | I47: 20 | J47: IBRAHIM | K47: Yousouf | L47: 0693850799 | M47: 0262415521 | N47: LA FILLE FIXE | O47: oui | Q47: non | U47: =IF(COUNTIFS(Contacts_Activation!D:D,D47,Contacts_Activation!N:N,"oui")>0,"oui","non") -> oui | V47: =IF(COUNTIFS(Travaux!C:C,D47,Travaux!X:X,"en_cours")>0,"travaux_en_cours",IF(COUNTIFS(Ventes!C:C,D47,Ventes!L:L,"signature")>0,"vente_signature",IF(COUNTIFS(Ventes!C:C,D47,Ventes!AD:AD,"oui")>0,"vente_bloquee",IF(COUNTIFS(Gestion_Locative!C:C,D47,Gestion_Locative!O:O,"incomplet")>0,"gestion_fragile","stable")))) -> vente_bloquee
A48: 2 | B48: Marcadet | C48: LTS-004 | D48: LTS-004-010 | E48: BARBADINES | F48: 41 Ruelle Marcadet | G48: 25 | H48: 57 | I48: 20 | J48: JOVIEN | K48: Marie Denise | L48: 0692218923 | O48: oui | Q48: non | U48: =IF(COUNTIFS(Contacts_Activation!D:D,D48,Contacts_Activation!N:N,"oui")>0,"oui","non") -> oui | V48: =IF(COUNTIFS(Travaux!C:C,D48,Travaux!X:X,"en_cours")>0,"travaux_en_cours",IF(COUNTIFS(Ventes!C:C,D48,Ventes!L:L,"signature")>0,"vente_signature",IF(COUNTIFS(Ventes!C:C,D48,Ventes!AD:AD,"oui")>0,"vente_bloquee",IF(COUNTIFS(Gestion_Locative!C:C,D48,Gestion_Locative!O:O,"incomplet")>0,"gestion_fragile","stable")))) -> vente_bloquee
A49: 2 | B49: Marcadet | C49: LTS-004 | D49: LTS-004-011 | E49: BARBADINES | F49: 53 Ruelle Marcadet | G49: 25 | H49: 57 | I49: 20 | J49: KAVO | K49: Marie Françoise | L49: 0692754305 | O49: oui | Q49: non | U49: =IF(COUNTIFS(Contacts_Activation!D:D,D49,Contacts_Activation!N:N,"oui")>0,"oui","non") -> oui | V49: =IF(COUNTIFS(Travaux!C:C,D49,Travaux!X:X,"en_cours")>0,"travaux_en_cours",IF(COUNTIFS(Ventes!C:C,D49,Ventes!L:L,"signature")>0,"vente_signature",IF(COUNTIFS(Ventes!C:C,D49,Ventes!AD:AD,"oui")>0,"vente_bloquee",IF(COUNTIFS(Gestion_Locative!C:C,D49,Gestion_Locative!O:O,"incomplet")>0,"gestion_fragile","stable")))) -> vente_bloquee
A50: 2 | B50: Marcadet | C50: LTS-004 | D50: LTS-004-012 | E50: BARBADINES | F50: 69 Ruelle Marcadet | G50: 25 | H50: 57 | I50: 20 | J50: LAVAL | K50: Yvette Marie Céline | L50: 0693017032 | M50: 0692934231 | N50: Jenifer | O50: oui | Q50: non | U50: =IF(COUNTIFS(Contacts_Activation!D:D,D50,Contacts_Activation!N:N,"oui")>0,"oui","non") -> oui | V50: =IF(COUNTIFS(Travaux!C:C,D50,Travaux!X:X,"en_cours")>0,"travaux_en_cours",IF(COUNTIFS(Ventes!C:C,D50,Ventes!L:L,"signature")>0,"vente_signature",IF(COUNTIFS(Ventes!C:C,D50,Ventes!AD:AD,"oui")>0,"vente_bloquee",IF(COUNTIFS(Gestion_Locative!C:C,D50,Gestion_Locative!O:O,"incomplet")>0,"gestion_fragile","stable")))) -> vente_bloquee
A51: 2 | B51: Marcadet | C51: LTS-004 | D51: LTS-004-013 | E51: BARBADINES | F51: 33 Ruelle Marcadet | G51: 25 | H51: 57 | I51: 20 | J51: MADJINDA | K51: Halima | L51: 0693206157 | O51: oui | Q51: non | U51: =IF(COUNTIFS(Contacts_Activation!D:D,D51,Contacts_Activation!N:N,"oui")>0,"oui","non") -> oui | V51: =IF(COUNTIFS(Travaux!C:C,D51,Travaux!X:X,"en_cours")>0,"travaux_en_cours",IF(COUNTIFS(Ventes!C:C,D51,Ventes!L:L,"signature")>0,"vente_signature",IF(COUNTIFS(Ventes!C:C,D51,Ventes!AD:AD,"oui")>0,"vente_bloquee",IF(COUNTIFS(Gestion_Locative!C:C,D51,Gestion_Locative!O:O,"incomplet")>0,"gestion_fragile","stable")))) -> vente_bloquee
A52: 2 | B52: Marcadet | C52: LTS-004 | D52: LTS-004-014 | E52: BARBADINES | F52: 71 Ruelle Marcadet | G52: 25 | H52: 57 | I52: 20 | J52: MARKA | K52: Marie Mélanie | O52: oui | Q52: non | U52: =IF(COUNTIFS(Contacts_Activation!D:D,D52,Contacts_Activation!N:N,"oui")>0,"oui","non") -> oui | V52: =IF(COUNTIFS(Travaux!C:C,D52,Travaux!X:X,"en_cours")>0,"travaux_en_cours",IF(COUNTIFS(Ventes!C:C,D52,Ventes!L:L,"signature")>0,"vente_signature",IF(COUNTIFS(Ventes!C:C,D52,Ventes!AD:AD,"oui")>0,"vente_bloquee",IF(COUNTIFS(Gestion_Locative!C:C,D52,Gestion_Locative!O:O,"incomplet")>0,"gestion_fragile","stable")))) -> vente_bloquee
A53: 2 | B53: Marcadet | C53: LTS-004 | D53: LTS-004-015 | E53: BARBADINES | F53: 57 Ruelle Marcadet | G53: 25 | H53: 57 | I53: 20 | J53: M'HOUMADI | K53: Oussoufi | L53: 0692631773 | O53: oui | Q53: non | U53: =IF(COUNTIFS(Contacts_Activation!D:D,D53,Contacts_Activation!N:N,"oui")>0,"oui","non") -> oui | V53: =IF(COUNTIFS(Travaux!C:C,D53,Travaux!X:X,"en_cours")>0,"travaux_en_cours",IF(COUNTIFS(Ventes!C:C,D53,Ventes!L:L,"signature")>0,"vente_signature",IF(COUNTIFS(Ventes!C:C,D53,Ventes!AD:AD,"oui")>0,"vente_bloquee",IF(COUNTIFS(Gestion_Locative!C:C,D53,Gestion_Locative!O:O,"incomplet")>0,"gestion_fragile","stable")))) -> vente_bloquee
A54: 2 | B54: Marcadet | C54: LTS-004 | D54: LTS-004-016 | E54: BARBADINES | F54: 23 Ruelle Marcadet | G54: 25 | H54: 57 | I54: 20 | J54: MAHABO | N54: 692543500 | O54: oui | Q54: non | U54: =IF(COUNTIFS(Contacts_Activation!D:D,D54,Contacts_Activation!N:N,"oui")>0,"oui","non") -> oui | V54: =IF(COUNTIFS(Travaux!C:C,D54,Travaux!X:X,"en_cours")>0,"travaux_en_cours",IF(COUNTIFS(Ventes!C:C,D54,Ventes!L:L,"signature")>0,"vente_signature",IF(COUNTIFS(Ventes!C:C,D54,Ventes!AD:AD,"oui")>0,"vente_bloquee",IF(COUNTIFS(Gestion_Locative!C:C,D54,Gestion_Locative!O:O,"incomplet")>0,"gestion_fragile","stable")))) -> vente_bloquee
A55: 2 | B55: Marcadet | C55: LTS-004 | D55: LTS-004-017 | E55: BARBADINES | F55: 27 Ruelle Marcadet | G55: 25 | H55: 57 | I55: 20 | J55: PAROS | K55: Simone | L55: 0692347454 | O55: oui | Q55: non | U55: =IF(COUNTIFS(Contacts_Activation!D:D,D55,Contacts_Activation!N:N,"oui")>0,"oui","non") -> oui | V55: =IF(COUNTIFS(Travaux!C:C,D55,Travaux!X:X,"en_cours")>0,"travaux_en_cours",IF(COUNTIFS(Ventes!C:C,D55,Ventes!L:L,"signature")>0,"vente_signature",IF(COUNTIFS(Ventes!C:C,D55,Ventes!AD:AD,"oui")>0,"vente_bloquee",IF(COUNTIFS(Gestion_Locative!C:C,D55,Gestion_Locative!O:O,"incomplet")>0,"gestion_fragile","stable")))) -> vente_bloquee
A56: 2 | B56: Marcadet | C56: LTS-004 | D56: LTS-004-018 | E56: BARBADINES | F56: 13 Ruelle Marcadet | G56: 25 | H56: 57 | I56: 20 | J56: PAYET | K56: David | L56: 0692328124 | O56: oui | Q56: non | U56: =IF(COUNTIFS(Contacts_Activation!D:D,D56,Contacts_Activation!N:N,"oui")>0,"oui","non") -> oui | V56: =IF(COUNTIFS(Travaux!C:C,D56,Travaux!X:X,"en_cours")>0,"travaux_en_cours",IF(COUNTIFS(Ventes!C:C,D56,Ventes!L:L,"signature")>0,"vente_signature",IF(COUNTIFS(Ventes!C:C,D56,Ventes!AD:AD,"oui")>0,"vente_bloquee",IF(COUNTIFS(Gestion_Locative!C:C,D56,Gestion_Locative!O:O,"incomplet")>0,"gestion_fragile","stable")))) -> vente_bloquee
A57: 2 | B57: Marcadet | C57: LTS-004 | D57: LTS-004-019 | E57: BARBADINES | F57: 39 Ruelle Marcadet | G57: 25 | H57: 57 | I57: 20 | J57: PAYET | K57: Marie Danielle | L57: 0692758155 | O57: oui | Q57: non | U57: =IF(COUNTIFS(Contacts_Activation!D:D,D57,Contacts_Activation!N:N,"oui")>0,"oui","non") -> oui | V57: =IF(COUNTIFS(Travaux!C:C,D57,Travaux!X:X,"en_cours")>0,"travaux_en_cours",IF(COUNTIFS(Ventes!C:C,D57,Ventes!L:L,"signature")>0,"vente_signature",IF(COUNTIFS(Ventes!C:C,D57,Ventes!AD:AD,"oui")>0,"vente_bloquee",IF(COUNTIFS(Gestion_Locative!C:C,D57,Gestion_Locative!O:O,"incomplet")>0,"gestion_fragile","stable")))) -> vente_bloquee
A58: 2 | B58: Marcadet | C58: LTS-004 | D58: LTS-004-020 | E58: BARBADINES | F58: 15 Ruelle Marcadet | G58: 25 | H58: 57 | I58: 20 | J58: RAVAT | K58: Fatema | L58: 0692677852 | O58: oui | Q58: non | U58: =IF(COUNTIFS(Contacts_Activation!D:D,D58,Contacts_Activation!N:N,"oui")>0,"oui","non") -> oui | V58: =IF(COUNTIFS(Travaux!C:C,D58,Travaux!X:X,"en_cours")>0,"travaux_en_cours",IF(COUNTIFS(Ventes!C:C,D58,Ventes!L:L,"signature")>0,"vente_signature",IF(COUNTIFS(Ventes!C:C,D58,Ventes!AD:AD,"oui")>0,"vente_bloquee",IF(COUNTIFS(Gestion_Locative!C:C,D58,Gestion_Locative!O:O,"incomplet")>0,"gestion_fragile","stable")))) -> vente_bloquee
A59: 2 | B59: Marcadet | C59: LTS-004 | D59: LTS-004-021 | E59: BARBADINES | F59: 29 Ruelle Marcadet | G59: 25 | H59: 57 | I59: 20 | J59: ROSENTAL | K59: Patricia | O59: oui | Q59: non | U59: =IF(COUNTIFS(Contacts_Activation!D:D,D59,Contacts_Activation!N:N,"oui")>0,"oui","non") -> oui | V59: =IF(COUNTIFS(Travaux!C:C,D59,Travaux!X:X,"en_cours")>0,"travaux_en_cours",IF(COUNTIFS(Ventes!C:C,D59,Ventes!L:L,"signature")>0,"vente_signature",IF(COUNTIFS(Ventes!C:C,D59,Ventes!AD:AD,"oui")>0,"vente_bloquee",IF(COUNTIFS(Gestion_Locative!C:C,D59,Gestion_Locative!O:O,"incomplet")>0,"gestion_fragile","stable")))) -> vente_bloquee
A60: 2 | B60: Marcadet | C60: LTS-004 | D60: LTS-004-022 | E60: BARBADINES | F60: 67 Ruelle Marcadet | G60: 25 | H60: 57 | I60: 20 | J60: SABABADICHETTY | K60: Jean Eric et Joseph Raoul | L60: 0692158289 | M60: 0693527699 | O60: oui | Q60: non | U60: =IF(COUNTIFS(Contacts_Activation!D:D,D60,Contacts_Activation!N:N,"oui")>0,"oui","non") -> oui | V60: =IF(COUNTIFS(Travaux!C:C,D60,Travaux!X:X,"en_cours")>0,"travaux_en_cours",IF(COUNTIFS(Ventes!C:C,D60,Ventes!L:L,"signature")>0,"vente_signature",IF(COUNTIFS(Ventes!C:C,D60,Ventes!AD:AD,"oui")>0,"vente_bloquee",IF(COUNTIFS(Gestion_Locative!C:C,D60,Gestion_Locative!O:O,"incomplet")>0,"gestion_fragile","stable")))) -> vente_bloquee
A61: 2 | B61: Marcadet | C61: LTS-004 | D61: LTS-004-023 | E61: BARBADINES | F61: 31 Ruelle Marcadet | G61: 25 | H61: 57 | I61: 20 | J61: SALEM | K61: Brice | L61: 0693311767 | M61: 0692186561 | N61: SA FEMME | O61: oui | Q61: non | U61: =IF(COUNTIFS(Contacts_Activation!D:D,D61,Contacts_Activation!N:N,"oui")>0,"oui","non") -> oui | V61: =IF(COUNTIFS(Travaux!C:C,D61,Travaux!X:X,"en_cours")>0,"travaux_en_cours",IF(COUNTIFS(Ventes!C:C,D61,Ventes!L:L,"signature")>0,"vente_signature",IF(COUNTIFS(Ventes!C:C,D61,Ventes!AD:AD,"oui")>0,"vente_bloquee",IF(COUNTIFS(Gestion_Locative!C:C,D61,Gestion_Locative!O:O,"incomplet")>0,"gestion_fragile","stable")))) -> vente_bloquee
A62: 2 | B62: Marcadet | C62: LTS-004 | D62: LTS-004-024 | E62: BARBADINES | F62: 43 Ruelle Marcadet | G62: 25 | H62: 57 | I62: 20 | J62: SANOLAH | K62: Eva Bibi | L62: 0692169701 | O62: oui | Q62: non | U62: =IF(COUNTIFS(Contacts_Activation!D:D,D62,Contacts_Activation!N:N,"oui")>0,"oui","non") -> oui | V62: =IF(COUNTIFS(Travaux!C:C,D62,Travaux!X:X,"en_cours")>0,"travaux_en_cours",IF(COUNTIFS(Ventes!C:C,D62,Ventes!L:L,"signature")>0,"vente_signature",IF(COUNTIFS(Ventes!C:C,D62,Ventes!AD:AD,"oui")>0,"vente_bloquee",IF(COUNTIFS(Gestion_Locative!C:C,D62,Gestion_Locative!O:O,"incomplet")>0,"gestion_fragile","stable")))) -> vente_bloquee
A63: 2 | B63: Marcadet | C63: LTS-004 | D63: LTS-004-025 | E63: BARBADINES | F63: 49 Ruelle Marcadet | G63: 25 | H63: 57 | I63: 20 | J63: ELIZEON | K63: Fabrice | L63: 0692856383 | O63: oui | Q63: non | U63: =IF(COUNTIFS(Contacts_Activation!D:D,D63,Contacts_Activation!N:N,"oui")>0,"oui","non") -> oui | V63: =IF(COUNTIFS(Travaux!C:C,D63,Travaux!X:X,"en_cours")>0,"travaux_en_cours",IF(COUNTIFS(Ventes!C:C,D63,Ventes!L:L,"signature")>0,"vente_signature",IF(COUNTIFS(Ventes!C:C,D63,Ventes!AD:AD,"oui")>0,"vente_bloquee",IF(COUNTIFS(Gestion_Locative!C:C,D63,Gestion_Locative!O:O,"incomplet")>0,"gestion_fragile","stable")))) -> vente_bloquee
A64: 4 | B64: Moufia | C64: LTS-005 | D64: LTS-005-001 | E64: BILIMBIS | F64: 5 Impasse des Bilimbis | G64: 24 | H64: 66 | I64: 33 | J64: ARABOUT | K64: Darina | L64: 0693338433 | O64: oui | Q64: non | U64: =IF(COUNTIFS(Contacts_Activation!D:D,D64,Contacts_Activation!N:N,"oui")>0,"oui","non") -> oui | V64: =IF(COUNTIFS(Travaux!C:C,D64,Travaux!X:X,"en_cours")>0,"travaux_en_cours",IF(COUNTIFS(Ventes!C:C,D64,Ventes!L:L,"signature")>0,"vente_signature",IF(COUNTIFS(Ventes!C:C,D64,Ventes!AD:AD,"oui")>0,"vente_bloquee",IF(COUNTIFS(Gestion_Locative!C:C,D64,Gestion_Locative!O:O,"incomplet")>0,"gestion_fragile","stable")))) -> vente_bloquee
A65: 4 | B65: Moufia | C65: LTS-005 | D65: LTS-005-002 | E65: BILIMBIS | F65: 18 Impasse des Bilimbis | G65: 24 | H65: 66 | I65: 33 | J65: BELVISEE | K65: Frédéric | L65: 0693046702 | O65: oui | Q65: non | U65: =IF(COUNTIFS(Contacts_Activation!D:D,D65,Contacts_Activation!N:N,"oui")>0,"oui","non") -> oui | V65: =IF(COUNTIFS(Travaux!C:C,D65,Travaux!X:X,"en_cours")>0,"travaux_en_cours",IF(COUNTIFS(Ventes!C:C,D65,Ventes!L:L,"signature")>0,"vente_signature",IF(COUNTIFS(Ventes!C:C,D65,Ventes!AD:AD,"oui")>0,"vente_bloquee",IF(COUNTIFS(Gestion_Locative!C:C,D65,Gestion_Locative!O:O,"incomplet")>0,"gestion_fragile","stable")))) -> vente_bloquee
A66: 4 | B66: Moufia | C66: LTS-005 | D66: LTS-005-003 | E66: BILIMBIS | F66: 16 Impasse des Bilimbis | G66: 24 | H66: 66 | I66: 33 | J66: ROBERT | K66: Marie Sylvie | L66: 0692692306 | N66: MME ROBERT | O66: oui | Q66: non | U66: =IF(COUNTIFS(Contacts_Activation!D:D,D66,Contacts_Activation!N:N,"oui")>0,"oui","non") -> oui | V66: =IF(COUNTIFS(Travaux!C:C,D66,Travaux!X:X,"en_cours")>0,"travaux_en_cours",IF(COUNTIFS(Ventes!C:C,D66,Ventes!L:L,"signature")>0,"vente_signature",IF(COUNTIFS(Ventes!C:C,D66,Ventes!AD:AD,"oui")>0,"vente_bloquee",IF(COUNTIFS(Gestion_Locative!C:C,D66,Gestion_Locative!O:O,"incomplet")>0,"gestion_fragile","stable")))) -> vente_bloquee
A67: 4 | B67: Moufia | C67: LTS-005 | D67: LTS-005-004 | E67: BILIMBIS | F67: 33 Impasse des Bilimbis | G67: 24 | H67: 66 | I67: 33 | J67: BOYER | K67: Mimose | L67: 0692779160 | O67: oui | Q67: non | U67: =IF(COUNTIFS(Contacts_Activation!D:D,D67,Contacts_Activation!N:N,"oui")>0,"oui","non") -> oui | V67: =IF(COUNTIFS(Travaux!C:C,D67,Travaux!X:X,"en_cours")>0,"travaux_en_cours",IF(COUNTIFS(Ventes!C:C,D67,Ventes!L:L,"signature")>0,"vente_signature",IF(COUNTIFS(Ventes!C:C,D67,Ventes!AD:AD,"oui")>0,"vente_bloquee",IF(COUNTIFS(Gestion_Locative!C:C,D67,Gestion_Locative!O:O,"incomplet")>0,"gestion_fragile","stable")))) -> vente_bloquee
A68: 4 | B68: Moufia | C68: LTS-005 | D68: LTS-005-005 | E68: BILIMBIS | F68: 8 Impasse des Bilimbis | G68: 24 | H68: 66 | I68: 33 | J68: BOYER | K68: Cyril Joseph | L68: 0692253800 | O68: oui | Q68: non | U68: =IF(COUNTIFS(Contacts_Activation!D:D,D68,Contacts_Activation!N:N,"oui")>0,"oui","non") -> oui | V68: =IF(COUNTIFS(Travaux!C:C,D68,Travaux!X:X,"en_cours")>0,"travaux_en_cours",IF(COUNTIFS(Ventes!C:C,D68,Ventes!L:L,"signature")>0,"vente_signature",IF(COUNTIFS(Ventes!C:C,D68,Ventes!AD:AD,"oui")>0,"vente_bloquee",IF(COUNTIFS(Gestion_Locative!C:C,D68,Gestion_Locative!O:O,"incomplet")>0,"gestion_fragile","stable")))) -> vente_bloquee
A69: 4 | B69: Moufia | C69: LTS-005 | D69: LTS-005-006 | E69: BILIMBIS | F69: 21 Impasse des Bilimbis | G69: 24 | H69: 66 | I69: 33 | J69: ROCROU | K69: Camille Joël | L69: 0692828750 | O69: oui | Q69: non | U69: =IF(COUNTIFS(Contacts_Activation!D:D,D69,Contacts_Activation!N:N,"oui")>0,"oui","non") -> oui | V69: =IF(COUNTIFS(Travaux!C:C,D69,Travaux!X:X,"en_cours")>0,"travaux_en_cours",IF(COUNTIFS(Ventes!C:C,D69,Ventes!L:L,"signature")>0,"vente_signature",IF(COUNTIFS(Ventes!C:C,D69,Ventes!AD:AD,"oui")>0,"vente_bloquee",IF(COUNTIFS(Gestion_Locative!C:C,D69,Gestion_Locative!O:O,"incomplet")>0,"gestion_fragile","stable")))) -> vente_bloquee
A70: 4 | B70: Moufia | C70: LTS-005 | D70: LTS-005-007 | E70: BILIMBIS | F70: 19 Impasse des Bilimbis | G70: 24 | H70: 66 | I70: 33 | J70: CHNAYTI | K70: Dounia | L70: 0692336953 | M70: 0262577819 | O70: oui | Q70: non | U70: =IF(COUNTIFS(Contacts_Activation!D:D,D70,Contacts_Activation!N:N,"oui")>0,"oui","non") -> oui | V70: =IF(COUNTIFS(Travaux!C:C,D70,Travaux!X:X,"en_cours")>0,"travaux_en_cours",IF(COUNTIFS(Ventes!C:C,D70,Ventes!L:L,"signature")>0,"vente_signature",IF(COUNTIFS(Ventes!C:C,D70,Ventes!AD:AD,"oui")>0,"vente_bloquee",IF(COUNTIFS(Gestion_Locative!C:C,D70,Gestion_Locative!O:O,"incomplet")>0,"gestion_fragile","stable")))) -> vente_bloquee
A71: 4 | B71: Moufia | C71: LTS-005 | D71: LTS-005-008 | E71: BILIMBIS | F71: 12 Impasse des Bilimbis | G71: 24 | H71: 66 | I71: 33 | J71: HOAREAU | K71: Jenifer | L71: 0693431072 | O71: oui | Q71: non | U71: =IF(COUNTIFS(Contacts_Activation!D:D,D71,Contacts_Activation!N:N,"oui")>0,"oui","non") -> oui | V71: =IF(COUNTIFS(Travaux!C:C,D71,Travaux!X:X,"en_cours")>0,"travaux_en_cours",IF(COUNTIFS(Ventes!C:C,D71,Ventes!L:L,"signature")>0,"vente_signature",IF(COUNTIFS(Ventes!C:C,D71,Ventes!AD:AD,"oui")>0,"vente_bloquee",IF(COUNTIFS(Gestion_Locative!C:C,D71,Gestion_Locative!O:O,"incomplet")>0,"gestion_fragile","stable")))) -> vente_bloquee
A72: 4 | B72: Moufia | C72: LTS-005 | D72: LTS-005-009 | E72: BILIMBIS | F72: 17 Impasse des Bilimbis | G72: 24 | H72: 66 | I72: 33 | J72: GRONDIN | K72: Marie Michèle | L72: 0262221550 | M72: 0692022133 | N72: 5 | O72: oui | Q72: non | U72: =IF(COUNTIFS(Contacts_Activation!D:D,D72,Contacts_Activation!N:N,"oui")>0,"oui","non") -> oui | V72: =IF(COUNTIFS(Travaux!C:C,D72,Travaux!X:X,"en_cours")>0,"travaux_en_cours",IF(COUNTIFS(Ventes!C:C,D72,Ventes!L:L,"signature")>0,"vente_signature",IF(COUNTIFS(Ventes!C:C,D72,Ventes!AD:AD,"oui")>0,"vente_bloquee",IF(COUNTIFS(Gestion_Locative!C:C,D72,Gestion_Locative!O:O,"incomplet")>0,"gestion_fragile","stable")))) -> vente_bloquee
A73: 4 | B73: Moufia | C73: LTS-005 | D73: LTS-005-010 | E73: BILIMBIS | F73: 10 Impasse des Bilimbis | G73: 24 | H73: 66 | I73: 33 | J73: HOAREAU | K73: Suzette Lourdes | L73: 0262298512 | O73: oui | Q73: non | U73: =IF(COUNTIFS(Contacts_Activation!D:D,D73,Contacts_Activation!N:N,"oui")>0,"oui","non") -> oui | V73: =IF(COUNTIFS(Travaux!C:C,D73,Travaux!X:X,"en_cours")>0,"travaux_en_cours",IF(COUNTIFS(Ventes!C:C,D73,Ventes!L:L,"signature")>0,"vente_signature",IF(COUNTIFS(Ventes!C:C,D73,Ventes!AD:AD,"oui")>0,"vente_bloquee",IF(COUNTIFS(Gestion_Locative!C:C,D73,Gestion_Locative!O:O,"incomplet")>0,"gestion_fragile","stable")))) -> vente_bloquee
A74: 4 | B74: Moufia | C74: LTS-005 | D74: LTS-005-011 | E74: BILIMBIS | F74: 11 Impasse des Bilimbis | G74: 24 | H74: 66 | I74: 33 | J74: HUET | K74: Marie Ingrid | L74: 0692809596 | O74: oui | Q74: non | U74: =IF(COUNTIFS(Contacts_Activation!D:D,D74,Contacts_Activation!N:N,"oui")>0,"oui","non") -> oui | V74: =IF(COUNTIFS(Travaux!C:C,D74,Travaux!X:X,"en_cours")>0,"travaux_en_cours",IF(COUNTIFS(Ventes!C:C,D74,Ventes!L:L,"signature")>0,"vente_signature",IF(COUNTIFS(Ventes!C:C,D74,Ventes!AD:AD,"oui")>0,"vente_bloquee",IF(COUNTIFS(Gestion_Locative!C:C,D74,Gestion_Locative!O:O,"incomplet")>0,"gestion_fragile","stable")))) -> vente_bloquee
A75: 4 | B75: Moufia | C75: LTS-005 | D75: LTS-005-012 | E75: BILIMBIS | F75: 3 Impasse des Bilimbis | G75: 24 | H75: 66 | I75: 33 | J75: ICHOUZA | K75: Béatrice | L75: 0262234375 | M75: 0692619143 | O75: oui | Q75: non | U75: =IF(COUNTIFS(Contacts_Activation!D:D,D75,Contacts_Activation!N:N,"oui")>0,"oui","non") -> oui | V75: =IF(COUNTIFS(Travaux!C:C,D75,Travaux!X:X,"en_cours")>0,"travaux_en_cours",IF(COUNTIFS(Ventes!C:C,D75,Ventes!L:L,"signature")>0,"vente_signature",IF(COUNTIFS(Ventes!C:C,D75,Ventes!AD:AD,"oui")>0,"vente_bloquee",IF(COUNTIFS(Gestion_Locative!C:C,D75,Gestion_Locative!O:O,"incomplet")>0,"gestion_fragile","stable")))) -> vente_bloquee
A76: 4 | B76: Moufia | C76: LTS-005 | D76: LTS-005-013 | E76: BILIMBIS | F76: 1 Impasse des Bilimbis | G76: 24 | H76: 66 | I76: 33 | J76: ICHOUZA | K76: Marie Gladys | L76: 0692799962 | O76: oui | Q76: non | U76: =IF(COUNTIFS(Contacts_Activation!D:D,D76,Contacts_Activation!N:N,"oui")>0,"oui","non") -> oui | V76: =IF(COUNTIFS(Travaux!C:C,D76,Travaux!X:X,"en_cours")>0,"travaux_en_cours",IF(COUNTIFS(Ventes!C:C,D76,Ventes!L:L,"signature")>0,"vente_signature",IF(COUNTIFS(Ventes!C:C,D76,Ventes!AD:AD,"oui")>0,"vente_bloquee",IF(COUNTIFS(Gestion_Locative!C:C,D76,Gestion_Locative!O:O,"incomplet")>0,"gestion_fragile","stable")))) -> vente_bloquee
A77: 4 | B77: Moufia | C77: LTS-005 | D77: LTS-005-014 | E77: BILIMBIS | F77: 28 Impasse des Bilimbis | G77: 24 | H77: 66 | I77: 33 | J77: IMIRA | K77: Marie Rita | L77: 0692782803 | O77: oui | Q77: non | U77: =IF(COUNTIFS(Contacts_Activation!D:D,D77,Contacts_Activation!N:N,"oui")>0,"oui","non") -> oui | V77: =IF(COUNTIFS(Travaux!C:C,D77,Travaux!X:X,"en_cours")>0,"travaux_en_cours",IF(COUNTIFS(Ventes!C:C,D77,Ventes!L:L,"signature")>0,"vente_signature",IF(COUNTIFS(Ventes!C:C,D77,Ventes!AD:AD,"oui")>0,"vente_bloquee",IF(COUNTIFS(Gestion_Locative!C:C,D77,Gestion_Locative!O:O,"incomplet")>0,"gestion_fragile","stable")))) -> vente_bloquee
A78: 4 | B78: Moufia | C78: LTS-005 | D78: LTS-005-015 | E78: BILIMBIS | F78: 25 Impasse des Bilimbis | G78: 24 | H78: 66 | I78: 33 | J78: JEAN BAPTISTE | K78: Alexandra | L78: 0692374881 | O78: oui | Q78: non | U78: =IF(COUNTIFS(Contacts_Activation!D:D,D78,Contacts_Activation!N:N,"oui")>0,"oui","non") -> oui | V78: =IF(COUNTIFS(Travaux!C:C,D78,Travaux!X:X,"en_cours")>0,"travaux_en_cours",IF(COUNTIFS(Ventes!C:C,D78,Ventes!L:L,"signature")>0,"vente_signature",IF(COUNTIFS(Ventes!C:C,D78,Ventes!AD:AD,"oui")>0,"vente_bloquee",IF(COUNTIFS(Gestion_Locative!C:C,D78,Gestion_Locative!O:O,"incomplet")>0,"gestion_fragile","stable")))) -> vente_bloquee
A79: 4 | B79: Moufia | C79: LTS-005 | D79: LTS-005-016 | E79: BILIMBIS | F79: 13 Impasse des Bilimbis | G79: 24 | H79: 66 | I79: 33 | J79: LEBON | K79: Rock | L79: 0692903963 | O79: oui | Q79: non | U79: =IF(COUNTIFS(Contacts_Activation!D:D,D79,Contacts_Activation!N:N,"oui")>0,"oui","non") -> oui | V79: =IF(COUNTIFS(Travaux!C:C,D79,Travaux!X:X,"en_cours")>0,"travaux_en_cours",IF(COUNTIFS(Ventes!C:C,D79,Ventes!L:L,"signature")>0,"vente_signature",IF(COUNTIFS(Ventes!C:C,D79,Ventes!AD:AD,"oui")>0,"vente_bloquee",IF(COUNTIFS(Gestion_Locative!C:C,D79,Gestion_Locative!O:O,"incomplet")>0,"gestion_fragile","stable")))) -> vente_bloquee
A80: 4 | B80: Moufia | C80: LTS-005 | D80: LTS-005-017 | E80: BILIMBIS | F80: 30 Impasse des Bilimbis | G80: 24 | H80: 66 | I80: 33 | J80: LEBRETON | K80: Yanito | L80: 0692922592 | O80: oui | Q80: non | U80: =IF(COUNTIFS(Contacts_Activation!D:D,D80,Contacts_Activation!N:N,"oui")>0,"oui","non") -> oui | V80: =IF(COUNTIFS(Travaux!C:C,D80,Travaux!X:X,"en_cours")>0,"travaux_en_cours",IF(COUNTIFS(Ventes!C:C,D80,Ventes!L:L,"signature")>0,"vente_signature",IF(COUNTIFS(Ventes!C:C,D80,Ventes!AD:AD,"oui")>0,"vente_bloquee",IF(COUNTIFS(Gestion_Locative!C:C,D80,Gestion_Locative!O:O,"incomplet")>0,"gestion_fragile","stable")))) -> vente_bloquee
A81: 4 | B81: Moufia | C81: LTS-005 | D81: LTS-005-018 | E81: BILIMBIS | F81: 20 Impasse des Bilimbis | G81: 24 | H81: 66 | I81: 33 | J81: KIBIO | K81: Kayliane | L81: 0692496477 | M81: 0693450257 | N81: MME KIBIO | O81: oui | Q81: non | U81: =IF(COUNTIFS(Contacts_Activation!D:D,D81,Contacts_Activation!N:N,"oui")>0,"oui","non") -> oui | V81: =IF(COUNTIFS(Travaux!C:C,D81,Travaux!X:X,"en_cours")>0,"travaux_en_cours",IF(COUNTIFS(Ventes!C:C,D81,Ventes!L:L,"signature")>0,"vente_signature",IF(COUNTIFS(Ventes!C:C,D81,Ventes!AD:AD,"oui")>0,"vente_bloquee",IF(COUNTIFS(Gestion_Locative!C:C,D81,Gestion_Locative!O:O,"incomplet")>0,"gestion_fragile","stable")))) -> vente_bloquee
A82: 4 | B82: Moufia | C82: LTS-005 | D82: LTS-005-019 | E82: BILIMBIS | F82: 2 Impasse des Bilimbis | G82: 24 | H82: 66 | I82: 33 | J82: ROBERT | K82: Eugénie | L82: 0692826196 | O82: oui | Q82: non | U82: =IF(COUNTIFS(Contacts_Activation!D:D,D82,Contacts_Activation!N:N,"oui")>0,"oui","non") -> oui | V82: =IF(COUNTIFS(Travaux!C:C,D82,Travaux!X:X,"en_cours")>0,"travaux_en_cours",IF(COUNTIFS(Ventes!C:C,D82,Ventes!L:L,"signature")>0,"vente_signature",IF(COUNTIFS(Ventes!C:C,D82,Ventes!AD:AD,"oui")>0,"vente_bloquee",IF(COUNTIFS(Gestion_Locative!C:C,D82,Gestion_Locative!O:O,"incomplet")>0,"gestion_fragile","stable")))) -> vente_bloquee
A83: 4 | B83: Moufia | C83: LTS-005 | D83: LTS-005-020 | E83: BILIMBIS | F83: 26 Impasse des Bilimbis | G83: 24 | H83: 66 | I83: 33 | J83: SADON | K83: Marie Jeanine | L83: 0693049639 | M83: 0262134356 | N83: fixe | O83: oui | Q83: non | U83: =IF(COUNTIFS(Contacts_Activation!D:D,D83,Contacts_Activation!N:N,"oui")>0,"oui","non") -> oui | V83: =IF(COUNTIFS(Travaux!C:C,D83,Travaux!X:X,"en_cours")>0,"travaux_en_cours",IF(COUNTIFS(Ventes!C:C,D83,Ventes!L:L,"signature")>0,"vente_signature",IF(COUNTIFS(Ventes!C:C,D83,Ventes!AD:AD,"oui")>0,"vente_bloquee",IF(COUNTIFS(Gestion_Locative!C:C,D83,Gestion_Locative!O:O,"incomplet")>0,"gestion_fragile","stable")))) -> vente_bloquee
A84: 4 | B84: Moufia | C84: LTS-005 | D84: LTS-005-021 | E84: BILIMBIS | F84: 4 Impasse des Bilimbis | G84: 24 | H84: 66 | I84: 33 | J84: SINAN | K84: Marie Anièle | L84: 0693037800 | O84: oui | Q84: non | U84: =IF(COUNTIFS(Contacts_Activation!D:D,D84,Contacts_Activation!N:N,"oui")>0,"oui","non") -> oui | V84: =IF(COUNTIFS(Travaux!C:C,D84,Travaux!X:X,"en_cours")>0,"travaux_en_cours",IF(COUNTIFS(Ventes!C:C,D84,Ventes!L:L,"signature")>0,"vente_signature",IF(COUNTIFS(Ventes!C:C,D84,Ventes!AD:AD,"oui")>0,"vente_bloquee",IF(COUNTIFS(Gestion_Locative!C:C,D84,Gestion_Locative!O:O,"incomplet")>0,"gestion_fragile","stable")))) -> vente_bloquee
A85: 4 | B85: Moufia | C85: LTS-005 | D85: LTS-005-022 | E85: BILIMBIS | F85: 27 Impasse des Bilimbis | G85: 24 | H85: 66 | I85: 33 | J85: TURPIN | K85: Josian | L85: 0692916291 | O85: oui | Q85: non | U85: =IF(COUNTIFS(Contacts_Activation!D:D,D85,Contacts_Activation!N:N,"oui")>0,"oui","non") -> oui | V85: =IF(COUNTIFS(Travaux!C:C,D85,Travaux!X:X,"en_cours")>0,"travaux_en_cours",IF(COUNTIFS(Ventes!C:C,D85,Ventes!L:L,"signature")>0,"vente_signature",IF(COUNTIFS(Ventes!C:C,D85,Ventes!AD:AD,"oui")>0,"vente_bloquee",IF(COUNTIFS(Gestion_Locative!C:C,D85,Gestion_Locative!O:O,"incomplet")>0,"gestion_fragile","stable")))) -> vente_bloquee
A86: 4 | B86: Moufia | C86: LTS-005 | D86: LTS-005-023 | E86: BILIMBIS | F86: 9 Impasse des Bilimbis | G86: 24 | H86: 66 | I86: 33 | J86: TURPIN | K86: Marie Julienne | L86: 0262299212 | M86: 0692697117 | O86: oui | Q86: non | U86: =IF(COUNTIFS(Contacts_Activation!D:D,D86,Contacts_Activation!N:N,"oui")>0,"oui","non") -> oui | V86: =IF(COUNTIFS(Travaux!C:C,D86,Travaux!X:X,"en_cours")>0,"travaux_en_cours",IF(COUNTIFS(Ventes!C:C,D86,Ventes!L:L,"signature")>0,"vente_signature",IF(COUNTIFS(Ventes!C:C,D86,Ventes!AD:AD,"oui")>0,"vente_bloquee",IF(COUNTIFS(Gestion_Locative!C:C,D86,Gestion_Locative!O:O,"incomplet")>0,"gestion_fragile","stable")))) -> vente_bloquee
A87: 4 | B87: Moufia | C87: LTS-005 | D87: LTS-005-024 | E87: BILIMBIS | F87: 23 Impasse des Bilimbis | G87: 24 | H87: 66 | I87: 33 | J87: VIDOT | K87: Marie Claude | L87: 0262977334 | M87: 0693802564 | N87: SA FILLE | O87: oui | Q87: non | U87: =IF(COUNTIFS(Contacts_Activation!D:D,D87,Contacts_Activation!N:N,"oui")>0,"oui","non") -> oui | V87: =IF(COUNTIFS(Travaux!C:C,D87,Travaux!X:X,"en_cours")>0,"travaux_en_cours",IF(COUNTIFS(Ventes!C:C,D87,Ventes!L:L,"signature")>0,"vente_signature",IF(COUNTIFS(Ventes!C:C,D87,Ventes!AD:AD,"oui")>0,"vente_bloquee",IF(COUNTIFS(Gestion_Locative!C:C,D87,Gestion_Locative!O:O,"incomplet")>0,"gestion_fragile","stable")))) -> vente_bloquee
A88: 4 | B88: La Bretagne | C88: LTS-006 | D88: LTS-006-001 | E88: LANGAVANT | F88: 18D CH DE LANGAVANT | G88: 2 | H88: 81 | I88: 68 | J88: SAITI | L88: 0262989287 | O88: oui | Q88: non | U88: =IF(COUNTIFS(Contacts_Activation!D:D,D88,Contacts_Activation!N:N,"oui")>0,"oui","non") -> oui | V88: =IF(COUNTIFS(Travaux!C:C,D88,Travaux!X:X,"en_cours")>0,"travaux_en_cours",IF(COUNTIFS(Ventes!C:C,D88,Ventes!L:L,"signature")>0,"vente_signature",IF(COUNTIFS(Ventes!C:C,D88,Ventes!AD:AD,"oui")>0,"vente_bloquee",IF(COUNTIFS(Gestion_Locative!C:C,D88,Gestion_Locative!O:O,"incomplet")>0,"gestion_fragile","stable")))) -> vente_bloquee
A89: 4 | B89: La Bretagne | C89: LTS-006 | D89: LTS-006-002 | E89: LANGAVANT | F89: 18C CH DE LANGAVANT | G89: 2 | H89: 81 | I89: 68 | J89: PANECHOU | L89: 0262526270 | O89: oui | Q89: non | U89: =IF(COUNTIFS(Contacts_Activation!D:D,D89,Contacts_Activation!N:N,"oui")>0,"oui","non") -> oui | V89: =IF(COUNTIFS(Travaux!C:C,D89,Travaux!X:X,"en_cours")>0,"travaux_en_cours",IF(COUNTIFS(Ventes!C:C,D89,Ventes!L:L,"signature")>0,"vente_signature",IF(COUNTIFS(Ventes!C:C,D89,Ventes!AD:AD,"oui")>0,"vente_bloquee",IF(COUNTIFS(Gestion_Locative!C:C,D89,Gestion_Locative!O:O,"incomplet")>0,"gestion_fragile","stable")))) -> vente_bloquee
A90: 3 | B90: Saint François | C90: LTS-007 | D90: LTS-007-001 | E90: CASKAVELS | F90: 18 Chemin Alfred Mazérieux | G90: 9 | H90: 73 | I90: 63 | J90: DIJOUX | K90: Sébastien | L90: 0692808959 | O90: oui | Q90: non | U90: =IF(COUNTIFS(Contacts_Activation!D:D,D90,Contacts_Activation!N:N,"oui")>0,"oui","non") -> oui | V90: =IF(COUNTIFS(Travaux!C:C,D90,Travaux!X:X,"en_cours")>0,"travaux_en_cours",IF(COUNTIFS(Ventes!C:C,D90,Ventes!L:L,"signature")>0,"vente_signature",IF(COUNTIFS(Ventes!C:C,D90,Ventes!AD:AD,"oui")>0,"vente_bloquee",IF(COUNTIFS(Gestion_Locative!C:C,D90,Gestion_Locative!O:O,"incomplet")>0,"gestion_fragile","stable")))) -> vente_bloquee
A91: 3 | B91: Saint François | C91: LTS-007 | D91: LTS-007-002 | E91: CASKAVELS | F91: 30 Chemin Alfred Mazérieux | G91: 9 | H91: 73 | I91: 63 | J91: PICARD | K91: Ignace Clémént | L91: 0692461865 | O91: oui | Q91: non | U91: =IF(COUNTIFS(Contacts_Activation!D:D,D91,Contacts_Activation!N:N,"oui")>0,"oui","non") -> oui | V91: =IF(COUNTIFS(Travaux!C:C,D91,Travaux!X:X,"en_cours")>0,"travaux_en_cours",IF(COUNTIFS(Ventes!C:C,D91,Ventes!L:L,"signature")>0,"vente_signature",IF(COUNTIFS(Ventes!C:C,D91,Ventes!AD:AD,"oui")>0,"vente_bloquee",IF(COUNTIFS(Gestion_Locative!C:C,D91,Gestion_Locative!O:O,"incomplet")>0,"gestion_fragile","stable")))) -> vente_bloquee
A92: 3 | B92: Saint François | C92: LTS-007 | D92: LTS-007-003 | E92: CASKAVELS | F92: 28 Chemin Alfred Mazérieux | G92: 9 | H92: 73 | I92: 63 | J92: HOARAU | K92: Sheila | L92: 0262302418 | M92: 0693022610 | O92: oui | Q92: non | U92: =IF(COUNTIFS(Contacts_Activation!D:D,D92,Contacts_Activation!N:N,"oui")>0,"oui","non") -> oui | V92: =IF(COUNTIFS(Travaux!C:C,D92,Travaux!X:X,"en_cours")>0,"travaux_en_cours",IF(COUNTIFS(Ventes!C:C,D92,Ventes!L:L,"signature")>0,"vente_signature",IF(COUNTIFS(Ventes!C:C,D92,Ventes!AD:AD,"oui")>0,"vente_bloquee",IF(COUNTIFS(Gestion_Locative!C:C,D92,Gestion_Locative!O:O,"incomplet")>0,"gestion_fragile","stable")))) -> vente_bloquee
A93: 3 | B93: Saint François | C93: LTS-007 | D93: LTS-007-004 | E93: CASKAVELS | F93: 24 Chemin Alfred Mazérieux | G93: 9 | H93: 73 | I93: 63 | J93: JOSON | K93: Marie Thérèse | O93: oui | Q93: non | U93: =IF(COUNTIFS(Contacts_Activation!D:D,D93,Contacts_Activation!N:N,"oui")>0,"oui","non") -> oui | V93: =IF(COUNTIFS(Travaux!C:C,D93,Travaux!X:X,"en_cours")>0,"travaux_en_cours",IF(COUNTIFS(Ventes!C:C,D93,Ventes!L:L,"signature")>0,"vente_signature",IF(COUNTIFS(Ventes!C:C,D93,Ventes!AD:AD,"oui")>0,"vente_bloquee",IF(COUNTIFS(Gestion_Locative!C:C,D93,Gestion_Locative!O:O,"incomplet")>0,"gestion_fragile","stable")))) -> vente_bloquee
A94: 3 | B94: Saint François | C94: LTS-007 | D94: LTS-007-005 | E94: CASKAVELS | F94: 26 Chemin Alfred Mazérieux | G94: 9 | H94: 73 | I94: 63 | J94: MAILLOT | K94: René-Claude | L94: 0262647470 | M94: 0692104376 | N94: RENE Claude | O94: oui | Q94: non | U94: =IF(COUNTIFS(Contacts_Activation!D:D,D94,Contacts_Activation!N:N,"oui")>0,"oui","non") -> oui | V94: =IF(COUNTIFS(Travaux!C:C,D94,Travaux!X:X,"en_cours")>0,"travaux_en_cours",IF(COUNTIFS(Ventes!C:C,D94,Ventes!L:L,"signature")>0,"vente_signature",IF(COUNTIFS(Ventes!C:C,D94,Ventes!AD:AD,"oui")>0,"vente_bloquee",IF(COUNTIFS(Gestion_Locative!C:C,D94,Gestion_Locative!O:O,"incomplet")>0,"gestion_fragile","stable")))) -> vente_bloquee
A95: 3 | B95: Saint François | C95: LTS-007 | D95: LTS-007-006 | E95: CASKAVELS | F95: 42 Chemin Alfred Mazérieux | G95: 9 | H95: 73 | I95: 63 | J95: MALAYA | K95: Jean Raymond | L95: 0262305300 | O95: oui | Q95: non | U95: =IF(COUNTIFS(Contacts_Activation!D:D,D95,Contacts_Activation!N:N,"oui")>0,"oui","non") -> oui | V95: =IF(COUNTIFS(Travaux!C:C,D95,Travaux!X:X,"en_cours")>0,"travaux_en_cours",IF(COUNTIFS(Ventes!C:C,D95,Ventes!L:L,"signature")>0,"vente_signature",IF(COUNTIFS(Ventes!C:C,D95,Ventes!AD:AD,"oui")>0,"vente_bloquee",IF(COUNTIFS(Gestion_Locative!C:C,D95,Gestion_Locative!O:O,"incomplet")>0,"gestion_fragile","stable")))) -> vente_bloquee
A96: 3 | B96: Saint François | C96: LTS-007 | D96: LTS-007-007 | E96: CASKAVELS | F96: 44 Chemin Alfred Mazérieux | G96: 9 | H96: 73 | I96: 63 | J96: MALAYA | K96: Simone | L96: 0262302939 | O96: oui | Q96: non | U96: =IF(COUNTIFS(Contacts_Activation!D:D,D96,Contacts_Activation!N:N,"oui")>0,"oui","non") -> oui | V96: =IF(COUNTIFS(Travaux!C:C,D96,Travaux!X:X,"en_cours")>0,"travaux_en_cours",IF(COUNTIFS(Ventes!C:C,D96,Ventes!L:L,"signature")>0,"vente_signature",IF(COUNTIFS(Ventes!C:C,D96,Ventes!AD:AD,"oui")>0,"vente_bloquee",IF(COUNTIFS(Gestion_Locative!C:C,D96,Gestion_Locative!O:O,"incomplet")>0,"gestion_fragile","stable")))) -> vente_bloquee
A97: 3 | B97: Saint François | C97: LTS-007 | D97: LTS-007-008 | E97: CASKAVELS | F97: 20 Chemin Alfred Mazérieux | G97: 9 | H97: 73 | I97: 63 | J97: NAZE | K97: Anne Marie Catherine | L97: 0262303814 | M97: 0693909611 | O97: oui | Q97: non | U97: =IF(COUNTIFS(Contacts_Activation!D:D,D97,Contacts_Activation!N:N,"oui")>0,"oui","non") -> oui | V97: =IF(COUNTIFS(Travaux!C:C,D97,Travaux!X:X,"en_cours")>0,"travaux_en_cours",IF(COUNTIFS(Ventes!C:C,D97,Ventes!L:L,"signature")>0,"vente_signature",IF(COUNTIFS(Ventes!C:C,D97,Ventes!AD:AD,"oui")>0,"vente_bloquee",IF(COUNTIFS(Gestion_Locative!C:C,D97,Gestion_Locative!O:O,"incomplet")>0,"gestion_fragile","stable")))) -> vente_bloquee
A98: 3 | B98: Saint François | C98: LTS-007 | D98: LTS-007-009 | E98: CASKAVELS | F98: 38 Chemin Alfred Mazérieux | G98: 9 | H98: 73 | I98: 63 | J98: TURPIN | K98: Marie Laetitia | L98: 0692181507 | M98: 0262811637 | O98: oui | Q98: non | U98: =IF(COUNTIFS(Contacts_Activation!D:D,D98,Contacts_Activation!N:N,"oui")>0,"oui","non") -> oui | V98: =IF(COUNTIFS(Travaux!C:C,D98,Travaux!X:X,"en_cours")>0,"travaux_en_cours",IF(COUNTIFS(Ventes!C:C,D98,Ventes!L:L,"signature")>0,"vente_signature",IF(COUNTIFS(Ventes!C:C,D98,Ventes!AD:AD,"oui")>0,"vente_bloquee",IF(COUNTIFS(Gestion_Locative!C:C,D98,Gestion_Locative!O:O,"incomplet")>0,"gestion_fragile","stable")))) -> vente_bloquee
A99: 4 | B99: Bois de Nefles | C99: LTS-008 | D99: LTS-008-001 | E99: CLOTILDA | F99: 2 bis Allée des Teks | G99: 27 | H99: 61 | I99: 58 | J99: BATONNET | K99: Jeannine Yvette | L99: 0693300830 | O99: non | P99: Résidence exclue du dispositif de vente | Q99: non | U99: =IF(COUNTIFS(Contacts_Activation!D:D,D99,Contacts_Activation!N:N,"oui")>0,"oui","non") -> oui | V99: =IF(COUNTIFS(Travaux!C:C,D99,Travaux!X:X,"en_cours")>0,"travaux_en_cours",IF(COUNTIFS(Ventes!C:C,D99,Ventes!L:L,"signature")>0,"vente_signature",IF(COUNTIFS(Ventes!C:C,D99,Ventes!AD:AD,"oui")>0,"vente_bloquee",IF(COUNTIFS(Gestion_Locative!C:C,D99,Gestion_Locative!O:O,"incomplet")>0,"gestion_fragile","stable")))) -> vente_bloquee
A100: 4 | B100: Bois de Nefles | C100: LTS-008 | D100: LTS-008-002 | E100: CLOTILDA | F100: 16 Allée des Teks | G100: 27 | H100: 61 | I100: 58 | J100: SALEZ | K100: Catherine | L100: 0693323223 | O100: non | P100: Résidence exclue du dispositif de vente | Q100: non | U100: =IF(COUNTIFS(Contacts_Activation!D:D,D100,Contacts_Activation!N:N,"oui")>0,"oui","non") -> oui | V100: =IF(COUNTIFS(Travaux!C:C,D100,Travaux!X:X,"en_cours")>0,"travaux_en_cours",IF(COUNTIFS(Ventes!C:C,D100,Ventes!L:L,"signature")>0,"vente_signature",IF(COUNTIFS(Ventes!C:C,D100,Ventes!AD:AD,"oui")>0,"vente_bloquee",IF(COUNTIFS(Gestion_Locative!C:C,D100,Gestion_Locative!O:O,"incomplet")>0,"gestion_fragile","stable")))) -> vente_bloquee
...

Sheet Logements
A1: secteur | B1: quartier | C1: code_lts | D1: code_acces | E1: adresse | F1: type de logement | G1: statut | H1: etat_general | I1: date_creation
A2: 1 | B2: Sainte Cloitlde | C2: LTS-001 | D2: LTS-001-001 | E2: 15 Bloc 20 Rue des Alamandas | F2: T4 | G2: occupé | H2: bon | I2: 1984
A3: 1 | B3: Sainte Cloitlde | C3: LTS-001 | D3: LTS-001-002 | E3: 26 Bloc 24 Rue des Alamandas | F3: T1 | G3: occupé | H3: bon | I3: 1984
A4: 1 | B4: Sainte Cloitlde | C4: LTS-001 | D4: LTS-001-003 | E4: 19 Bloc 22 Rue des Alamandas | F4: T2 | G4: occupé | H4: bon | I4: 1984
A5: 1 | B5: Sainte Cloitlde | C5: LTS-001 | D5: LTS-001-004 | E5: 27 Bloc 24 Rue des Alamandas | F5: T3 | G5: occupé | H5: bon | I5: 1984
A6: 1 | B6: Sainte Cloitlde | C6: LTS-001 | D6: LTS-001-005 | E6: 11 Bloc 18 Rue des Alamandas | F6: T4 | G6: occupé | H6: bon | I6: 1984
A7: 1 | B7: Sainte Cloitlde | C7: LTS-001 | D7: LTS-001-006 | E7: 24 Bloc 22 Rue des Alamandas | F7: T1 | G7: occupé | H7: bon | I7: 1984
A8: 1 | B8: Sainte Cloitlde | C8: LTS-001 | D8: LTS-001-007 | E8: 12 Bloc 18 Rue des Alamandas | F8: T2 | G8: occupé | H8: bon | I8: 1984
A9: 1 | B9: Sainte Cloitlde | C9: LTS-001 | D9: LTS-001-008 | E9: 29 Bloc 24 Rue des Alamandas | F9: T3 | G9: occupé | H9: bon | I9: 1984
A10: 1 | B10: Sainte Cloitlde | C10: LTS-001 | D10: LTS-001-009 | E10: 13 Bloc 20 Rue des Alamandas | F10: T4 | G10: occupé | H10: bon | I10: 1984
A11: 1 | B11: Sainte Cloitlde | C11: LTS-001 | D11: LTS-001-010 | E11: 25 Bloc 24 Rue des Alamandas | F11: T1 | G11: occupé | H11: bon | I11: 1984
A12: 1 | B12: Sainte Cloitlde | C12: LTS-001 | D12: LTS-001-011 | E12: 2 Bloc 16 Rue des Alamandas | F12: T2 | G12: occupé | H12: bon | I12: 1984
A13: 1 | B13: Sainte Cloitlde | C13: LTS-001 | D13: LTS-001-012 | E13: 4 Bloc 16 Rue des Alamandas | F13: T3 | G13: occupé | H13: bon | I13: 1984
... A529: 2 | B529: Montagne 8eme | C529: LTS-034 | D529: LTS-034-015 | E529: 5 Allée des Fougères | F529: T3 | G529: occupé | H529: bon | I529: 1985

Sheet Occupants
A1: code_acces | B1: id_occupant | C1: nom | D1: prenom | E1: telephone_principal | F1: email | G1: staut | H1: titre | I1: date_titre | J1: impaye(€) | K1: date_entree | L1: date_sortie | M1: commentaire
A2: LTS-001-001 | B2: ALAM-001 | C2: RIVIERE | D2: Fabienne | E2: 0692670367 | G2: locataire | H2: oui | I2: 2025
A3: LTS-001-002 | B3: ALAM-002 | C3: ARAYE | D3: Evelyne | E3: 0262294396 | G3: locataire | H3: oui | I3: 2025
A4: LTS-001-003 | B4: ALAM-003 | C4: ARLANDON | D4: Jean Luc | E4: 0692253329 | G4: locataire | H4: oui | I4: 2025
A5: LTS-001-004 | B5: ALAM-004 | C5: CAZAMBO | D5: Jean François | E5: 0693137209 | G5: locataire | H5: oui | I5: 2025
A6: LTS-001-005 | B6: ALAM-005 | C6: CHANE LAW | D6: Jimmy | E6: 0692957824 | G6: locataire | H6: oui | I6: 2025
A7: LTS-001-006 | B7: ALAM-006 | C7: METELLUS | D7: Stéphane | E7: 0693044649 | G7: locataire | H7: oui | I7: 2025
A8: LTS-001-007 | B8: ALAM-007 | C8: FICHORA | D8: Armand | E8: 0262284589 | G8: locataire | H8: oui | I8: 2025
A9: LTS-001-008 | B9: ALAM-008 | C9: LOUISE | D9: Marie | E9: 0693051870 | G9: locataire | H9: oui | I9: 2025
A10: LTS-001-009 | B10: ALAM-009 | C10: GALTIER | D10: Rita Marie | E10: 0262293081 | G10: locataire | H10: oui | I10: 2025
A11: LTS-001-010 | B11: ALAM-010 | C11: GERVILLE | D11: Rose May | E11: 0692464983 | G11: locataire | H11: oui | I11: 2025
A12: LTS-001-011 | B12: ALAM-011 | C12: GRENIER | D12: Ruffine Marie | E12: 0262503633 | G12: locataire | H12: oui | I12: 2025
A13: LTS-001-012 | B13: ALAM-012 | C13: SAUTRON | D13: Willy David | E13: 0693634302 | G13: locataire | H13: oui | I13: 2025
... A39: LTS-004-001 | B39: BAR-001 | C39: ABDALAH BEDANI | D39: Marie Thérèse | E39: 0692128814 | G39: locataire | H39: oui | I39: 2025
A40: LTS-004-002 | B40: BAR-002 | C40: MAILLOT | E40: 0692209721 | G40: locataire | H40: oui | I40: 2025
A41: LTS-004-003 | B41: BAR-003 | C41: CARPIN VELLEYEN | D41: Maximin | E41: 0692353423 | G41: locataire | H41: oui | I41: 2025
A42: LTS-004-004 | B42: BAR-004 | C42: CLAIN | D42: Christian Daniel | E42: 0692102185 | G42: locataire | H42: oui | I42: 2025
A43: LTS-004-005 | B43: BAR-005 | C43: ELEONORE | D43: Yves Joseph | E43: 0692517903 | G43: locataire | H43: oui | I43: 2025
A44: LTS-004-006 | B44: BAR-006 | C44: ERINACINT | D44: Marie Régine | G44: locataire | H44: oui | I44: 2025
A45: LTS-004-007 | B45: BAR-007 | C45: ESPARON | D45: Marie Rose Andrée | E45: 0262418046 | G45: locataire | H45: oui | I45: 2025
A46: LTS-004-008 | B46: BAR-008 | C46: GRONDIN | D46: Joseph Jean Yves | E46: 0693945329 | G46: locataire | H46: oui | I46: 2025
A47: LTS-004-009 | B47: BAR-009 | C47: IBRAHIM | D47: Yousouf | E47: 0693850799 | G47: locataire | H47: oui | I47: 2025
A48: LTS-004-010 | B48: BAR-010 | C48: JOVIEN | D48: Marie Denise | E48: 0692218923 | G48: locataire | H48: oui | I48: 2025
A49: LTS-004-011 | B49: BAR-011 | C49: KAVO | D49: Marie Françoise | E49: 0692754305 | G49: locataire | H49: oui | I49: 2025
A50: LTS-004-012 | B50: BAR-012 | C50: LAVAL | D50: Yvette Marie Céline | E50: 0693017032 | G50: locataire | H50: oui | I50: 2025
A51: LTS-004-013 | B51: BAR-013 | C51: MADJINDA | D51: Halima | E51: 0693206157 | G51: locataire | H51: oui | I51: 2025
A52: LTS-004-014 | B52: BAR-014 | C52: MARKA | D52: Marie Mélanie | G52: locataire | H52: oui | I52: 2025
A53: LTS-004-015 | B53: BAR-015 | C53: M'HOUMADI | D53: Oussoufi | E53: 0692631773 | G53: locataire | H53: oui | I53: 2025
A54: LTS-004-016 | B54: BAR-016 | C54: MAHABO | G54: locataire | H54: oui | I54: 2025
A55: LTS-004-017 | B55: BAR-017 | C55: PAROS | D55: Simone | E55: 0692347454 | G55: locataire | H55: oui | I55: 2025
A56: LTS-004-018 | B56: BAR-018 | C56: PAYET | D56: David | E56: 0692328124 | G56: locataire | H56: oui | I56: 2025
A57: LTS-004-019 | B57: BAR-019 | C57: PAYET | D57: Marie Danielle | E57: 0692758155 | G57: locataire | H57: oui | I57: 2025
A58: LTS-004-020 | B58: BAR-020 | C58: RAVAT | D58: Fatema | E58: 0692677852 | G58: locataire | H58: oui | I58: 2025
A59: LTS-004-021 | B59: BAR-021 | C59: ROSENTAL | D59: Patricia | G59: locataire | H59: oui | I59: 2025
A60: LTS-004-022 | B60: BAR-022 | C60: SABABADICHETTY | D60: Jean Eric et Joseph Raoul | E60: 0692158289 | G60: locataire | H60: oui | I60: 2025
A61: LTS-004-023 | B61: BAR-023 | C61: SALEM | D61: Brice | E61: 0693311767 | G61: locataire | H61: oui | I61: 2025
A62: LTS-004-024 | B62: BAR-024 | C62: SANOLAH | D62: Eva Bibi | E62: 0692169701 | G62: locataire | H62: oui | I62: 2025
A63: LTS-004-025 | B63: BAR-025 | C63: ELIZEON | D63: Fabrice | E63: 0692856383 | G63: locataire | H63: oui | I63: 2025
A64: LTS-005-001 | B64: BIL-001 | C64: ARABOUT | D64: Darina | E64: 0693338433 | G64: locataire | H64: oui | I64: 2025
A65: LTS-005-002 | B65: BIL-002 | C65: BELVISEE | D65: Frédéric | E65: 0693046702 | G65: locataire | H65: oui | I65: 2025
A66: LTS-005-003 | B66: BIL-003 | C66: ROBERT | D66: Marie Sylvie | E66: 0692692306 | G66: locataire | H66: oui | I66: 2025
A67: LTS-005-004 | B67: BIL-004 | C67: BOYER | D67: Mimose | E67: 0692779160 | G67: locataire | H67: oui | I67: 2025
A68: LTS-005-005 | B68: BIL-005 | C68: BOYER | D68: Cyril Joseph | E68: 0692253800 | G68: locataire | H68: oui | I68: 2025
A69: LTS-005-006 | B69: BIL-006 | C69: ROCROU | D69: Camille Joël | E69: 0692828750 | G69: locataire | H69: oui | I69: 2025
A70: LTS-005-007 | B70: BIL-007 | C70: CHNAYTI | D70: Dounia | E70: 0692336953 | G70: locataire | H70: oui | I70: 2025
A71: LTS-005-008 | B71: BIL-008 | C71: HOAREAU | D71: Jenifer | E71: 0693431072 | G71: locataire | H71: oui | I71: 2025
... A87: LTS-005-024 | B87: BIL-024 | C87: VIDOT | D87: Marie Claude | E87: 0262977334 | G87: locataire | H87: oui | I87: 2025
A88: LTS-006-001 | B88: LAN-001 | C88: SAITI | E88: 0262989287 | G88: locataire | H88: oui | I88: 2025
A89: LTS-006-002 | B89: LAN-002 | C89: PANECHOU | E89: 0262526270 | G89: locataire | H89: oui | I89: 2025
A90: LTS-007-001 | B90: CAS-001 | C90: DIJOUX | D90: Sébastien | E90: 0692808959 | G90: locataire | H90: oui | I90: 2025
A91: LTS-007-002 | B91: CAS-002 | C91: PICARD | D91: Ignace Clémént | E91: 0692461865 | G91: locataire | H91: oui | I91: 2025
A92: LTS-007-003 | B92: CAS-003 | C92: HOARAU | D92: Sheila | E92: 0262302418 | G92: locataire | H92: oui | I92: 2025
A93: LTS-007-004 | B93: CAS-004 | C93: JOSON | D93: Marie Thérèse | G93: locataire | H93: oui | I93: 2025
A94: LTS-007-005 | B94: CAS-005 | C94: MAILLOT | D94: René-Claude | E94: 0262647470 | G94: locataire | H94: oui | I94: 2025
A95: LTS-007-006 | B95: CAS-006 | C95: MALAYA | D95: Jean Raymond | E95: 0262305300 | G95: locataire | H95: oui | I95: 2025
A96: LTS-007-007 | B96: CAS-007 | C96: MALAYA | D96: Simone | E96: 0262302939 | G96: locataire | H96: oui | I96: 2025
A97: LTS-007-008 | B97: CAS-008 | C97: NAZE | D97: Anne Marie Catherine | E97: 0262303814 | G97: locataire | H97: oui | I97: 2025
A98: LTS-007-009 | B98: CAS-009 | C98: TURPIN | D98: Marie Laetitia | E98: 0692181507 | G98: locataire | H98: oui | I98: 2025
A99: LTS-008-001 | B99: CLO-001 | C99: BATONNET | D99: Jeannine Yvette | E99: 0693300830 | G99: locataire | H99: oui | I99: 2025
A100: LTS-008-002 | B100: CLO-002 | C100: SALEZ | D100: Catherine | E100: 0693323223 | G100: locataire | H100: oui | I100: 2025
A101: LTS-008-003 | B101: CLO-003 | C101: BOYER | D101: Maryse Marie Christelle | E101: 0692885828 | G101: locataire | H101: oui | I101: 2025
A102: LTS-008-004 | B102: CLO-004 | C102: CALIAMA | D102: Antonine | E102: 0692137556 | G102: locataire | H102: oui | I102: 2025
A103: LTS-008-005 | B103: CLO-005 | C103: CAMARET | D103: Marie Céline | E103: 0262094914 | G103: locataire | H103: oui | I103: 2025
A104: LTS-008-006 | B104: CLO-006 | C104: CATHERINE | D104: Patrick | E104: 0693025951 | G104: locataire | H104: oui | I104: 2025
A105: LTS-008-007 | B105: CLO-007 | C105: DIJOUX | D105: Gilbert | E105: 0693416344 | G105: locataire | H105: oui | I105: 2025
A106: LTS-008-008 | B106: CLO-008 | C106: DIJOUX | D106: Stéphane | E106: 0693106390 | G106: locataire | H106: oui | I106: 2025
A107: LTS-008-009 | B107: CLO-009 | C107: FERINOUT | D107: Véronique | E107: 0692719141 | G107: occupant sans titre | H107: non
A108: LTS-008-010 | B108: CLO-010 | C108: GRONDIN | D108: David Jean Patrice | E108: 0692782489 | G108: locataire | H108: oui | I108: 2025
A109: LTS-008-011 | B109: CLO-011 | C109: INJIRAKY | D109: Lise May | E109: 0693431975 | G109: locataire | H109: oui | I109: 2025
A110: LTS-008-012 | B110: CLO-012 | C110: LAFABLE | D110: Benjy | E110: 0693111371 | G110: locataire | H110: oui | I110: 2025
A111: LTS-008-013 | B111: CLO-013 | C111: LEPINAY | D111: Marie Franceline | G111: locataire | H111: oui | I111: 2025
A112: LTS-008-014 | B112: CLO-014 | C112: MADI | D112: Hafoussoiti | E112: 0692748782 | G112: locataire | H112: oui | I112: 2025
A113: LTS-008-015 | B113: CLO-015 | C113: MALLARD | D113: Paul | E113: 0692861154 | G113: locataire | H113: oui | I113: 2025
A114: LTS-008-016 | B114: CLO-016 | C114: MOUCASSAGUENE | D114: Marie Roselyne | E114: 0692172537 | G114: occupant sans titre | H114: non
A115: LTS-008-017 | B115: CLO-017 | C115: CARPAYE | D115: JEAN GEOFFROY | E115: 0692801176 | G115: locataire | H115: oui | I115: 2025
A116: LTS-008-018 | B116: CLO-018 | C116: RAMDEEHUL | D116: Rajaram | E116: 0262294426 | G116: locataire | H116: oui | I116: 2025
A117: LTS-008-019 | B117: CLO-019 | C117: RASI | D117: Cédric | G117: locataire | H117: oui | I117: 2025
A118: LTS-008-020 | B118: CLO-020 | C118: ROBERT | D118: Yannick | E118: 0692333281 | G118: locataire | H118: oui | I118: 2025
A119: LTS-008-021 | B119: CLO-021 | C119: SERAPHIN | D119: Charles Eric | E119: 0692417734 | G119: locataire | H119: oui | I119: 2025
A120: LTS-008-022 | B120: CLO-022 | C120: TANGATCHY | D120: Marie Hélène DCD | E120: 0693653665 | G120: locataire | H120: oui | I120: 2025
A121: LTS-008-023 | B121: CLO-023 | C121: TETTONI | D121: Jean Luc | E121: 0693024925 | G121: locataire | H121: oui | I121: 2025
A122: LTS-008-024 | B122: CLO-024 | C122: THIONG KAY | D122: Jean Philippe | E122: 0692726315 | G122: locataire | H122: oui | I122: 2025
A123: LTS-008-025 | B123: CLO-025 | C123: THOMAS | D123: Jules Yoland | E123: 0692372329 | G123: locataire | H123: oui | I123: 2025
A124: LTS-008-026 | B124: CLO-026 | C124: TILIN | D124: Floris | E124: 0692827563 | G124: locataire | H124: oui | I124: 2025
A125: LTS-008-027 | B125: CLO-027 | G125: locataire | H125: oui | I125: 2025
A126: LTS-009-001 | B126: COM-001 | C126: LEBON | D126: Eliane Thérèse Gabrielle | E126: 0692731124 | G126: locataire | H126: oui | I126: 2025
A127: LTS-009-002 | B127: COM-002 | G127: locataire | H127: oui | I127: 2025
A128: LTS-010-001 | B128: EVI-001 | C128: GONTHIER | D128: Marie France | E128: 0692634942 | G128: locataire | H128: oui | I128: 2025
A129: LTS-010-002 | B129: EVI-002 | C129: NERINA | D129: Marie Daisy | G129: locataire | H129: oui | I129: 2025
A130: LTS-010-003 | B130: EVI-003 | C130: NODODUS | D130: Julien Mathias | E130: 0692412664 | G130: locataire | H130: oui | I130: 2025
A131: LTS-011-001 | B131: FIG-001 | C131: WILMANN | D131: Jean Paul | E131: 0692694696 | G131: locataire | H131: oui | I131: 2025
A132: LTS-011-002 | B132: FIG-002 | C132: GRONDIN | D132: Marie Claudine | G132: locataire | H132: oui | I132: 2025
A133: LTS-012-001 | B133: FIN-001 | C133: BATAILLE | D133: Jean Denis | E133: 0692200314 | G133: locataire | H133: oui | I133: 2025
A134: LTS-012-002 | B134: FIN-002 | C134: DAMOUR | D134: Marie Louisane | E134: 0262298121 | G134: locataire | H134: oui | I134: 2025
A135: LTS-012-003 | B135: FIN-003 | C135: DIJOUX | D135: Marie Alda | E135: 0692894841 | G135: locataire | H135: oui | I135: 2025
A136: LTS-012-004 | B136: FIN-004 | C136: IEVE PARIS | D136: Marie Rosita | E136: 0692564446 | G136: locataire | H136: oui | I136: 2025
A137: LTS-013-001 | B137: FR1-001 | C137: ADOLPHE VENEROSY | D137: Marie Mireille | E137: 0692438407 | G137: locataire | H137: oui | I137: 2025
A138: LTS-013-002 | B138: FR1-002 | C138: BOYER | D138: Jean Henri Fred | E138: 0692950415 | G138: locataire | H138: oui | I138: 2025
A139: LTS-013-003 | B139: FR1-003 | C139: DALLEAU | D139: Marie Berthe | E139: 0692694905 | G139: locataire | H139: oui | I139: 2025
A140: LTS-013-004 | B140: FR1-004 | C140: HOAREAU | D140: Jean Claude | E140: 0692273497 | G140: locataire | H140: oui | I140: 2025
...

Sheet Impayes
A1: id_occupant | B1: nom | C1: prenom | D1: montant | E1: staut
A2: ALAM-001 | B2: RIVIERE | C2: Fabienne
A3: ALAM-002 | B3: ARAYE | C3: Evelyne
A4: ALAM-003 | B4: ARLANDON | C4: Jean Luc
A5: ALAM-004 | B5: CAZAMBO | C5: Jean François
A6: ALAM-005 | B6: CHANE LAW | C6: Jimmy
A7: ALAM-006 | B7: METELLUS | C7: Stéphane
A8: ALAM-007 | B8: FICHORA | C8: Armand
A9: ALAM-008 | B9: LOUISE | C9: Marie
A10: ALAM-009 | B10: GALTIER | C10: Rita Marie
A11: ALAM-010 | B11: GERVILLE | C11: Rose May
A12: ALAM-011 | B12: GRENIER | C12: Ruffine Marie
A13: ALAM-012 | B13: SAUTRON | C13: Willy David
... A39: BAR-001 | B39: ABDALAH BEDANI | C39: Marie Thérèse
A40: BAR-002 | B40: MAILLOT
A41: BAR-003 | B41: CARPIN VELLEYEN | C41: Maximin
A42: BAR-004 | B42: CLAIN | C42: Christian Daniel
A43: BAR-005 | B43: ELEONORE | C43: Yves Joseph
A44: BAR-006 | B44: ERINACINT | C44: Marie Régine
A45: BAR-007 | B45: ESPARON | C45: Marie Rose Andrée
A46: BAR-008 | B46: GRONDIN | C46: Joseph Jean Yves
A47: BAR-009 | B47: IBRAHIM | C47: Yousouf
A48: BAR-010 | B48: JOVIEN | C48: Marie Denise
A49: BAR-011 | B49: KAVO | C49: Marie Françoise
A50: BAR-012 | B50: LAVAL | C50: Yvette Marie Céline
A51: BAR-013 | B51: MADJINDA | C51: Halima
A52: BAR-014 | B52: MARKA | C52: Marie Mélanie
A53: BAR-015 | B53: M'HOUMADI | C53: Oussoufi
A54: BAR-016 | B54: MAHABO
A55: BAR-017 | B55: PAROS | C55: Simone
A56: BAR-018 | B56: PAYET | C56: David
A57: BAR-019 | B57: PAYET | C57: Marie Danielle
A58: BAR-020 | B58: RAVAT | C58: Fatema
A59: BAR-021 | B59: ROSENTAL | C59: Patricia
A60: BAR-022 | B60: SABABADICHETTY | C60: Jean Eric et Joseph Raoul
A61: BAR-023 | B61: SALEM | C61: Brice
A62: BAR-024 | B62: SANOLAH | C62: Eva Bibi
A63: BAR-025 | B63: ELIZEON | C63: Fabrice
A64: BIL-001 | B64: ARABOUT | C64: Darina
A65: BIL-002 | B65: BELVISEE | C65: Frédéric
A66: BIL-003 | B66: ROBERT | C66: Marie Sylvie
... A87: BIL-024 | B87: VIDOT | C87: Marie Claude
A88: LAN-001 | B88: SAITI
A89: LAN-002 | B89: PANECHOU
A90: CAS-001 | B90: DIJOUX | C90: Sébastien
A91: CAS-002 | B91: PICARD | C91: Ignace Clémént
A92: CAS-003 | B92: HOARAU | C92: Sheila
A93: CAS-004 | B93: JOSON | C93: Marie Thérèse
A94: CAS-005 | B94: MAILLOT | C94: René-Claude
A95: CAS-006 | B95: MALAYA | C95: Jean Raymond
A96: CAS-007 | B96: MALAYA | C96: Simone
A97: CAS-008 | B97: NAZE | C97: Anne Marie Catherine
A98: CAS-009 | B98: TURPIN | C98: Marie Laetitia
A99: CLO-001 | B99: BATONNET | C99: Jeannine Yvette
A100: CLO-002 | B100: SALEZ | C100: Catherine
A101: CLO-003 | B101: BOYER | C101: Maryse Marie Christelle
... A124: CLO-026 | B124: TILIN | C124: Floris
A125: CLO-027
A126: COM-001 | B126: LEBON | C126: Eliane Thérèse Gabrielle
A127: COM-002
A128: EVI-001 | B128: GONTHIER | C128: Marie France
A129: EVI-002 | B129: NERINA | C129: Marie Daisy
A130: EVI-003 | B130: NODODUS | C130: Julien Mathias
A131: FIG-001 | B131: WILMANN | C131: Jean Paul
A132: FIG-002 | B132: GRONDIN | C132: Marie Claudine
A133: FIN-001 | B133: BATAILLE | C133: Jean Denis
A134: FIN-002 | B134: DAMOUR | C134: Marie Louisane
A135: FIN-003 | B135: DIJOUX | C135: Marie Alda
A136: FIN-004 | B136: IEVE PARIS | C136: Marie Rosita
A137: FR1-001 | B137: ADOLPHE VENEROSY | C137: Marie Mireille
A138: FR1-002 | B138: BOYER | C138: Jean Henri Fred
A139: FR1-003 | B139: DALLEAU | C139: Marie Berthe
... A156: FR3-002 | B156: FONTAINE | C156: Marie Céline Margarette
A157: FR3-003 | B157: GAUVIN
A158: FR3-004 | B158: IZOU | C158: Saint Ange
A159: FR3-005 | B159: LAUDE | C159: Jean Patrick
A160: FR3-006 | B160: LUSINIER | C160: Chantal
A161: FR3-007 | B161: RIVIERE | C161: Doris Nicolas
A162: FR3-008 | B162: ROULLIN | C162: Noëlio Franceau
A163: FR3-009 | B163: SAUTRON | C163: Jean Denis
A164: FR3-010 | B164: SAUTRON (EX RIVIERE) | C164: Gabrielle
A165: GIR-001 | B165: DUCHEMANN | C165: Anne Marie
A166: GIR-002 | B166: OINDA | C166: Marie Anasthasie
A167: GRE-001 | B167: BANOR | C167: Marie Céline
A168: GRE-002 | B168: BEGUE | C168: Gisèle Rénette
A169: GRE-003 | B169: BEGUE | C169: Eddy Jean Alain
... A205: GRE-039 | B205: REFITAHA | C205: Jessie Marie Christelle
A206: GRE-040
A207: GRE-041 | B207: SUMATRA | C207: Sully
A208: GRE-042 | B208: TIMON | C208: Bertrand
A209: GRE-043 | B209: DORMEUIL | C209: Freddy
A210: GRE-044 | B210: VIRAMA | C210: Jocelyn
A211: GRE-045 | B211: ZITTE | C211: Angélique
A212: JA1-001 | B212: APAYA | C212: Jean Paul
A213: JA1-002 | B213: AUBER | C213: Jean Pierre
A214: JA1-003 | B214: CHAMBAUD | C214: Marie Therese
A215: JA1-004 | B215: BARAKE | C215: Marie Thérèse
A216: JA1-005 | B216: BARAKE | C216: Marie Roseline
A217: JA1-006 | B217: BIDOIS | C217: Jean Pascal
A218: JA1-007 | B218: BORDIER | C218: Heliard
...

Sheet Gestion_Locative
A1: secteur | B1: code_lts | C1: code_acces | D1: nom_lts | E1: adresse_complete | F1: nom | G1: prenom | H1: telephone_principal | I1: telephone_secondaire | J1: assurance_ok | K1: avis_impot_ok | L1: piece_manquante | M1: renouvellement_bail | N1: date_echeance_bail | O1: etat_dossier | P1: derniere_signature_gestion | Q1: date_derniere_notif | R1: alerte_bail | S1: commentaire
A2: 1 | B2: LTS-001 | C2: LTS-001-001 | D2: ALAMANDAS | E2: 15 Bloc 20 Rue des Alamandas | F2: RIVIERE | G2: Fabienne | H2: 0692670367 | L2: non | M2: non | O2: =IF(L2="oui","incomplet",IF(OR(J2="non",K2="non"),"a_regulariser",IF(AND(J2="oui",K2="oui"),"ok","")))
A3: 1 | B3: LTS-001 | C3: LTS-001-002 | D3: ALAMANDAS | E3: 26 Bloc 24 Rue des Alamandas | F3: ARAYE | G3: Evelyne | H3: 0262294396 | I3: 0692085376 | L3: non | M3: non | O3: =IF(L3="oui","incomplet",IF(OR(J3="non",K3="non"),"a_regulariser",IF(AND(J3="oui",K3="oui"),"ok","")))
A4: 1 | B4: LTS-001 | C4: LTS-001-003 | D4: ALAMANDAS | E4: 19 Bloc 22 Rue des Alamandas | F4: ARLANDON | G4: Jean Luc | H4: 0692253329 | I4: 0692373955 | L4: non | M4: non | O4: =IF(L4="oui","incomplet",IF(OR(J4="non",K4="non"),"a_regulariser",IF(AND(J4="oui",K4="oui"),"ok","")))
A5: 1 | B5: LTS-001 | C5: LTS-001-004 | D5: ALAMANDAS | E5: 27 Bloc 24 Rue des Alamandas | F5: CAZAMBO | G5: Jean François | H5: 0693137209 | L5: non | M5: non | O5: =IF(L5="oui","incomplet",IF(OR(J5="non",K5="non"),"a_regulariser",IF(AND(J5="oui",K5="oui"),"ok","")))
A6: 1 | B6: LTS-001 | C6: LTS-001-005 | D6: ALAMANDAS | E6: 11 Bloc 18 Rue des Alamandas | F6: CHANE LAW | G6: Jimmy | H6: 0692957824 | L6: non | M6: non | O6: =IF(L6="oui","incomplet",IF(OR(J6="non",K6="non"),"a_regulariser",IF(AND(J6="oui",K6="oui"),"ok","")))
A7: 1 | B7: LTS-001 | C7: LTS-001-006 | D7: ALAMANDAS | E7: 24 Bloc 22 Rue des Alamandas | F7: METELLUS | G7: Stéphane | H7: 0693044649 | L7: non | M7: non | O7: =IF(L7="oui","incomplet",IF(OR(J7="non",K7="non"),"a_regulariser",IF(AND(J7="oui",K7="oui"),"ok","")))
A8: 1 | B8: LTS-001 | C8: LTS-001-007 | D8: ALAMANDAS | E8: 12 Bloc 18 Rue des Alamandas | F8: FICHORA | G8: Armand | H8: 0262284589 | L8: non | M8: non | O8: =IF(L8="oui","incomplet",IF(OR(J8="non",K8="non"),"a_regulariser",IF(AND(J8="oui",K8="oui"),"ok","")))
A9: 1 | B9: LTS-001 | C9: LTS-001-008 | D9: ALAMANDAS | E9: 29 Bloc 24 Rue des Alamandas | F9: LOUISE | G9: Marie | H9: 0693051870 | L9: non | M9: non | O9: =IF(L9="oui","incomplet",IF(OR(J9="non",K9="non"),"a_regulariser",IF(AND(J9="oui",K9="oui"),"ok","")))
A10: 1 | B10: LTS-001 | C10: LTS-001-009 | D10: ALAMANDAS | E10: 13 Bloc 20 Rue des Alamandas | F10: GALTIER | G10: Rita Marie | H10: 0262293081 | I10: 0692898654 | L10: non | M10: non | O10: =IF(L10="oui","incomplet",IF(OR(J10="non",K10="non"),"a_regulariser",IF(AND(J10="oui",K10="oui"),"ok","")))
A11: 1 | B11: LTS-001 | C11: LTS-001-010 | D11: ALAMANDAS | E11: 25 Bloc 24 Rue des Alamandas | F11: GERVILLE | G11: Rose May | H11: 0692464983 | L11: non | M11: non | O11: =IF(L11="oui","incomplet",IF(OR(J11="non",K11="non"),"a_regulariser",IF(AND(J11="oui",K11="oui"),"ok","")))
A12: 1 | B12: LTS-001 | C12: LTS-001-011 | D12: ALAMANDAS | E12: 2 Bloc 16 Rue des Alamandas | F12: GRENIER | G12: Ruffine Marie | H12: 0262503633 | I12: 0692190983 | L12: non | M12: non | O12: =IF(L12="oui","incomplet",IF(OR(J12="non",K12="non"),"a_regulariser",IF(AND(J12="oui",K12="oui"),"ok","")))
A13: 1 | B13: LTS-001 | C13: LTS-001-012 | D13: ALAMANDAS | E13: 4 Bloc 16 Rue des Alamandas | F13: SAUTRON | G13: Willy David | H13: 0693634302 | I13: 0692084218 / 0692494271 | L13: non | M13: non | O13: =IF(L13="oui","incomplet",IF(OR(J13="non",K13="non"),"a_regulariser",IF(AND(J13="oui",K13="oui"),"ok","")))
A14: 1 | B14: LTS-001 | C14: LTS-001-013 | D14: ALAMANDAS | E14: 9 Bloc 18 Rue des Alamandas | F14: LAFABLE | G14: Philippe | H14: 0692467006 | L14: non | M14: non | O14: =IF(L14="oui","incomplet",IF(OR(J14="non",K14="non"),"a_regulariser",IF(AND(J14="oui",K14="oui"),"ok","")))
A15: 1 | B15: LTS-001 | C15: LTS-001-014 | D15: ALAMANDAS | E15: 14 Bloc 20 Rue des Alamandas | F15: LAURENT | G15: Jean René | H15: 0262289120 | L15: non | M15: non | O15: =IF(L15="oui","incomplet",IF(OR(J15="non",K15="non"),"a_regulariser",IF(AND(J15="oui",K15="oui"),"ok","")))
A16: 1 | B16: LTS-001 | C16: LTS-001-015 | D16: ALAMANDAS | E16: 16 Bloc 20 Rue des Alamandas | F16: LAURENT | G16: Jean Bernard | H16: 0692916258 | L16: non | M16: non | O16: =IF(L16="oui","incomplet",IF(OR(J16="non",K16="non"),"a_regulariser",IF(AND(J16="oui",K16="oui"),"ok","")))
A17: 1 | B17: LTS-001 | C17: LTS-001-016 | D17: ALAMANDAS | E17: 3 Bloc 16 Rue des Alamandas | F17: MARKA | G17: Claude | H17: 0692906779 | L17: non | M17: non | O17: =IF(L17="oui","incomplet",IF(OR(J17="non",K17="non"),"a_regulariser",IF(AND(J17="oui",K17="oui"),"ok","")))
A18: 1 | B18: LTS-001 | C18: LTS-001-017 | D18: ALAMANDAS | E18: 30 Bloc 24 Rue des Alamandas | F18: MOUTOUSSAMY | G18: Jacques Antoine | H18: 0692807626 | I18: 0262190122 | L18: non | M18: non | O18: =IF(L18="oui","incomplet",IF(OR(J18="non",K18="non"),"a_regulariser",IF(AND(J18="oui",K18="oui"),"ok","")))
A19: 1 | B19: LTS-001 | C19: LTS-001-018 | D19: ALAMANDAS | E19: 20 Bloc 22 Rue des Alamandas | F19: PAYET | G19: Josiane Aline | H19: 0262504956 | I19: 0692677087 | L19: non | M19: non | O19: =IF(L19="oui","incomplet",IF(OR(J19="non",K19="non"),"a_regulariser",IF(AND(J19="oui",K19="oui"),"ok","")))
A20: 1 | B20: LTS-001 | C20: LTS-001-019 | D20: ALAMANDAS | E20: 8 Bloc 18 Rue des Alamandas | F20: ROBERT | G20: Jean Patrick | H20: 0692668371 | I20: 0692916112 | L20: non | M20: non | O20: =IF(L20="oui","incomplet",IF(OR(J20="non",K20="non"),"a_regulariser",IF(AND(J20="oui",K20="oui"),"ok","")))
A21: 1 | B21: LTS-001 | C21: LTS-001-020 | D21: ALAMANDAS | E21: 5 Bloc 16 Rue des Alamandas | F21: REFANE | G21: Marie Virginie | H21: 0692860902 | L21: non | M21: non | O21: =IF(L21="oui","incomplet",IF(OR(J21="non",K21="non"),"a_regulariser",IF(AND(J21="oui",K21="oui"),"ok","")))
A22: 1 | B22: LTS-001 | C22: LTS-001-021 | D22: ALAMANDAS | E22: 6 Bloc 16 Rue des Alamandas | F22: SINAPAYEN SINAMALE | G22: Henriette | H22: 0693860123 | I22: 0692143045 | L22: non | M22: non | O22: =IF(L22="oui","incomplet",IF(OR(J22="non",K22="non"),"a_regulariser",IF(AND(J22="oui",K22="oui"),"ok","")))
A23: 1 | B23: LTS-001 | C23: LTS-001-022 | D23: ALAMANDAS | E23: 7 Bloc 18 Rue des Alamandas | F23: MARKA | G23: GREGORY | H23: 0692843883 | L23: non | M23: non | O23: =IF(L23="oui","incomplet",IF(OR(J23="non",K23="non"),"a_regulariser",IF(AND(J23="oui",K23="oui"),"ok","")))
A24: 1 | B24: LTS-001 | C24: LTS-001-023 | D24: ALAMANDAS | E24: 10 Bloc 18 Rue des Alamandas | F24: TECHER | G24: Jean Fabrice | H24: 0693546553 | L24: non | M24: non | O24: =IF(L24="oui","incomplet",IF(OR(J24="non",K24="non"),"a_regulariser",IF(AND(J24="oui",K24="oui"),"ok","")))
A25: 1 | B25: LTS-001 | C25: LTS-001-024 | D25: ALAMANDAS | E25: 1 Bloc 16 Rue des Alamandas | F25: TECHER | G25: Joseph Francis | H25: 0692487884 | L25: non | M25: non | O25: =IF(L25="oui","incomplet",IF(OR(J25="non",K25="non"),"a_regulariser",IF(AND(J25="oui",K25="oui"),"ok","")))
A26: 1 | B26: LTS-001 | C26: LTS-001-025 | D26: ALAMANDAS | E26: 23 Bloc 22 Rue des Alamandas | F26: VIRAPIN CAROUMBIN | G26: Marie-Josée | H26: 0692689202 | L26: non | M26: non | O26: =IF(L26="oui","incomplet",IF(OR(J26="non",K26="non"),"a_regulariser",IF(AND(J26="oui",K26="oui"),"ok","")))
A27: 1 | B27: LTS-001 | C27: LTS-001-026 | D27: ALAMANDAS | E27: 17 Bloc 20 Rue des Alamandas | F27: CORRE | G27: Laurianne Emmanuelle | H27: 0692842718 | I27: 0692341364 | L27: non | M27: non | O27: =IF(L27="oui","incomplet",IF(OR(J27="non",K27="non"),"a_regulariser",IF(AND(J27="oui",K27="oui"),"ok","")))
A28: 1 | B28: LTS-001 | C28: LTS-001-027 | D28: ALAMANDAS | E28: 21 Bloc 22 Rue des Alamandas | F28: SEVERIN | G28: André Claude | H28: 0692922924 | I28: 0693283029 / 0692661125 | L28: non | M28: non | O28: =IF(L28="oui","incomplet",IF(OR(J28="non",K28="non"),"a_regulariser",IF(AND(J28="oui",K28="oui"),"ok","")))
A29: 1 | B29: LTS-001 | C29: LTS-001-028 | D29: ALAMANDAS | E29: 22 Bloc 22 Rue des Alamandas | F29: LAURENT | G29: Thomas | H29: 0692139045 | L29: non | M29: non | O29: =IF(L29="oui","incomplet",IF(OR(J29="non",K29="non"),"a_regulariser",IF(AND(J29="oui",K29="oui"),"ok","")))
A30: 1 | B30: LTS-001 | C30: LTS-001-029 | D30: ALAMANDAS | E30: 28 Bloc 24 Rue des Alamandas | F30: LAURENT | G30: Jean Alain | H30: 0692590826 | I30: 0692946258 / 0693823305 | L30: non | M30: non | O30: =IF(L30="oui","incomplet",IF(OR(J30="non",K30="non"),"a_regulariser",IF(AND(J30="oui",K30="oui"),"ok","")))
A31: 1 | B31: LTS-001 | C31: LTS-001-030 | D31: ALAMANDAS | E31: 18 Bloc 20 Rue des Alamandas | F31: FIBAC | G31: Marie Hélène | H31: 0692660767 | L31: non | M31: non | O31: =IF(L31="oui","incomplet",IF(OR(J31="non",K31="non"),"a_regulariser",IF(AND(J31="oui",K31="oui"),"ok","")))
A32: 1 | B32: LTS-002 | C32: LTS-002-001 | D32: ATTES | E32: 37 Rue du Stade de L'Est | F32: ANDRIANA | G32: Marie Françoise | H32: 0693525546 | I32: 0692547291 | L32: non | M32: non | O32: =IF(L32="oui","incomplet",IF(OR(J32="non",K32="non"),"a_regulariser",IF(AND(J32="oui",K32="oui"),"ok","")))
A33: 1 | B33: LTS-002 | C33: LTS-002-002 | D33: ATTES | E33: 23 Rue des Lavandières | F33: HIVANHOE | G33: Jean Patrick | H33: 0262902947 | L33: non | M33: non | O33: =IF(L33="oui","incomplet",IF(OR(J33="non",K33="non"),"a_regulariser",IF(AND(J33="oui",K33="oui"),"ok","")))
A34: 1 | B34: LTS-002 | C34: LTS-002-003 | D34: ATTES | E34: 11 Rue des Lavandières | F34: MASSEAUX | G34: Clarisse Alida | H34: 0692260455 | L34: non | M34: non | O34: =IF(L34="oui","incomplet",IF(OR(J34="non",K34="non"),"a_regulariser",IF(AND(J34="oui",K34="oui"),"ok","")))
A35: 3 | B35: LTS-003 | C35: LTS-003-001 | D35: AZALEES | E35: 107 Route des Azalées | F35: IMAHO | G35: Emmanuelle Anne Gaëlle | H35: 0692631658 | I35: 0693111634 | L35: non | M35: non | O35: =IF(L35="oui","incomplet",IF(OR(J35="non",K35="non"),"a_regulariser",IF(AND(J35="oui",K35="oui"),"ok","")))
A36: 3 | B36: LTS-003 | C36: LTS-003-002 | D36: AZALEES | E36: 111 Route des Azalées | F36: IFIANTEPIA | G36: occupé en attente decision | H36: 0692229197 | L36: non | M36: non | O36: =IF(L36="oui","incomplet",IF(OR(J36="non",K36="non"),"a_regulariser",IF(AND(J36="oui",K36="oui"),"ok","")))
A37: 3 | B37: LTS-003 | C37: LTS-003-003 | D37: AZALEES | E37: 107 ter Route des Azalées | F37: THOMAS NÉE TURPIN | G37: Marie Micheline | H37: 0692587339 | L37: non | M37: non | O37: =IF(L37="oui","incomplet",IF(OR(J37="non",K37="non"),"a_regulariser",IF(AND(J37="oui",K37="oui"),"ok","")))
A38: 3 | B38: LTS-003 | C38: LTS-003-004 | D38: AZALEES | E38: 107 bis Route des Azalées | F38: POLEYA | G38: Joachim | H38: 0692743656 | L38: non | M38: non | O38: =IF(L38="oui","incomplet",IF(OR(J38="non",K38="non"),"a_regulariser",IF(AND(J38="oui",K38="oui"),"ok","")))
A39: 2 | B39: LTS-004 | C39: LTS-004-001 | D39: BARBADINES | E39: 65 Ruelle Marcadet | F39: ABDALAH BEDANI | G39: Marie Thérèse | H39: 0692128814 | L39: non | M39: non | O39: =IF(L39="oui","incomplet",IF(OR(J39="non",K39="non"),"a_regulariser",IF(AND(J39="oui",K39="oui"),"ok","")))
A40: 2 | B40: LTS-004 | C40: LTS-004-002 | D40: BARBADINES | E40: 45 Ruelle Marcadet | F40: MAILLOT | H40: 0692209721 | L40: non | M40: non | O40: =IF(L40="oui","incomplet",IF(OR(J40="non",K40="non"),"a_regulariser",IF(AND(J40="oui",K40="oui"),"ok","")))
A41: 2 | B41: LTS-004 | C41: LTS-004-003 | D41: BARBADINES | E41: 25 Ruelle Marcadet | F41: CARPIN VELLEYEN | G41: Maximin | H41: 0692353423 | I41: 0692326054 / 0692362257 | L41: non | M41: non | O41: =IF(L41="oui","incomplet",IF(OR(J41="non",K41="non"),"a_regulariser",IF(AND(J41="oui",K41="oui"),"ok","")))
A42: 2 | B42: LTS-004 | C42: LTS-004-004 | D42: BARBADINES | E42: 47 Ruelle Marcadet | F42: CLAIN | G42: Christian Daniel | H42: 0692102185 | L42: non | M42: non | O42: =IF(L42="oui","incomplet",IF(OR(J42="non",K42="non"),"a_regulariser",IF(AND(J42="oui",K42="oui"),"ok","")))
A43: 2 | B43: LTS-004 | C43: LTS-004-005 | D43: BARBADINES | E43: 21 Ruelle Marcadet | F43: ELEONORE | G43: Yves Joseph | H43: 0692517903 | L43: non | M43: non | O43: =IF(L43="oui","incomplet",IF(OR(J43="non",K43="non"),"a_regulariser",IF(AND(J43="oui",K43="oui"),"ok","")))
A44: 2 | B44: LTS-004 | C44: LTS-004-006 | D44: BARBADINES | E44: 63 Ruelle Marcadet | F44: ERINACINT | G44: Marie Régine | L44: non | M44: non | O44: =IF(L44="oui","incomplet",IF(OR(J44="non",K44="non"),"a_regulariser",IF(AND(J44="oui",K44="oui"),"ok","")))
A45: 2 | B45: LTS-004 | C45: LTS-004-007 | D45: BARBADINES | E45: 9 Ruelle Marcadet | F45: ESPARON | G45: Marie Rose Andrée | H45: 0262418046 | L45: non | M45: non | O45: =IF(L45="oui","incomplet",IF(OR(J45="non",K45="non"),"a_regulariser",IF(AND(J45="oui",K45="oui"),"ok","")))
A46: 2 | B46: LTS-004 | C46: LTS-004-008 | D46: BARBADINES | E46: 61 Ruelle Marcadet | F46: GRONDIN | G46: Joseph Jean Yves | H46: 0693945329 | I46: 0692769137 | L46: non | M46: non | O46: =IF(L46="oui","incomplet",IF(OR(J46="non",K46="non"),"a_regulariser",IF(AND(J46="oui",K46="oui"),"ok","")))
A47: 2 | B47: LTS-004 | C47: LTS-004-009 | D47: BARBADINES | E47: 55 Ruelle Marcadet | F47: IBRAHIM | G47: Yousouf | H47: 0693850799 | I47: 0262415521 | L47: non | M47: non | O47: =IF(L47="oui","incomplet",IF(OR(J47="non",K47="non"),"a_regulariser",IF(AND(J47="oui",K47="oui"),"ok","")))
A48: 2 | B48: LTS-004 | C48: LTS-004-010 | D48: BARBADINES | E48: 41 Ruelle Marcadet | F48: JOVIEN | G48: Marie Denise | H48: 0692218923 | L48: non | M48: non | O48: =IF(L48="oui","incomplet",IF(OR(J48="non",K48="non"),"a_regulariser",IF(AND(J48="oui",K48="oui"),"ok","")))
A49: 2 | B49: LTS-004 | C49: LTS-004-011 | D49: BARBADINES | E49: 53 Ruelle Marcadet | F49: KAVO | G49: Marie Françoise | H49: 0692754305 | L49: non | M49: non | O49: =IF(L49="oui","incomplet",IF(OR(J49="non",K49="non"),"a_regulariser",IF(AND(J49="oui",K49="oui"),"ok","")))
A50: 2 | B50: LTS-004 | C50: LTS-004-012 | D50: BARBADINES | E50: 69 Ruelle Marcadet | F50: LAVAL | G50: Yvette Marie Céline | H50: 0693017032 | I50: 0692934231 | L50: non | M50: non | O50: =IF(L50="oui","incomplet",IF(OR(J50="non",K50="non"),"a_regulariser",IF(AND(J50="oui",K50="oui"),"ok","")))
A51: 2 | B51: LTS-004 | C51: LTS-004-013 | D51: BARBADINES | E51: 33 Ruelle Marcadet | F51: MADJINDA | G51: Halima | H51: 0693206157 | L51: non | M51: non | O51: =IF(L51="oui","incomplet",IF(OR(J51="non",K51="non"),"a_regulariser",IF(AND(J51="oui",K51="oui"),"ok","")))
A52: 2 | B52: LTS-004 | C52: LTS-004-014 | D52: BARBADINES | E52: 71 Ruelle Marcadet | F52: MARKA | G52: Marie Mélanie | L52: non | M52: non | O52: =IF(L52="oui","incomplet",IF(OR(J52="non",K52="non"),"a_regulariser",IF(AND(J52="oui",K52="oui"),"ok","")))
A53: 2 | B53: LTS-004 | C53: LTS-004-015 | D53: BARBADINES | E53: 57 Ruelle Marcadet | F53: M'HOUMADI | G53: Oussoufi | H53: 0692631773 | L53: non | M53: non | O53: =IF(L53="oui","incomplet",IF(OR(J53="non",K53="non"),"a_regulariser",IF(AND(J53="oui",K53="oui"),"ok","")))
A54: 2 | B54: LTS-004 | C54: LTS-004-016 | D54: BARBADINES | E54: 23 Ruelle Marcadet | F54: MAHABO | L54: non | M54: non | O54: =IF(L54="oui","incomplet",IF(OR(J54="non",K54="non"),"a_regulariser",IF(AND(J54="oui",K54="oui"),"ok","")))
A55: 2 | B55: LTS-004 | C55: LTS-004-017 | D55: BARBADINES | E55: 27 Ruelle Marcadet | F55: PAROS | G55: Simone | H55: 0692347454 | L55: non | M55: non | O55: =IF(L55="oui","incomplet",IF(OR(J55="non",K55="non"),"a_regulariser",IF(AND(J55="oui",K55="oui"),"ok","")))
A56: 2 | B56: LTS-004 | C56: LTS-004-018 | D56: BARBADINES | E56: 13 Ruelle Marcadet | F56: PAYET | G56: David | H56: 0692328124 | L56: non | M56: non | O56: =IF(L56="oui","incomplet",IF(OR(J56="non",K56="non"),"a_regulariser",IF(AND(J56="oui",K56="oui"),"ok","")))
A57: 2 | B57: LTS-004 | C57: LTS-004-019 | D57: BARBADINES | E57: 39 Ruelle Marcadet | F57: PAYET | G57: Marie Danielle | H57: 0692758155 | L57: non | M57: non | O57: =IF(L57="oui","incomplet",IF(OR(J57="non",K57="non"),"a_regulariser",IF(AND(J57="oui",K57="oui"),"ok","")))
A58: 2 | B58: LTS-004 | C58: LTS-004-020 | D58: BARBADINES | E58: 15 Ruelle Marcadet | F58: RAVAT | G58: Fatema | H58: 0692677852 | L58: non | M58: non | O58: =IF(L58="oui","incomplet",IF(OR(J58="non",K58="non"),"a_regulariser",IF(AND(J58="oui",K58="oui"),"ok","")))
A59: 2 | B59: LTS-004 | C59: LTS-004-021 | D59: BARBADINES | E59: 29 Ruelle Marcadet | F59: ROSENTAL | G59: Patricia | L59: non | M59: non | O59: =IF(L59="oui","incomplet",IF(OR(J59="non",K59="non"),"a_regulariser",IF(AND(J59="oui",K59="oui"),"ok","")))
A60: 2 | B60: LTS-004 | C60: LTS-004-022 | D60: BARBADINES | E60: 67 Ruelle Marcadet | F60: SABABADICHETTY | G60: Jean Eric et Joseph Raoul | H60: 0692158289 | I60: 0693527699 | L60: non | M60: non | O60: =IF(L60="oui","incomplet",IF(OR(J60="non",K60="non"),"a_regulariser",IF(AND(J60="oui",K60="oui"),"ok","")))
A61: 2 | B61: LTS-004 | C61: LTS-004-023 | D61: BARBADINES | E61: 31 Ruelle Marcadet | F61: SALEM | G61: Brice | H61: 0693311767 | I61: 0692186561 | L61: non | M61: non | O61: =IF(L61="oui","incomplet",IF(OR(J61="non",K61="non"),"a_regulariser",IF(AND(J61="oui",K61="oui"),"ok","")))
A62: 2 | B62: LTS-004 | C62: LTS-004-024 | D62: BARBADINES | E62: 43 Ruelle Marcadet | F62: SANOLAH | G62: Eva Bibi | H62: 0692169701 | L62: non | M62: non | O62: =IF(L62="oui","incomplet",IF(OR(J62="non",K62="non"),"a_regulariser",IF(AND(J62="oui",K62="oui"),"ok","")))
A63: 2 | B63: LTS-004 | C63: LTS-004-025 | D63: BARBADINES | E63: 49 Ruelle Marcadet | F63: ELIZEON | G63: Fabrice | H63: 0692856383 | L63: non | M63: non | O63: =IF(L63="oui","incomplet",IF(OR(J63="non",K63="non"),"a_regulariser",IF(AND(J63="oui",K63="oui"),"ok","")))
A64: 4 | B64: LTS-005 | C64: LTS-005-001 | D64: BILIMBIS | E64: 5 Impasse des Bilimbis | F64: ARABOUT | G64: Darina | H64: 0693338433 | L64: non | M64: non | O64: =IF(L64="oui","incomplet",IF(OR(J64="non",K64="non"),"a_regulariser",IF(AND(J64="oui",K64="oui"),"ok","")))
A65: 4 | B65: LTS-005 | C65: LTS-005-002 | D65: BILIMBIS | E65: 18 Impasse des Bilimbis | F65: BELVISEE | G65: Frédéric | H65: 0693046702 | L65: non | M65: non | O65: =IF(L65="oui","incomplet",IF(OR(J65="non",K65="non"),"a_regulariser",IF(AND(J65="oui",K65="oui"),"ok","")))
A66: 4 | B66: LTS-005 | C66: LTS-005-003 | D66: BILIMBIS | E66: 16 Impasse des Bilimbis | F66: ROBERT | G66: Marie Sylvie | H66: 0692692306 | L66: non | M66: non | O66: =IF(L66="oui","incomplet",IF(OR(J66="non",K66="non"),"a_regulariser",IF(AND(J66="oui",K66="oui"),"ok","")))
A67: 4 | B67: LTS-005 | C67: LTS-005-004 | D67: BILIMBIS | E67: 33 Impasse des Bilimbis | F67: BOYER | G67: Mimose | H67: 0692779160 | L67: non | M67: non | O67: =IF(L67="oui","incomplet",IF(OR(J67="non",K67="non"),"a_regulariser",IF(AND(J67="oui",K67="oui"),"ok","")))
A68: 4 | B68: LTS-005 | C68: LTS-005-005 | D68: BILIMBIS | E68: 8 Impasse des Bilimbis | F68: BOYER | G68: Cyril Joseph | H68: 0692253800 | L68: non | M68: non | O68: =IF(L68="oui","incomplet",IF(OR(J68="non",K68="non"),"a_regulariser",IF(AND(J68="oui",K68="oui"),"ok","")))
A69: 4 | B69: LTS-005 | C69: LTS-005-006 | D69: BILIMBIS | E69: 21 Impasse des Bilimbis | F69: ROCROU | G69: Camille Joël | H69: 0692828750 | L69: non | M69: non | O69: =IF(L69="oui","incomplet",IF(OR(J69="non",K69="non"),"a_regulariser",IF(AND(J69="oui",K69="oui"),"ok","")))
A70: 4 | B70: LTS-005 | C70: LTS-005-007 | D70: BILIMBIS | E70: 19 Impasse des Bilimbis | F70: CHNAYTI | G70: Dounia | H70: 0692336953 | I70: 0262577819 | L70: non | M70: non | O70: =IF(L70="oui","incomplet",IF(OR(J70="non",K70="non"),"a_regulariser",IF(AND(J70="oui",K70="oui"),"ok","")))
A71: 4 | B71: LTS-005 | C71: LTS-005-008 | D71: BILIMBIS | E71: 12 Impasse des Bilimbis | F71: HOAREAU | G71: Jenifer | H71: 0693431072 | L71: non | M71: non | O71: =IF(L71="oui","incomplet",IF(OR(J71="non",K71="non"),"a_regulariser",IF(AND(J71="oui",K71="oui"),"ok","")))
A72: 4 | B72: LTS-005 | C72: LTS-005-009 | D72: BILIMBIS | E72: 17 Impasse des Bilimbis | F72: GRONDIN | G72: Marie Michèle | H72: 0262221550 | I72: 0692022133 | L72: non | M72: non | O72: =IF(L72="oui","incomplet",IF(OR(J72="non",K72="non"),"a_regulariser",IF(AND(J72="oui",K72="oui"),"ok","")))
A73: 4 | B73: LTS-005 | C73: LTS-005-010 | D73: BILIMBIS | E73: 10 Impasse des Bilimbis | F73: HOAREAU | G73: Suzette Lourdes | H73: 0262298512 | L73: non | M73: non | O73: =IF(L73="oui","incomplet",IF(OR(J73="non",K73="non"),"a_regulariser",IF(AND(J73="oui",K73="oui"),"ok","")))
A74: 4 | B74: LTS-005 | C74: LTS-005-011 | D74: BILIMBIS | E74: 11 Impasse des Bilimbis | F74: HUET | G74: Marie Ingrid | H74: 0692809596 | L74: non | M74: non | O74: =IF(L74="oui","incomplet",IF(OR(J74="non",K74="non"),"a_regulariser",IF(AND(J74="oui",K74="oui"),"ok","")))
A75: 4 | B75: LTS-005 | C75: LTS-005-012 | D75: BILIMBIS | E75: 3 Impasse des Bilimbis | F75: ICHOUZA | G75: Béatrice | H75: 0262234375 | I75: 0692619143 | L75: non | M75: non | O75: =IF(L75="oui","incomplet",IF(OR(J75="non",K75="non"),"a_regulariser",IF(AND(J75="oui",K75="oui"),"ok","")))
A76: 4 | B76: LTS-005 | C76: LTS-005-013 | D76: BILIMBIS | E76: 1 Impasse des Bilimbis | F76: ICHOUZA | G76: Marie Gladys | H76: 0692799962 | L76: non | M76: non | O76: =IF(L76="oui","incomplet",IF(OR(J76="non",K76="non"),"a_regulariser",IF(AND(J76="oui",K76="oui"),"ok","")))
A77: 4 | B77: LTS-005 | C77: LTS-005-014 | D77: BILIMBIS | E77: 28 Impasse des Bilimbis | F77: IMIRA | G77: Marie Rita | H77: 0692782803 | L77: non | M77: non | O77: =IF(L77="oui","incomplet",IF(OR(J77="non",K77="non"),"a_regulariser",IF(AND(J77="oui",K77="oui"),"ok","")))
A78: 4 | B78: LTS-005 | C78: LTS-005-015 | D78: BILIMBIS | E78: 25 Impasse des Bilimbis | F78: JEAN BAPTISTE | G78: Alexandra | H78: 0692374881 | L78: non | M78: non | O78: =IF(L78="oui","incomplet",IF(OR(J78="non",K78="non"),"a_regulariser",IF(AND(J78="oui",K78="oui"),"ok","")))
A79: 4 | B79: LTS-005 | C79: LTS-005-016 | D79: BILIMBIS | E79: 13 Impasse des Bilimbis | F79: LEBON | G79: Rock | H79: 0692903963 | L79: non | M79: non | O79: =IF(L79="oui","incomplet",IF(OR(J79="non",K79="non"),"a_regulariser",IF(AND(J79="oui",K79="oui"),"ok","")))
A80: 4 | B80: LTS-005 | C80: LTS-005-017 | D80: BILIMBIS | E80: 30 Impasse des Bilimbis | F80: LEBRETON | G80: Yanito | H80: 0692922592 | L80: non | M80: non | O80: =IF(L80="oui","incomplet",IF(OR(J80="non",K80="non"),"a_regulariser",IF(AND(J80="oui",K80="oui"),"ok","")))
A81: 4 | B81: LTS-005 | C81: LTS-005-018 | D81: BILIMBIS | E81: 20 Impasse des Bilimbis | F81: KIBIO | G81: Kayliane | H81: 0692496477 | I81: 0693450257 | L81: non | M81: non | O81: =IF(L81="oui","incomplet",IF(OR(J81="non",K81="non"),"a_regulariser",IF(AND(J81="oui",K81="oui"),"ok","")))
A82: 4 | B82: LTS-005 | C82: LTS-005-019 | D82: BILIMBIS | E82: 2 Impasse des Bilimbis | F82: ROBERT | G82: Eugénie | H82: 0692826196 | L82: non | M82: non | O82: =IF(L82="oui","incomplet",IF(OR(J82="non",K82="non"),"a_regulariser",IF(AND(J82="oui",K82="oui"),"ok","")))
A83: 4 | B83: LTS-005 | C83: LTS-005-020 | D83: BILIMBIS | E83: 26 Impasse des Bilimbis | F83: SADON | G83: Marie Jeanine | H83: 0693049639 | I83: 0262134356 | L83: non | M83: non | O83: =IF(L83="oui","incomplet",IF(OR(J83="non",K83="non"),"a_regulariser",IF(AND(J83="oui",K83="oui"),"ok","")))
A84: 4 | B84: LTS-005 | C84: LTS-005-021 | D84: BILIMBIS | E84: 4 Impasse des Bilimbis | F84: SINAN | G84: Marie Anièle | H84: 0693037800 | L84: non | M84: non | O84: =IF(L84="oui","incomplet",IF(OR(J84="non",K84="non"),"a_regulariser",IF(AND(J84="oui",K84="oui"),"ok","")))
A85: 4 | B85: LTS-005 | C85: LTS-005-022 | D85: BILIMBIS | E85: 27 Impasse des Bilimbis | F85: TURPIN | G85: Josian | H85: 0692916291 | L85: non | M85: non | O85: =IF(L85="oui","incomplet",IF(OR(J85="non",K85="non"),"a_regulariser",IF(AND(J85="oui",K85="oui"),"ok","")))
A86: 4 | B86: LTS-005 | C86: LTS-005-023 | D86: BILIMBIS | E86: 9 Impasse des Bilimbis | F86: TURPIN | G86: Marie Julienne | H86: 0262299212 | I86: 0692697117 | L86: non | M86: non | O86: =IF(L86="oui","incomplet",IF(OR(J86="non",K86="non"),"a_regulariser",IF(AND(J86="oui",K86="oui"),"ok","")))
A87: 4 | B87: LTS-005 | C87: LTS-005-024 | D87: BILIMBIS | E87: 23 Impasse des Bilimbis | F87: VIDOT | G87: Marie Claude | H87: 0262977334 | I87: 0693802564 | L87: non | M87: non | O87: =IF(L87="oui","incomplet",IF(OR(J87="non",K87="non"),"a_regulariser",IF(AND(J87="oui",K87="oui"),"ok","")))
A88: 4 | B88: LTS-006 | C88: LTS-006-001 | D88: LANGAVANT | E88: 18D CH DE LANGAVANT | F88: SAITI | H88: 0262989287 | L88: non | M88: non | O88: =IF(L88="oui","incomplet",IF(OR(J88="non",K88="non"),"a_regulariser",IF(AND(J88="oui",K88="oui"),"ok","")))
A89: 4 | B89: LTS-006 | C89: LTS-006-002 | D89: LANGAVANT | E89: 18C CH DE LANGAVANT | F89: PANECHOU | H89: 0262526270 | L89: non | M89: non | O89: =IF(L89="oui","incomplet",IF(OR(J89="non",K89="non"),"a_regulariser",IF(AND(J89="oui",K89="oui"),"ok","")))
A90: 3 | B90: LTS-007 | C90: LTS-007-001 | D90: CASKAVELS | E90: 18 Chemin Alfred Mazérieux | F90: DIJOUX | G90: Sébastien | H90: 0692808959 | L90: non | M90: non | O90: =IF(L90="oui","incomplet",IF(OR(J90="non",K90="non"),"a_regulariser",IF(AND(J90="oui",K90="oui"),"ok","")))
A91: 3 | B91: LTS-007 | C91: LTS-007-002 | D91: CASKAVELS | E91: 30 Chemin Alfred Mazérieux | F91: PICARD | G91: Ignace Clémént | H91: 0692461865 | L91: non | M91: non | O91: =IF(L91="oui","incomplet",IF(OR(J91="non",K91="non"),"a_regulariser",IF(AND(J91="oui",K91="oui"),"ok","")))
A92: 3 | B92: LTS-007 | C92: LTS-007-003 | D92: CASKAVELS | E92: 28 Chemin Alfred Mazérieux | F92: HOARAU | G92: Sheila | H92: 0262302418 | I92: 0693022610 | L92: non | M92: non | O92: =IF(L92="oui","incomplet",IF(OR(J92="non",K92="non"),"a_regulariser",IF(AND(J92="oui",K92="oui"),"ok","")))
A93: 3 | B93: LTS-007 | C93: LTS-007-004 | D93: CASKAVELS | E93: 24 Chemin Alfred Mazérieux | F93: JOSON | G93: Marie Thérèse | L93: non | M93: non | O93: =IF(L93="oui","incomplet",IF(OR(J93="non",K93="non"),"a_regulariser",IF(AND(J93="oui",K93="oui"),"ok","")))
A94: 3 | B94: LTS-007 | C94: LTS-007-005 | D94: CASKAVELS | E94: 26 Chemin Alfred Mazérieux | F94: MAILLOT | G94: René-Claude | H94: 0262647470 | I94: 0692104376 | L94: non | M94: non | O94: =IF(L94="oui","incomplet",IF(OR(J94="non",K94="non"),"a_regulariser",IF(AND(J94="oui",K94="oui"),"ok","")))
A95: 3 | B95: LTS-007 | C95: LTS-007-006 | D95: CASKAVELS | E95: 42 Chemin Alfred Mazérieux | F95: MALAYA | G95: Jean Raymond | H95: 0262305300 | L95: non | M95: non | O95: =IF(L95="oui","incomplet",IF(OR(J95="non",K95="non"),"a_regulariser",IF(AND(J95="oui",K95="oui"),"ok","")))
A96: 3 | B96: LTS-007 | C96: LTS-007-007 | D96: CASKAVELS | E96: 44 Chemin Alfred Mazérieux | F96: MALAYA | G96: Simone | H96: 0262302939 | L96: non | M96: non | O96: =IF(L96="oui","incomplet",IF(OR(J96="non",K96="non"),"a_regulariser",IF(AND(J96="oui",K96="oui"),"ok","")))
A97: 3 | B97: LTS-007 | C97: LTS-007-008 | D97: CASKAVELS | E97: 20 Chemin Alfred Mazérieux | F97: NAZE | G97: Anne Marie Catherine | H97: 0262303814 | I97: 0693909611 | L97: non | M97: non | O97: =IF(L97="oui","incomplet",IF(OR(J97="non",K97="non"),"a_regulariser",IF(AND(J97="oui",K97="oui"),"ok","")))
A98: 3 | B98: LTS-007 | C98: LTS-007-009 | D98: CASKAVELS | E98: 38 Chemin Alfred Mazérieux | F98: TURPIN | G98: Marie Laetitia | H98: 0692181507 | I98: 0262811637 | L98: non | M98: non | O98: =IF(L98="oui","incomplet",IF(OR(J98="non",K98="non"),"a_regulariser",IF(AND(J98="oui",K98="oui"),"ok","")))
A99: 4 | B99: LTS-008 | C99: LTS-008-001 | D99: CLOTILDA | E99: 2 bis Allée des Teks | F99: BATONNET | G99: Jeannine Yvette | H99: 0693300830 | L99: non | M99: non | O99: =IF(L99="oui","incomplet",IF(OR(J99="non",K99="non"),"a_regulariser",IF(AND(J99="oui",K99="oui"),"ok","")))
A100: 4 | B100: LTS-008 | C100: LTS-008-002 | D100: CLOTILDA | E100: 16 Allée des Teks | F100: SALEZ | G100: Catherine | H100: 0693323223 | L100: non | M100: non | O100: =IF(L100="oui","incomplet",IF(OR(J100="non",K100="non"),"a_regulariser",IF(AND(J100="oui",K100="oui"),"ok","")))
...

Sheet Diagnostics
A1: secteur | B1: code_lts | C1: code_acces | D1: tae | E1: spanc | F1: conformite_assainissement | G1: date_controle | H1: observation
A2: 1 | B2: LTS-001 | C2: LTS-001-001 | D2: non | E2: non
A3: 1 | B3: LTS-001 | C3: LTS-001-002 | D3: non | E3: non
A4: 1 | B4: LTS-001 | C4: LTS-001-003 | D4: non | E4: non
A5: 1 | B5: LTS-001 | C5: LTS-001-004 | D5: non | E5: non
A6: 1 | B6: LTS-001 | C6: LTS-001-005 | D6: non | E6: non
A7: 1 | B7: LTS-001 | C7: LTS-001-006 | D7: non | E7: non
A8: 1 | B8: LTS-001 | C8: LTS-001-007 | D8: non | E8: non
A9: 1 | B9: LTS-001 | C9: LTS-001-008 | D9: non | E9: non
A10: 1 | B10: LTS-001 | C10: LTS-001-009 | D10: non | E10: non
A11: 1 | B11: LTS-001 | C11: LTS-001-010 | D11: non | E11: non
A12: 1 | B12: LTS-001 | C12: LTS-001-011 | D12: non | E12: non
A13: 1 | B13: LTS-001 | C13: LTS-001-012 | D13: non | E13: non
... A529: 2 | B529: LTS-034 | C529: LTS-034-015 | D529: oui | E529: non

Sheet Ventes
A1: secteur | B1: code_lts | C1: code_acces | D1: nom_lts | E1: adresse_complete | F1: origine_demande | G1: date_demande | H1: demande_achat | I1: validation_agent | J1: date_validation_agent | K1: vente_autorisee | L1: statut_vente | M1: prix_initial | N1: prix_confirme | O1: date_prix_confirme | P1: cheque_primo_eligible | Q1: cheque_primo_montant | R1: aide_ville | S1: cheque_cinor_eligible | T1: aide_cinor | U1: cheque_cinor_statut | V1: montant_total_aides | W1: prix_final | X1: diag_tae_obligatoire | Y1: diag_tae_statut | Z1: diag_tae_date | AA1: spanc_obligatoire | AB1: spanc_statut | AC1: spanc_date | AD1: statut_vente | AE1: motif_blocage | AF1: notaire | AG1: date_signature_prevue | AH1: date_signature | AI1: statut_paiement | AJ1: date_virement_notaire | AK1: pieces_manquantes | AL1: avancement_dossier | AM1: notification_demande | AN1: notification_suivi | AO1: notification_signature | AP1: notification_realisation | AQ1: date_derniere_notif | AR1: commentaire
A2: 1 | B2: LTS-001 | C2: LTS-001-001 | D2: ALAMANDAS | E2: 15 Bloc 20 Rue des Alamandas | F2: locataire | H2: non | K2: non | N2: non | P2: non | Q2: =IF(P2="oui",MIN(Parametres!$B$4,MAX(Parametres!$B$3,IF(M2="",Parametres!$B$3,ROUND(M2*10%,0)))),"") | R2: non_concerne | S2: non | T2: =IF(S2="oui",Parametres!$B$5,"") | U2: non_concerne | V2: =SUM(Q2,T2) -> 0 | W2: =IF(M2="","",M2-V2) | X2: non | Y2: non_concerne | AA2: non | AB2: non_concerne | AD2: =IF(K2<>"oui","oui",IF(OR(AND(X2="oui",Y2<>"fait"),AND(AA2="oui",AB2<>"fait"),AND(P2="oui",R2<>"valide"),AND(S2="oui",U2<>"valide"),N2<>"oui"),"oui","non")) -> oui | AE2: =IF(K2<>"oui","Résidence ou logement non vendable",IF(AND(X2="oui",Y2<>"fait"),"TAE manquant",IF(AND(AA2="oui",AB2<>"fait"),"SPANC manquant",IF(AND(P2="oui",R2<>"valide"),"Chèque primo non validé",IF(AND(S2="oui",U2<>"valide"),"Chèque CINOR non validé",IF(N2<>"oui","Prix non confirmé","")))))) -> Résidence ou logement non vendable | AI2: non_concerne | AM2: non_concerne | AN2: non_concerne | AO2: non_concerne | AP2: non_concerne
A3: 1 | B3: LTS-001 | C3: LTS-001-002 | D3: ALAMANDAS | E3: 26 Bloc 24 Rue des Alamandas | F3: locataire | H3: non | K3: non | N3: non | P3: non | Q3: =IF(P3="oui",MIN(Parametres!$B$4,MAX(Parametres!$B$3,IF(M3="",Parametres!$B$3,ROUND(M3*10%,0)))),"") | R3: non_concerne | S3: non | T3: =IF(S3="oui",Parametres!$B$5,"") | U3: non_concerne | V3: =SUM(Q3,T3) -> 0 | W3: =IF(M3="","",M3-V3) | X3: non | Y3: non_concerne | AA3: non | AB3: non_concerne | AD3: =IF(K3<>"oui","oui",IF(OR(AND(X3="oui",Y3<>"fait"),AND(AA3="oui",AB3<>"fait"),AND(P3="oui",R3<>"valide"),AND(S3="oui",U3<>"valide"),N3<>"oui"),"oui","non")) -> oui | AE3: =IF(K3<>"oui","Résidence ou logement non vendable",IF(AND(X3="oui",Y3<>"fait"),"TAE manquant",IF(AND(AA3="oui",AB3<>"fait"),"SPANC manquant",IF(AND(P3="oui",R3<>"valide"),"Chèque primo non validé",IF(AND(S3="oui",U3<>"valide"),"Chèque CINOR non validé",IF(N3<>"oui","Prix non confirmé","")))))) -> Résidence ou logement non vendable | AI3: non_concerne | AM3: non_concerne | AN3: non_concerne | AO3: non_concerne | AP3: non_concerne
A4: 1 | B4: LTS-001 | C4: LTS-001-003 | D4: ALAMANDAS | E4: 19 Bloc 22 Rue des Alamandas | F4: locataire | H4: non | K4: non | N4: non | P4: non | Q4: =IF(P4="oui",MIN(Parametres!$B$4,MAX(Parametres!$B$3,IF(M4="",Parametres!$B$3,ROUND(M4*10%,0)))),"") | R4: non_concerne | S4: non | T4: =IF(S4="oui",Parametres!$B$5,"") | U4: non_concerne | V4: =SUM(Q4,T4) -> 0 | W4: =IF(M4="","",M4-V4) | X4: non | Y4: non_concerne | AA4: non | AB4: non_concerne | AD4: =IF(K4<>"oui","oui",IF(OR(AND(X4="oui",Y4<>"fait"),AND(AA4="oui",AB4<>"fait"),AND(P4="oui",R4<>"valide"),AND(S4="oui",U4<>"valide"),N4<>"oui"),"oui","non")) -> oui | AE4: =IF(K4<>"oui","Résidence ou logement non vendable",IF(AND(X4="oui",Y4<>"fait"),"TAE manquant",IF(AND(AA4="oui",AB4<>"fait"),"SPANC manquant",IF(AND(P4="oui",R4<>"valide"),"Chèque primo non validé",IF(AND(S4="oui",U4<>"valide"),"Chèque CINOR non validé",IF(N4<>"oui","Prix non confirmé","")))))) -> Résidence ou logement non vendable | AI4: non_concerne | AM4: non_concerne | AN4: non_concerne | AO4: non_concerne | AP4: non_concerne
A5: 1 | B5: LTS-001 | C5: LTS-001-004 | D5: ALAMANDAS | E5: 27 Bloc 24 Rue des Alamandas | F5: locataire | H5: non | K5: non | N5: non | P5: non | Q5: =IF(P5="oui",MIN(Parametres!$B$4,MAX(Parametres!$B$3,IF(M5="",Parametres!$B$3,ROUND(M5*10%,0)))),"") | R5: non_concerne | S5: non | T5: =IF(S5="oui",Parametres!$B$5,"") | U5: non_concerne | V5: =SUM(Q5,T5) -> 0 | W5: =IF(M5="","",M5-V5) | X5: non | Y5: non_concerne | AA5: non | AB5: non_concerne | AD5: =IF(K5<>"oui","oui",IF(OR(AND(X5="oui",Y5<>"fait"),AND(AA5="oui",AB5<>"fait"),AND(P5="oui",R5<>"valide"),AND(S5="oui",U5<>"valide"),N5<>"oui"),"oui","non")) -> oui | AE5: =IF(K5<>"oui","Résidence ou logement non vendable",IF(AND(X5="oui",Y5<>"fait"),"TAE manquant",IF(AND(AA5="oui",AB5<>"fait"),"SPANC manquant",IF(AND(P5="oui",R5<>"valide"),"Chèque primo non validé",IF(AND(S5="oui",U5<>"valide"),"Chèque CINOR non validé",IF(N5<>"oui","Prix non confirmé","")))))) -> Résidence ou logement non vendable | AI5: non_concerne | AM5: non_concerne | AN5: non_concerne | AO5: non_concerne | AP5: non_concerne
A6: 1 | B6: LTS-001 | C6: LTS-001-005 | D6: ALAMANDAS | E6: 11 Bloc 18 Rue des Alamandas | F6: locataire | H6: non | K6: non | N6: non | P6: non | Q6: =IF(P6="oui",MIN(Parametres!$B$4,MAX(Parametres!$B$3,IF(M6="",Parametres!$B$3,ROUND(M6*10%,0)))),"") | R6: non_concerne | S6: non | T6: =IF(S6="oui",Parametres!$B$5,"") | U6: non_concerne | V6: =SUM(Q6,T6) -> 0 | W6: =IF(M6="","",M6-V6) | X6: non | Y6: non_concerne | AA6: non | AB6: non_concerne | AD6: =IF(K6<>"oui","oui",IF(OR(AND(X6="oui",Y6<>"fait"),AND(AA6="oui",AB6<>"fait"),AND(P6="oui",R6<>"valide"),AND(S6="oui",U6<>"valide"),N6<>"oui"),"oui","non")) -> oui | AE6: =IF(K6<>"oui","Résidence ou logement non vendable",IF(AND(X6="oui",Y6<>"fait"),"TAE manquant",IF(AND(AA6="oui",AB6<>"fait"),"SPANC manquant",IF(AND(P6="oui",R6<>"valide"),"Chèque primo non validé",IF(AND(S6="oui",U6<>"valide"),"Chèque CINOR non validé",IF(N6<>"oui","Prix non confirmé","")))))) -> Résidence ou logement non vendable | AI6: non_concerne | AM6: non_concerne | AN6: non_concerne | AO6: non_concerne | AP6: non_concerne
A7: 1 | B7: LTS-001 | C7: LTS-001-006 | D7: ALAMANDAS | E7: 24 Bloc 22 Rue des Alamandas | F7: locataire | H7: non | K7: non | N7: non | P7: non | Q7: =IF(P7="oui",MIN(Parametres!$B$4,MAX(Parametres!$B$3,IF(M7="",Parametres!$B$3,ROUND(M7*10%,0)))),"") | R7: non_concerne | S7: non | T7: =IF(S7="oui",Parametres!$B$5,"") | U7: non_concerne | V7: =SUM(Q7,T7) -> 0 | W7: =IF(M7="","",M7-V7) | X7: non | Y7: non_concerne | AA7: non | AB7: non_concerne | AD7: =IF(K7<>"oui","oui",IF(OR(AND(X7="oui",Y7<>"fait"),AND(AA7="oui",AB7<>"fait"),AND(P7="oui",R7<>"valide"),AND(S7="oui",U7<>"valide"),N7<>"oui"),"oui","non")) -> oui | AE7: =IF(K7<>"oui","Résidence ou logement non vendable",IF(AND(X7="oui",Y7<>"fait"),"TAE manquant",IF(AND(AA7="oui",AB7<>"fait"),"SPANC manquant",IF(AND(P7="oui",R7<>"valide"),"Chèque primo non validé",IF(AND(S7="oui",U7<>"valide"),"Chèque CINOR non validé",IF(N7<>"oui","Prix non confirmé","")))))) -> Résidence ou logement non vendable | AI7: non_concerne | AM7: non_concerne | AN7: non_concerne | AO7: non_concerne | AP7: non_concerne
A8: 1 | B8: LTS-001 | C8: LTS-001-007 | D8: ALAMANDAS | E8: 12 Bloc 18 Rue des Alamandas | F8: locataire | H8: non | K8: non | N8: non | P8: non | Q8: =IF(P8="oui",MIN(Parametres!$B$4,MAX(Parametres!$B$3,IF(M8="",Parametres!$B$3,ROUND(M8*10%,0)))),"") | R8: non_concerne | S8: non | T8: =IF(S8="oui",Parametres!$B$5,"") | U8: non_concerne | V8: =SUM(Q8,T8) -> 0 | W8: =IF(M8="","",M8-V8) | X8: non | Y8: non_concerne | AA8: non | AB8: non_concerne | AD8: =IF(K8<>"oui","oui",IF(OR(AND(X8="oui",Y8<>"fait"),AND(AA8="oui",AB8<>"fait"),AND(P8="oui",R8<>"valide"),AND(S8="oui",U8<>"valide"),N8<>"oui"),"oui","non")) -> oui | AE8: =IF(K8<>"oui","Résidence ou logement non vendable",IF(AND(X8="oui",Y8<>"fait"),"TAE manquant",IF(AND(AA8="oui",AB8<>"fait"),"SPANC manquant",IF(AND(P8="oui",R8<>"valide"),"Chèque primo non validé",IF(AND(S8="oui",U8<>"valide"),"Chèque CINOR non validé",IF(N8<>"oui","Prix non confirmé","")))))) -> Résidence ou logement non vendable | AI8: non_concerne | AM8: non_concerne | AN8: non_concerne | AO8: non_concerne | AP8: non_concerne
A9: 1 | B9: LTS-001 | C9: LTS-001-008 | D9: ALAMANDAS | E9: 29 Bloc 24 Rue des Alamandas | F9: locataire | H9: non | K9: non | N9: non | P9: non | Q9: =IF(P9="oui",MIN(Parametres!$B$4,MAX(Parametres!$B$3,IF(M9="",Parametres!$B$3,ROUND(M9*10%,0)))),"") | R9: non_concerne | S9: non | T9: =IF(S9="oui",Parametres!$B$5,"") | U9: non_concerne | V9: =SUM(Q9,T9) -> 0 | W9: =IF(M9="","",M9-V9) | X9: non | Y9: non_concerne | AA9: non | AB9: non_concerne | AD9: =IF(K9<>"oui","oui",IF(OR(AND(X9="oui",Y9<>"fait"),AND(AA9="oui",AB9<>"fait"),AND(P9="oui",R9<>"valide"),AND(S9="oui",U9<>"valide"),N9<>"oui"),"oui","non")) -> oui | AE9: =IF(K9<>"oui","Résidence ou logement non vendable",IF(AND(X9="oui",Y9<>"fait"),"TAE manquant",IF(AND(AA9="oui",AB9<>"fait"),"SPANC manquant",IF(AND(P9="oui",R9<>"valide"),"Chèque primo non validé",IF(AND(S9="oui",U9<>"valide"),"Chèque CINOR non validé",IF(N9<>"oui","Prix non confirmé","")))))) -> Résidence ou logement non vendable | AI9: non_concerne | AM9: non_concerne | AN9: non_concerne | AO9: non_concerne | AP9: non_concerne
A10: 1 | B10: LTS-001 | C10: LTS-001-009 | D10: ALAMANDAS | E10: 13 Bloc 20 Rue des Alamandas | F10: locataire | H10: non | K10: non | N10: non | P10: non | Q10: =IF(P10="oui",MIN(Parametres!$B$4,MAX(Parametres!$B$3,IF(M10="",Parametres!$B$3,ROUND(M10*10%,0)))),"") | R10: non_concerne | S10: non | T10: =IF(S10="oui",Parametres!$B$5,"") | U10: non_concerne | V10: =SUM(Q10,T10) -> 0 | W10: =IF(M10="","",M10-V10) | X10: non | Y10: non_concerne | AA10: non | AB10: non_concerne | AD10: =IF(K10<>"oui","oui",IF(OR(AND(X10="oui",Y10<>"fait"),AND(AA10="oui",AB10<>"fait"),AND(P10="oui",R10<>"valide"),AND(S10="oui",U10<>"valide"),N10<>"oui"),"oui","non")) -> oui | AE10: =IF(K10<>"oui","Résidence ou logement non vendable",IF(AND(X10="oui",Y10<>"fait"),"TAE manquant",IF(AND(AA10="oui",AB10<>"fait"),"SPANC manquant",IF(AND(P10="oui",R10<>"valide"),"Chèque primo non validé",IF(AND(S10="oui",U10<>"valide"),"Chèque CINOR non validé",IF(N10<>"oui","Prix non confirmé","")))))) -> Résidence ou logement non vendable | AI10: non_concerne | AM10: non_concerne | AN10: non_concerne | AO10: non_concerne | AP10: non_concerne
A11: 1 | B11: LTS-001 | C11: LTS-001-010 | D11: ALAMANDAS | E11: 25 Bloc 24 Rue des Alamandas | F11: locataire | H11: non | K11: non | N11: non | P11: non | Q11: =IF(P11="oui",MIN(Parametres!$B$4,MAX(Parametres!$B$3,IF(M11="",Parametres!$B$3,ROUND(M11*10%,0)))),"") | R11: non_concerne | S11: non | T11: =IF(S11="oui",Parametres!$B$5,"") | U11: non_concerne | V11: =SUM(Q11,T11) -> 0 | W11: =IF(M11="","",M11-V11) | X11: non | Y11: non_concerne | AA11: non | AB11: non_concerne | AD11: =IF(K11<>"oui","oui",IF(OR(AND(X11="oui",Y11<>"fait"),AND(AA11="oui",AB11<>"fait"),AND(P11="oui",R11<>"valide"),AND(S11="oui",U11<>"valide"),N11<>"oui"),"oui","non")) -> oui | AE11: =IF(K11<>"oui","Résidence ou logement non vendable",IF(AND(X11="oui",Y11<>"fait"),"TAE manquant",IF(AND(AA11="oui",AB11<>"fait"),"SPANC manquant",IF(AND(P11="oui",R11<>"valide"),"Chèque primo non validé",IF(AND(S11="oui",U11<>"valide"),"Chèque CINOR non validé",IF(N11<>"oui","Prix non confirmé","")))))) -> Résidence ou logement non vendable | AI11: non_concerne | AM11: non_concerne | AN11: non_concerne | AO11: non_concerne | AP11: non_concerne
A12: 1 | B12: LTS-001 | C12: LTS-001-011 | D12: ALAMANDAS | E12: 2 Bloc 16 Rue des Alamandas | F12: locataire | H12: non | K12: non | N12: non | P12: non | Q12: =IF(P12="oui",MIN(Parametres!$B$4,MAX(Parametres!$B$3,IF(M12="",Parametres!$B$3,ROUND(M12*10%,0)))),"") | R12: non_concerne | S12: non | T12: =IF(S12="oui",Parametres!$B$5,"") | U12: non_concerne | V12: =SUM(Q12,T12) -> 0 | W12: =IF(M12="","",M12-V12) | X12: non | Y12: non_concerne | AA12: non | AB12: non_concerne | AD12: =IF(K12<>"oui","oui",IF(OR(AND(X12="oui",Y12<>"fait"),AND(AA12="oui",AB12<>"fait"),AND(P12="oui",R12<>"valide"),AND(S12="oui",U12<>"valide"),N12<>"oui"),"oui","non")) -> oui | AE12: =IF(K12<>"oui","Résidence ou logement non vendable",IF(AND(X12="oui",Y12<>"fait"),"TAE manquant",IF(AND(AA12="oui",AB12<>"fait"),"SPANC manquant",IF(AND(P12="oui",R12<>"valide"),"Chèque primo non validé",IF(AND(S12="oui",U12<>"valide"),"Chèque CINOR non validé",IF(N12<>"oui","Prix non confirmé","")))))) -> Résidence ou logement non vendable | AI12: non_concerne | AM12: non_concerne | AN12: non_concerne | AO12: non_concerne | AP12: non_concerne
A13: 1 | B13: LTS-001 | C13: LTS-001-012 | D13: ALAMANDAS | E13: 4 Bloc 16 Rue des Alamandas | F13: locataire | H13: non | K13: non | N13: non | P13: non | Q13: =IF(P13="oui",MIN(Parametres!$B$4,MAX(Parametres!$B$3,IF(M13="",Parametres!$B$3,ROUND(M13*10%,0)))),"") | R13: non_concerne | S13: non | T13: =IF(S13="oui",Parametres!$B$5,"") | U13: non_concerne | V13: =SUM(Q13,T13) -> 0 | W13: =IF(M13="","",M13-V13) | X13: non | Y13: non_concerne | AA13: non | AB13: non_concerne | AD13: =IF(K13<>"oui","oui",IF(OR(AND(X13="oui",Y13<>"fait"),AND(AA13="oui",AB13<>"fait"),AND(P13="oui",R13<>"valide"),AND(S13="oui",U13<>"valide"),N13<>"oui"),"oui","non")) -> oui | AE13: =IF(K13<>"oui","Résidence ou logement non vendable",IF(AND(X13="oui",Y13<>"fait"),"TAE manquant",IF(AND(AA13="oui",AB13<>"fait"),"SPANC manquant",IF(AND(P13="oui",R13<>"valide"),"Chèque primo non validé",IF(AND(S13="oui",U13<>"valide"),"Chèque CINOR non validé",IF(N13<>"oui","Prix non confirmé","")))))) -> Résidence ou logement non vendable | AI13: non_concerne | AM13: non_concerne | AN13: non_concerne | AO13: non_concerne | AP13: non_concerne
... A529: 2 | B529: LTS-034 | C529: LTS-034-015 | D529: VANGASSAYES | E529: 5 Allée des Fougères | F529: locataire | H529: non | K529: oui | N529: non | P529: oui | Q529: =IF(P529="oui",MIN(Parametres!$B$4,MAX(Parametres!$B$3,IF(M529="",Parametres!$B$3,ROUND(M529*10%,0)))),"") -> 0 | R529: a_instruire | S529: oui | T529: =IF(S529="oui",Parametres!$B$5,"") -> 500 | U529: a_instruire | V529: =SUM(Q529,T529) -> 500 | W529: =IF(M529="","",M529-V529) | X529: oui | Y529: a_faire | AA529: non | AB529: non_concerne | AD529: =IF(K529<>"oui","oui",IF(OR(AND(X529="oui",Y529<>"fait"),AND(AA529="oui",AB529<>"fait"),AND(P529="oui",R529<>"valide"),AND(S529="oui",U529<>"valide"),N529<>"oui"),"oui","non")) -> oui | AE529: =IF(K529<>"oui","Résidence ou logement non vendable",IF(AND(X529="oui",Y529<>"fait"),"TAE manquant",IF(AND(AA529="oui",AB529<>"fait"),"SPANC manquant",IF(AND(P529="oui",R529<>"valide"),"Chèque primo non validé",IF(AND(S529="oui",U529<>"valide"),"Chèque CINOR non validé",IF(N529<>"oui","Prix non confirmé","")))))) -> TAE manquant | AI529: non_concerne | AM529: a_notifier | AN529: a_notifier | AO529: a_notifier | AP529: a_notifier

Sheet Travaux
